Workbook

Sheet ex2024
A1: UF | B1: Estatal | C1: Sigla | D1: CNPJ | E1: Situação | F1: Setor | G1: Espécie | H1: Organização jurídica | I1: Tipo de Capital | J1: Listada em Bolsa | K1: É Subsidiária | L1: Dependência | M1: Número de Empregados (incluindo temporários e terceirizados) | N1: Possui Conselho de Administração | O1: Possui Conselho Fiscal | P1: Possui Comitê de Autidoria | Q1: Link Carta Anual | R1: Receita Líquida Operacional | S1: Despesa com Pessoal, incluindo temporários e terceirizados (por competência) | T1: Despesa Total (por competência) | U1: Investimento (por competência) | V1: Foi Distribuído PLR ou RVA no exercício | W1: Remuneração bruta total paga no ano (empregado que recebeu a maior remuneração) | X1: PLR ou RVA pagos no ano (empregado que recebeu a maior remuneração) | Y1: Indenizações pagas no ano (empregado que recebeu a maior remuneração) | Z1: Lucro / Prejuízo Líquido do Exercício | AA1: Patrimônio Líquido | AB1: Valor de Mercado | AC1: Dividendos e Juros sobre Capital Próprio pagos ao Tesouro Estadual / Municipal (pago) | AD1: Subvenções - Exercício anterior | AE1: Subvenções - Exercício | AF1: Passivos - Exercício anterior | AG1: Passivos - exercício | AH1: Reforço de Capital - Exercício anterior | AI1: Reforço de Capital - Exercício | AJ1: Ações ou cotas - Exercício anterior | AK1: Ações ou cotas - Exercício | AL1: Capital Social Integralizado - Exercício anterior | AM1: Capital Social Integralizado - Exercício | AN1: Capital Social a Integralizar -Exercício anterior | AO1: Capital Social a Integralizar - Exercício | AP1: Rentabilidade
A2: AC | B2: Empresa de Processamento de Dados do Acre - ACREDATA | C2: ACREDATA | D2: 04.088.985/0001-00 | E2: ATIVA | F2: INFORMÁTICA E TECNOLOGIA DA INFORMAÇÃO | G2: EMPRESA PÚBLICA | H2: S.A. | I2: FECHADO | J2: NÃO | K2: NÃO | L2: DEPENDENTE | M2: 84 | N2: SIM | O2: SIM | P2: NÃO | R2: 13107416 | S2: 6325167.2 | T2: 13107416 | U2: 0 | V2: SIM | W2: 0 | X2: 0 | Y2: 0 | Z2: 11811972 | AA2: 1.037203e+08 | AB2: 0 | AC2: 0 | AD2: 11684206 | AE2: 13107416 | AF2: 0 | AG2: 0 | AH2: 0 | AI2: 0 | AJ2: 4396687.6 | AK2: 4396687.6 | AL2: 4396687.6 | AM2: 4396687.6 | AN2: 0 | AO2: 0 | AP2: =Z2*100/AA2 -> 11.388293
A3: AC | B3: Agencia de Negócios do Estado do Acre - ANAC | C3: ANAC | D3: 05.899.982/0001-19 | E3: ATIVA | F3: OUTROS | G3: SOCIEDADE DE ECONOMIA MISTA | H3: S.A. | I3: FECHADO | J3: NÃO | K3: NÃO | L3: DEPENDENTE | M3: 12 | N3: SIM | O3: SIM | P3: NÃO | R3: 8531737.6 | S3: 7155806.2 | T3: 10314428 | U3: 0 | V3: NÃO | W3: 407932.32 | X3: 0 | Y3: 99128.6 | Z3: -10051186 | AA3: 39712876 | AB3: 0 | AC3: 0 | AD3: 0 | AE3: 0 | AF3: 0 | AG3: 0 | AH3: 5563422.4 | AI3: 8531737.6 | AJ3: 0 | AK3: 0 | AL3: 1.5620548e+08 | AM3: 1.6473722e+08 | AN3: 3794518.8 | AO3: 9762781.2 | AP3: =Z3*100/AA3 -> -25.309639
A4: AC | B4: Administradora da Zona de Processamento de Exportação do Acre - AZPE/AC | C4: AZPE | D4: 12.467.990/0001-51 | E4: ATIVA | F4: DESENVOLVIMENTO REGIONAL | G4: SOCIEDADE DE ECONOMIA MISTA | H4: S.A. | I4: FECHADO | J4: NÃO | K4: NÃO | L4: DEPENDENTE | M4: 0 | N4: SIM | O4: SIM | P4: NÃO | R4: 0 | S4: 0 | T4: 0 | U4: 0 | V4: NÃO | W4: 0 | X4: 0 | Y4: 0 | Z4: 0 | AA4: 0 | AB4: 0 | AC4: 0 | AD4: 0 | AE4: 0 | AF4: 0 | AG4: 0 | AH4: 0 | AI4: 0 | AJ4: 0 | AK4: 0 | AL4: 0 | AM4: 0 | AN4: 0 | AO4: 0 | AP4: =Z4*100/AA4 -> #DIV/0!
A5: AC | B5: Banco do Estado do Acre - BANACRE | C5: BANACRE | D5: 04.064.077/0001-86 | E5: EM LIQUIDAÇÃO | F5: FINANCEIRO | G5: SOCIEDADE DE ECONOMIA MISTA | H5: S.A. | I5: FECHADO | J5: NÃO | K5: NÃO | L5: DEPENDENTE | M5: 12 | N5: SIM | O5: SIM | P5: NÃO | R5: 1776184.3 | S5: 1444341.2 | T5: 1643842.5 | U5: 2348.39 | V5: NÃO | W5: 109184.47 | X5: 0 | Y5: 0 | Z5: -2514600.7 | AA5: -1.9934195e+08 | AB5: 0 | AC5: 0 | AD5: 1780362.8 | AE5: 1774049 | AF5: 0 | AG5: 0 | AH5: 0 | AI5: 0 | AJ5: 0 | AK5: 0 | AL5: 24365821 | AM5: 24365821 | AN5: 0 | AO5: 0 | AP5: =Z5*100/AA5 -> 1.2614508
A6: AC | B6: Companhia de Armazéns e Entrepostos do Acre - CAGEACRE | C6: CAGEACRE | D6: 04.043.493/0001-06 | E6: ATIVA | F6: ABASTECIMENTO DE ALIMENTOS E OUTROS INSUMOS | G6: EMPRESA PÚBLICA | H6: OUTRAS | I6: FECHADO | J6: NÃO | K6: NÃO | L6: DEPENDENTE | M6: 155 | N6: NÃO | O6: SIM | P6: NÃO | R6: 14729465 | S6: 13419884 | T6: 14759182 | U6: 0 | V6: NÃO | W6: 215350.25 | X6: 0 | Y6: 548258.13 | Z6: 678045.71 | AA6: 7447035.2 | AB6: 0 | AC6: 0 | AD6: 19543507 | AE6: 14729465 | AF6: 305753.42 | AG6: 170846.03 | AH6: 0 | AI6: 0 | AJ6: 727.45 | AK6: 727.45 | AL6: 8219091 | AM6: 8219091 | AN6: 0 | AO6: 0 | AP6: =Z6*100/AA6 -> 9.1049081
A7: AC | B7: Companhia Agência de Desenvolvimento e Serviços Ambientais do Estado do Acre - CDSA | C7: CDSA | D7: 16.864.341/0001-45 | E7: ATIVA | F7: DESENVOLVIMENTO REGIONAL | G7: SOCIEDADE DE ECONOMIA MISTA | H7: S.A. | I7: FECHADO | J7: NÃO | K7: NÃO | L7: DEPENDENTE | M7: 13 | N7: SIM | O7: SIM | P7: NÃO | R7: 1521027 | S7: 1483227 | T7: 1483227 | U7: 0 | V7: NÃO | W7: 233705.73 | X7: 0 | Y7: 0 | Z7: -24631.91 | AA7: 3.0056081e+09 | AB7: 0 | AC7: 0 | AD7: 957768.34 | AE7: 1521027 | AF7: 973545.94 | AG7: 1483227 | AH7: 2447100 | AI7: 2400000 | AJ7: 3003209100 | AK7: 3005609100 | AL7: 3003209100 | AM7: 3005609100 | AN7: 3397100 | AO7: 997100 | AP7: =Z7*100/AA7 -> -0.00081953166
A8: AC | B8: Companhia Industrial de Laticínios do Acre - CILA | C8: CILA | D8: 04.061.693/0001-83 | E8: ATIVA | F8: ABASTECIMENTO DE ALIMENTOS E OUTROS INSUMOS | G8: EMPRESA PÚBLICA | H8: S.A. | I8: FECHADO | J8: NÃO | K8: SIM | L8: DEPENDENTE | M8: 29 | N8: SIM | O8: SIM | P8: NÃO | R8: 2820871.2 | S8: 2497093.8 | T8: 2820871.2 | U8: 1686.87 | V8: NÃO | W8: 2183003.7 | X8: 0 | Y8: 0 | Z8: 142443.37 | AA8: -88773663 | AB8: 0 | AC8: 0 | AD8: 2317412.3 | AE8: 2820871.2 | AF8: 2147999.3 | AG8: 1996951.8 | AH8: 0 | AI8: 0 | AJ8: 0 | AK8: 0 | AL8: 416.44 | AM8: 416.44 | AN8: 0 | AO8: 0 | AP8: =Z8*100/AA8 -> -0.16045679
A9: AC | B9: Companhia de Desenvolvimento Industrial do Acre - CODISACRE | C9: CODISACRE | D9: 04.039.277/0001-89 | E9: ATIVA | F9: DESENVOLVIMENTO REGIONAL | G9: EMPRESA PÚBLICA | H9: OUTRAS | I9: FECHADO | J9: NÃO | K9: SIM | L9: DEPENDENTE | M9: 37 | N9: SIM | O9: SIM | P9: NÃO | R9: 5026604.3 | S9: 3944525.1 | T9: 5010921 | U9: 244185.81 | V9: NÃO | W9: 198405.6 | X9: 0 | Y9: 0 | Z9: 693377.74 | AA9: 6665321.6 | AB9: 0 | AC9: 0 | AD9: 4779201.4 | AE9: 5010921 | AF9: 410259.38 | AG9: 397316.62 | AH9: 0 | AI9: 0 | AJ9: 0 | AK9: 0 | AL9: 3791691 | AM9: 3791691 | AN9: 0 | AO9: 0 | AP9: =Z9*100/AA9 -> 10.402765
A10: AC | B10: Companhia de Habitação do Acre - COHAB/ACRE | C10: COHAB | D10: 04.066.007/0001-67 | E10: ATIVA | F10: HABITAÇÃO E URBANIZAÇÃO | G10: SOCIEDADE DE ECONOMIA MISTA | H10: OUTRAS | I10: FECHADO | J10: NÃO | K10: NÃO | L10: DEPENDENTE | M10: 63 | N10: SIM | O10: SIM | P10: NÃO | R10: 7431327.1 | S10: 6325167.2 | T10: 9499084.6 | U10: 0 | V10: NÃO | W10: 270124.92 | X10: 0 | Y10: 0 | Z10: 3953141.1 | AA10: 79307669 | AB10: 0 | AC10: 0 | AD10: 6949505.2 | AE10: 8771679.9 | AF10: 8064674.4 | AG10: 7204783.3 | AH10: 0 | AI10: 0 | AJ10: 0.99 | AK10: 0.99 | AL10: 62840607 | AM10: 62840607 | AN10: 0 | AO10: 0 | AP10: =Z10*100/AA10 -> 4.9845635
A11: AC | B11: Companhia de Colonização do Acre - COLONACRE | C11: COLONACRE | D11: 04.039.673/0001-06 | E11: EM LIQUIDAÇÃO | F11: DESENVOLVIMENTO REGIONAL | G11: EMPRESA PÚBLICA | H11: OUTRAS | I11: FECHADO | J11: NÃO | K11: SIM | L11: DEPENDENTE | M11: 17 | N11: NÃO | O11: SIM | P11: NÃO | R11: 1705223.6 | S11: 1658046.4 | T11: 1658621.4 | U11: 0 | V11: NÃO | W11: 1040941.4 | X11: 0 | Y11: 0 | Z11: 46963.39 | AA11: 5690130.8 | AB11: 0 | AC11: 0 | AD11: 1397964.1 | AE11: 1705223.6 | AF11: 0 | AG11: 0 | AH11: 0 | AI11: 0 | AJ11: 3958917.2 | AK11: 3595917.2 | AL11: 3598917.2 | AM11: 3598917.2 | AN11: 0 | AO11: 0 | AP11: =Z11*100/AA11 -> 0.82534816
A12: AC | B12: Empresa de Assistência Técnica e Extensão Rural do Acre - EMATER | C12: EMATER | D12: 04.044.244/0001-27 | E12: ATIVA | F12: PESQUISA E ASSISTÊNCIA TÉCNICA AGROPECUÁRIA | G12: EMPRESA PÚBLICA | H12: OUTRAS | I12: FECHADO | J12: NÃO | K12: NÃO | L12: DEPENDENTE | M12: 152 | N12: SIM | O12: SIM | P12: NÃO | R12: 23737121 | S12: 18707804 | T12: 22994301 | U12: 0 | V12: NÃO | W12: 349852.72 | X12: 0 | Y12: 5040 | Z12: 167735.68 | AA12: -8249.79 | AB12: 0 | AC12: 0 | AD12: 21676919 | AE12: 23737121 | AF12: 0 | AG12: 0 | AH12: 2052870.8 | AI12: 2149510.2 | AJ12: 0 | AK12: 0 | AL12: 0 | AM12: 0 | AN12: 0 | AO12: 0 | AP12: =Z12*100/AA12 -> -2033.2115
A13: AC | B13: Companhia de Saneamento do Acre - SANACRE | C13: SANACRE | D13: 04.003.232/0001-54 | E13: ATIVA | F13: SANEAMENTO | G13: SOCIEDADE DE ECONOMIA MISTA | H13: OUTRAS | I13: FECHADO | J13: NÃO | K13: NÃO | L13: DEPENDENTE | M13: 189 | N13: SIM | O13: SIM | P13: NÃO | R13: 0 | S13: 22880993 | T13: 22972686 | U13: 0 | V13: NÃO | W13: 0 | X13: 0 | Y13: 0 | Z13: 91692.53 | AA13: 19805481 | AB13: 0 | AC13: 0 | AD13: 3364776.2 | AE13: 3547857.4 | AF13: 0 | AG13: 0 | AH13: 0 | AI13: 0 | AJ13: 0 | AK13: 0 | AL13: 0 | AM13: 0 | AN13: 0 | AO13: 0 | AP13: =Z13*100/AA13 -> 0.46296543
A14: AL | B14: Agência de Fomento de Alagoas - Desenvolve | C14: AFAL | D14: 10.769.660/0001-95 | E14: ATIVA | F14: FINANCEIRO | G14: SOCIEDADE DE ECONOMIA MISTA | H14: S.A. | I14: FECHADO | J14: NÃO | K14: SIM | L14: DEPENDENTE | M14: 57 | N14: SIM | O14: SIM | P14: NÃO | R14: -7615000 | S14: 651000 | T14: 8475000 | U14: 0 | V14: NÃO | W14: 119587 | X14: 0 | Y14: 0 | Z14: -7444000 | AA14: 45079000 | AC14: 0 | AD14: 0 | AE14: 0 | AF14: 0 | AG14: 0 | AH14: 0 | AI14: 0 | AJ14: 8041 | AK14: 8041 | AL14: 80414000 | AM14: 80414000 | AN14: 0 | AO14: 0 | AP14: =Z14*100/AA14 -> -16.513232
A15: AL | B15: Companhia Alagoana de Recursos Humanos e Patrimoniais | C15: CARHP | D15: 12.291.274/0001-66 | E15: EM LIQUIDAÇÃO | F15: HABITAÇÃO E URBANIZAÇÃO | G15: SOCIEDADE DE ECONOMIA MISTA | H15: S.A. | I15: FECHADO | J15: NÃO | K15: NÃO | L15: DEPENDENTE | M15: 1 | N15: NÃO | O15: SIM | P15: NÃO | R15: 918583.9 | S15: 16778.87 | T15: 376826.32 | U15: 323632.27 | V15: NÃO | W15: 218125.31 | X15: 0 | Y15: 0 | Z15: -22558098 | AA15: 19491992 | AC15: 0 | AD15: 5776972.9 | AE15: 2734522 | AF15: 1.0955497e+08 | AG15: 1.0961923e+08 | AH15: 0 | AI15: 0 | AJ15: 0 | AK15: 0 | AL15: 20251521 | AM15: 20251521 | AN15: 0 | AO15: 0 | AP15: =Z15*100/AA15 -> -115.73008
A16: AL | B16: Laboratório Industrial Farmacêutico | C16: LIFAL | D16: 12.343.158/0001-43 | E16: EM LIQUIDAÇÃO | F16: SAÚDE | G16: SOCIEDADE DE ECONOMIA MISTA | H16: S.A. | I16: FECHADO | J16: NÃO | K16: NÃO | L16: DEPENDENTE | M16: 0 | N16: NÃO | O16: SIM | P16: NÃO | R16: 416573.91 | S16: 4793.94 | T16: 4793.94 | U16: 0 | V16: NÃO | W16: 62321.22 | X16: 0 | Y16: 152320.29 | Z16: 86544.66 | AA16: -50970.82 | AC16: 0 | AD16: 354932.54 | AE16: 430375.27 | AF16: 837615.8 | AG16: 837615.8 | AH16: 0 | AI16: 0 | AJ16: 0 | AK16: 0 | AL16: 0 | AM16: 0 | AN16: 0 | AO16: 0 | AP16: =Z16*100/AA16 -> -169.79256
A17: AL | B17: Banco do Estado de Alagoas S.A | C17: PRODUBAN | D17: 12.275.749/0001-20 | E17: EM LIQUIDAÇÃO | F17: FINANCEIRO | G17: SOCIEDADE DE ECONOMIA MISTA | H17: S.A. | I17: FECHADO | J17: NÃO | K17: NÃO | L17: DEPENDENTE | M17: 3 | N17: NÃO | O17: SIM | P17: NÃO | R17: 538686.32 | S17: 554179.85 | T17: 20349597 | U17: 0 | V17: NÃO | W17: 325324.89 | X17: 0 | Y17: 0 | Z17: -20349597 | AA17: 1.2073279e+08 | AC17: 0 | AD17: 100000 | AE17: 100000 | AF17: 0 | AG17: 0 | AH17: 0 | AI17: 16000000 | AJ17: 6750 | AK17: 6750 | AL17: 4.998111e+08 | AM17: 4.998111e+08 | AN17: 0 | AO17: 0 | AP17: =Z17*100/AA17 -> -16.855071
A18: AL | B18: Serviços de Engenharia de Alagoas S.A | C18: SERVEAL | D18: 12.318.887/0001-40 | E18: EM LIQUIDAÇÃO | F18: OUTROS | G18: SOCIEDADE DE ECONOMIA MISTA | H18: S.A. | I18: FECHADO | J18: NÃO | K18: NÃO | L18: DEPENDENTE | M18: 5 | N18: NÃO | O18: SIM | P18: NÃO | R18: 539804.76 | S18: 41523.44 | T18: 42358.91 | U18: 0 | V18: NÃO | W18: 539804.72 | X18: 0 | Y18: 0 | Z18: 0 | AA18: -1653049.8 | AC18: 0 | AD18: 1018063.9 | AE18: 387314.54 | AF18: 3889423.1 | AG18: 3855251.4 | AH18: 0 | AI18: 0 | AJ18: 0 | AK18: 0 | AL18: -505486.95 | AM18: -505486.95 | AN18: 0 | AO18: 0 | AP18: =Z18*100/AA18 -> 0
A19: AL | B19: Alagoas Ativos S.A | C19: ALAtivos | D19: 29.218.037/0001-72 | E19: ATIVA | F19: GESTÃO DE ATIVOS | G19: EMPRESA PÚBLICA | H19: S.A. | I19: FECHADO | J19: NÃO | K19: NÃO | L19: NÃO DEPENDENTE | M19: 19 | N19: SIM | O19: SIM | P19: NÃO | R19: 5313174.6 | S19: 2192507.7 | T19: 7586434.2 | U19: 0 | V19: NÃO | W19: 405711.63 | X19: 0 | Y19: 0 | Z19: 646243.59 | AA19: 1354881.7 | AC19: 0 | AD19: 0 | AE19: 0 | AF19: 0 | AG19: 0 | AH19: 0 | AI19: 0 | AJ19: 0 | AK19: 0 | AL19: 10000000 | AM19: 0 | AN19: 0 | AO19: 0 | AP19: =Z19*100/AA19 -> 47.697419
A20: AL | B20: Gás de Alagoas S.A | C20: ALGÁS | D20: 69.983.484/0001-32 | E20: ATIVA | F20: GÁS E DERIVADOS | G20: SOCIEDADE DE ECONOMIA MISTA | H20: S.A. | I20: FECHADO | J20: NÃO | K20: NÃO | L20: NÃO DEPENDENTE | M20: 161 | N20: SIM | O20: SIM | P20: SIM | Q20: https://governanca,algas,com,br/carta-anual-de-politicas-publicas-e-governanca-corporativa | R20: 4.5279713e+08 | S20: 25539770 | T20: 4.5719368e+08 | U20: 34430658 | V20: NÃO | W20: 398267.27 | X20: 0 | Y20: 0 | Z20: 40882910 | AA20: 1.4065218e+08 | AC20: 10638724 | AD20: 0 | AE20: 0 | AF20: 0 | AG20: 0 | AH20: 0 | AI20: 0 | AJ20: 2873893 | AK20: 3212493.4 | AL20: 23729600 | AM20: 26525400 | AN20: 0 | AO20: 0 | AP20: =Z20*100/AA20 -> 29.066674
A21: AL | B21: Companhia de Saneamento de Alagoas | C21: CASAL | D21: 12.294.708/0001-81 | E21: ATIVA | F21: SANEAMENTO | G21: SOCIEDADE DE ECONOMIA MISTA | H21: S.A. | I21: FECHADO | J21: NÃO | K21: NÃO | L21: NÃO DEPENDENTE | M21: 856 | N21: SIM | O21: SIM | P21: SIM | Q21: https://www,casal,al,gov,br/arquivos/carta-anual-de-politicas-publicas-e-governanca-corporativa-2024/ | R21: 464911233 | S21: 109360615 | T21: 5.4383181e+08 | U21: 11453707 | V21: NÃO | W21: 475077.99 | X21: 0 | Y21: 23628.57 | Z21: 76660074 | AA21: 6571826958 | AC21: 0 | AD21: 0 | AE21: 0 | AF21: 0 | AG21: 0 | AH21: 44880272 | AI21: 51271902 | AJ21: 1.364436e+09 | AK21: 1.364436e+09 | AL21: 4.6968194e+08 | AM21: 5.2557004e+08 | AN21: 2.8769973e+08 | AO21: 2.3181163e+08 | AP21: =Z21*100/AA21 -> 1.1664956
A22: AL | B22: Companhia de Edição Impressão e Publicação de Alagoas | C22: CEPAL | D22: 04.308.836/0001-09 | E22: ATIVA | F22: COMUNICAÇÃO | G22: SOCIEDADE DE ECONOMIA MISTA | H22: S.A. | I22: FECHADO | J22: NÃO | K22: NÃO | L22: NÃO DEPENDENTE | M22: 119 | N22: SIM | O22: SIM | P22: NÃO | Q22: https://www,imprensaoficial,al,gov,br/storage/files/2025/04/Carta_Anual_de_Políticas_Públicas_CEPAL_Aprovada_Conselho_2024,pdf | R22: 17985778 | S22: 12885086 | T22: 20957137 | U22: 0 | V22: NÃO | W22: 298779.51 | X22: 0 | Y22: 0 | Z22: -5899240.4 | AA22: 217370.56 | AC22: 0 | AD22: 0 | AE22: 0 | AF22: 0 | AG22: 0 | AH22: 0 | AI22: 0 | AJ22: 10083000 | AK22: 10083000 | AL22: 10083000 | AM22: 10083000 | AN22: 0 | AO22: 0 | AP22: =Z22*100/AA22 -> -2713.9096
A23: AM | B23: Agência de Desenvolvimento Sustentável do Amazonas | C23: ADS | D23: 05.867.581/0001-87 | E23: ATIVA | F23: DESENVOLVIMENTO REGIONAL | G23: EMPRESA PÚBLICA | H23: S.A. | I23: FECHADO | J23: NÃO | K23: NÃO | L23: DEPENDENTE | M23: 83 | N23: SIM | O23: SIM | P23: NÃO | Q23: Não possui | R23: 1890024 | S23: 4164370.4 | T23: 1.3566569e+08 | U23: 0 | V23: NÃO | W23: 180416.58 | X23: 0 | Y23: 133966.4 | Z23: -4743532 | AA23: 795178.7 | AB23: 0 | AC23: 0 | AD23: 1.0214802e+08 | AE23: 1.2582989e+08 | AF23: 0 | AG23: 0 | AH23: 0 | AI23: 0 | AJ23: 0 | AK23: 0 | AL23: 10000000 | AM23: 10000000 | AN23: 0 | AO23: 0 | AP23: =Z23*100/AA23 -> -596.5366
A24: AM | B24: Empresa Estadual de Turismo | C24: AMAZONASTUR | D24: 05.662.046/0001-90 | E24: ATIVA | F24: TURISMO | G24: EMPRESA PÚBLICA | H24: OUTRAS | I24: FECHADO | J24: NÃO | K24: NÃO | L24: DEPENDENTE | M24: 144 | N24: SIM | O24: SIM | P24: SIM | Q24: https://www,amazonastur,am,gov,br/wpcontent/ uploads/2024/10/amazonastur-cartaservicos- 2024,pdf | R24: 631607.64 | S24: 13648435 | T24: 1.0485808e+08 | U24: 38772283 | V24: NÃO | W24: 407740 | X24: 0 | Y24: 0 | Z24: -803617.85 | AA24: 4189166.1 | AB24: 0 | AC24: 0 | AD24: 71978546 | AE24: 1.0425863e+08 | AF24: 2807045.4 | AG24: 6734566.2 | AH24: 0 | AI24: 0 | AJ24: 1 | AK24: 1 | AL24: 27123375 | AM24: 27123375 | AN24: 0 | AO24: 0 | AP24: =Z24*100/AA24 -> -19.183242
A25: AM | B25: Cia. de Desenvolvimento do Estado do Amazonas | C25: CIAMA | D25: 00.624.961/0001-77 | E25: ATIVA | F25: DESENVOLVIMENTO REGIONAL | G25: SOCIEDADE DE ECONOMIA MISTA | H25: S.A. | I25: FECHADO | J25: NÃO | K25: NÃO | L25: DEPENDENTE | M25: 191 | N25: SIM | O25: SIM | P25: NÃO | Q25: www,ciama,am,gov,br | R25: 0 | S25: 30883607 | T25: 35833134 | U25: 0 | V25: NÃO | W25: 758106.55 | X25: 0 | Y25: 6500 | Z25: -18991279 | AA25: 53266635 | AB25: 0 | AC25: 0 | AD25: 30817836 | AE25: 17074546 | AF25: 0 | AG25: 0 | AH25: 0 | AI25: 16526312 | AJ25: 62880631 | AK25: 66058773 | AL25: 3.2697928e+08 | AM25: 3.4350559e+08 | AN25: 49020720 | AO25: 32494407 | AP25: =Z25*100/AA25 -> -35.653235
A26: AM | B26: Cia. de Saneamento do Amazonas | C26: COSAMA | D26: 04.406.195/0001-25 | E26: ATIVA | F26: SANEAMENTO | G26: SOCIEDADE DE ECONOMIA MISTA | H26: S.A. | I26: FECHADO | J26: NÃO | K26: NÃO | L26: DEPENDENTE | M26: 522 | N26: SIM | O26: SIM | P26: NÃO | Q26: Não foi publicada carta anual, | R26: 73990521 | S26: 45340671 | T26: 83896774 | U26: 4303097.2 | V26: NÃO | W26: 469688.87 | X26: 0 | Y26: 4525.34 | Z26: -8231341.9 | AA26: -22972209 | AB26: 0 | AC26: 0 | AD26: 47283701 | AE26: 49576266 | AF26: 0 | AG26: 0 | AH26: 4042877 | AI26: 1290000 | AJ26: 22094870827 | AK26: 22094870827 | AL26: 5.3386274e+08 | AM26: 5.3386274e+08 | AN26: 0 | AO26: 0 | AP26: =Z26*100/AA26 -> 35.831739
A27: AM | B27: Agência de Fomento do Estado do Amazonas | C27: AFEAM | D27: 03.183.937/0001-38 | E27: ATIVA | F27: FINANCEIRO | G27: EMPRESA PÚBLICA | H27: S.A. | I27: FECHADO | J27: NÃO | K27: NÃO | L27: NÃO DEPENDENTE | M27: 253 | N27: SIM | O27: SIM | P27: SIM | Q27: https://www,afeam,am,gov,br/wpcontent/ uploads/2025/04/CARTAANUAL¿ 2024,pdf | R27: 26835089 | S27: 50347133 | T27: 3.723726e+08 | U27: 3.2202546e+08 | V27: NÃO | W27: 567085.72 | X27: 0 | Y27: 34305.43 | Z27: 14463130 | AA27: 1.2578599e+08 | AB27: 0 | AC27: 0 | AD27: 0 | AE27: 0 | AF27: 0 | AG27: 0 | AH27: 0 | AI27: 0 | AJ27: 103963256 | AK27: 106465046 | AL27: 103963256 | AM27: 106465046 | AN27: 0 | AO27: 0 | AP27: =Z27*100/AA27 -> 11.498204
A28: AM | B28: Cia. Amazonense de Desenvolvimento e Mobilização de Ativos | C28: CADA | D28: 40.182.478/0001-02 | E28: ATIVA | F28: GESTÃO DE ATIVOS | G28: EMPRESA PÚBLICA | H28: S.A. | I28: FECHADO | J28: NÃO | K28: NÃO | L28: NÃO DEPENDENTE | M28: 26 | N28: SIM | O28: SIM | P28: SIM | Q28: https://www,cada,am,gov,br/wpcontent/uploads/2025/02/Carta-Anual-2025-Data-Base-2024,pdf | R28: 765121 | S28: 4383063 | T28: 4974652 | U28: 0 | V28: NÃO | W28: 439200 | X28: 0 | Y28: 6500 | Z28: 6811743 | AA28: 153408 | AB28: 0 | AC28: 0 | AD28: 0 | AE28: 0 | AF28: 0 | AG28: 0 | AH28: 6000000 | AI28: 4000000 | AJ28: 15000000 | AK28: 19000000 | AL28: 15000000 | AM28: 19000000 | AN28: 0 | AO28: 0 | AP28: =Z28*100/AA28 -> 4440.2789
A29: AM | B29: Cia. de Gás do Amazonas | C29: CIGAS | D29: 00.624.964/0001-00 | E29: ATIVA | F29: GÁS E DERIVADOS | G29: SOCIEDADE DE ECONOMIA MISTA | H29: S.A. | I29: FECHADO | J29: NÃO | K29: NÃO | L29: NÃO DEPENDENTE | M29: 230 | N29: SIM | O29: SIM | P29: NÃO | Q29: https://www,cigas-am,com,br/relatorio-de-sustentabilidade | R29: 3.5530374e+09 | S29: 2056766.3 | T29: 3.3761082e+09 | U29: 22339240 | V29: SIM | W29: 765000 | X29: 45000 | Y29: 14048 | Z29: 1.9728408e+08 | AA29: 5.0508971e+08 | AB29: 0 | AC29: 11365846 | AD29: 0 | AE29: 0 | AF29: 0 | AG29: 0 | AH29: 0 | AI29: 0 | AJ29: 12059543 | AK29: 12059543 | AL29: 45042129 | AM29: 58100045 | AN29: 0 | AO29: 0 | AP29: =Z29*100/AA29 -> 39.059216
A30: AM | B30: Processamento de Dados do Amazonas | C30: PRODAM | D30: 04.407.920/0001-80 | E30: ATIVA | F30: INFORMÁTICA E TECNOLOGIA DA INFORMAÇÃO | G30: SOCIEDADE DE ECONOMIA MISTA | H30: S.A. | I30: FECHADO | J30: NÃO | K30: NÃO | L30: NÃO DEPENDENTE | M30: 446 | N30: SIM | O30: SIM | P30: SIM | Q30: https://prodam,am,gov,br/acesso-a-informacao/carta-de-governanca-2024/ | R30: 136009915 | S30: 69725561 | T30: 78824023 | U30: 9098462 | V30: NÃO | W30: 730797.6 | X30: 0 | Y30: 23926.98 | Z30: 9749845 | AA30: 25157069 | AB30: 0 | AC30: 0 | AD30: 0 | AE30: 0 | AF30: 0 | AG30: 0 | AH30: 0 | AI30: 0 | AJ30: 99.89 | AK30: 99.89 | AL30: 45193991 | AM30: 45193991 | AN30: 0 | AO30: 0 | AP30: =Z30*100/AA30 -> 38.755886
A31: AP | B31: COMPANHIA DE ÁGUA E ESGOTO DO AMAPÁ | C31: CAESA | D31: 05.976.311/0001-04 | E31: ATIVA | F31: SANEAMENTO | G31: SOCIEDADE DE ECONOMIA MISTA | H31: S.A. | I31: FECHADO | J31: NÃO | K31: NÃO | L31: DEPENDENTE | M31: 298 | N31: SIM | O31: SIM | P31: NÃO | Q31: caesa,portal,ap,gov,br | R31: 2764377.3 | S31: 45689258 | T31: 1.2608268e+08 | U31: 519101.98 | V31: NÃO | W31: 284698.07 | X31: 0 | Y31: 200076.6 | Z31: -1.233183e+08 | AA31: 1.2129848e+08 | AB31: 0 | AC31: 0 | AD31: 51326173 | AE31: 51535695 | AF31: 1.5857231e+08 | AG31: 1.1186538e+08 | AH31: 51326173 | AI31: 51535695 | AJ31: 5245225458 | AK31: 5245225458 | AL31: 5.0695917e+08 | AM31: 5.5982014e+08 | AN31: 52860967 | AO31: 52607136 | AP31: =Z31*100/AA31 -> -101.66516
A32: AP | B32: AGÊNCIA DE FOMENTO POPULAR | C32: AFAP | D32: 02.929.977/0001-13 | E32: ATIVA | F32: FINANCEIRO | G32: EMPRESA PÚBLICA | H32: S.A. | I32: FECHADO | J32: NÃO | K32: NÃO | L32: NÃO DEPENDENTE | M32: 99 | N32: SIM | O32: SIM | P32: NÃO | R32: 11665247 | S32: 4546633.4 | T32: 13015641 | U32: 0 | V32: NÃO | W32: 204363.69 | X32: 0 | Y32: 63428.18 | Z32: -1045966.9 | AA32: 16811614 | AB32: 0 | AC32: 0 | AD32: 0 | AE32: 0 | AF32: 0 | AG32: 0 | AH32: 0 | AI32: 0 | AJ32: 39255740 | AK32: 39255740 | AL32: 34455740 | AM32: 39255740 | AN32: 34455740 | AO32: 39255740 | AP32: =Z32*100/AA32 -> -6.2216926
A33: AP | B33: COMPANHIA DE GÁS DO AMAPÁ | C33: GASAP | D33: 05.943.400/0001-54 | E33: ATIVA | F33: GÁS E DERIVADOS | G33: SOCIEDADE DE ECONOMIA MISTA | H33: S.A. | I33: FECHADO | J33: NÃO | K33: NÃO | L33: NÃO DEPENDENTE | M33: 2 | N33: SIM | O33: SIM | P33: NÃO | Q33: https://gasap,com,br/acesso-a-informacao/governanca/carta-anual-de-governanca | R33: 0 | S33: 169282.13 | T33: 312664.81 | U33: 0 | V33: NÃO | W33: 58275 | X33: 0 | Y33: 0 | Z33: 332463.03 | AA33: 135120.81 | AB33: 0 | AC33: 0 | AD33: 0 | AE33: 0 | AF33: 0 | AG33: 0 | AH33: 0 | AI33: 0 | AJ33: 790500 | AK33: 790500 | AL33: 2999000 | AM33: 31000 | AN33: 101000 | AO33: 0 | AP33: =Z33*100/AA33 -> 246.04872
A34: BA | B34: BAHIA PESCA S.A. | C34: BAHIAPESCA | D34: 13.187.745/0001-53 | E34: ATIVA | F34: ABASTECIMENTO DE ALIMENTOS E OUTROS INSUMOS | G34: SOCIEDADE DE ECONOMIA MISTA | H34: S.A. | I34: FECHADO | J34: NÃO | K34: NÃO | L34: DEPENDENTE | M34: 110 | N34: SIM | O34: SIM | P34: NÃO | Q34: https://www,ba,gov,br/bahiapesca/sites/site-bahiapesca/files/2024-12/Carta%20Anual%20exerc%C3%ADcio%202023,pdf | R34: 83617 | S34: 13857900 | T34: 28561678 | U34: 865276 | V34: NÃO | W34: 379709.85 | X34: 0 | Y34: 0 | Z34: 3377901 | AA34: -3362003 | AB34: 0 | AC34: 0 | AD34: 5400883 | AE34: 6890791.4 | AF34: 2558600 | AG34: 2762929 | AH34: 0 | AI34: 0 | AJ34: 16079007 | AK34: 16079007 | AL34: 4824688.6 | AM34: 4824688.6 | AN34: 0 | AO34: 0 | AP34: =Z34*100/AA34 -> -100.47287
A35: BA | B35: COMPANHA DE DESENVOLVIMENTO E AÇÃO REGIONAL | C35: CAR | D35: 13.221.247/0001-80 | E35: ATIVA | F35: DESENVOLVIMENTO REGIONAL | G35: EMPRESA PÚBLICA | H35: S.A. | I35: FECHADO | J35: NÃO | K35: NÃO | L35: DEPENDENTE | M35: 375 | N35: SIM | O35: SIM | P35: NÃO | Q35: https://www,car,ba,gov,br/sites/default/files/2025-01/Carta%20Anual%202025,pdf | R35: 63124352 | S35: 43114341 | T35: 60917575 | U35: 0 | V35: NÃO | W35: 463700.92 | X35: 0 | Y35: 4892.8 | Z35: 2270183.7 | AA35: -37037212 | AB35: 0 | AC35: 0 | AD35: 51115067 | AE35: 62005726 | AF35: 0 | AG35: 0 | AH35: 0 | AI35: 0 | AJ35: 13542532 | AK35: 13542532 | AL35: 13542532 | AM35: 13542532 | AN35: 12549846 | AO35: 12513332 | AP35: =Z35*100/AA35 -> -6.1294669
A36: BA | B36: COMPANHIA BAIANA DE PESQUISA MINERAL | C36: CBPM | D36: 13.554.910/0001-68 | E36: ATIVA | F36: MINERAÇÃO | G36: SOCIEDADE DE ECONOMIA MISTA | H36: S.A. | I36: FECHADO | J36: NÃO | K36: NÃO | L36: DEPENDENTE | M36: 141 | N36: SIM | O36: SIM | P36: NÃO | Q36: http://www,cbpm,ba,gov,br/transparencia/carta-anual-de-politicas-publicas-e-governanca-corporativa/ | R36: 57231013 | S36: 53051335 | T36: 95695329 | U36: 787226 | V36: NÃO | W36: 463398.48 | X36: 0 | Y36: 16133.11 | Z36: -10532826 | AA36: -83137845 | AB36: 0 | AC36: 0 | AD36: 6087023.9 | AE36: 8346554.7 | AF36: 0 | AG36: 0 | AH36: 0 | AI36: 0 | AJ36: 99991387 | AK36: 99991387 | AL36: 100000000 | AM36: 100000000 | AN36: 0 | AO36: 0 | AP36: =Z36*100/AA36 -> 12.669111
A37: BA | B37: COMPANHIA DE ENGENHARIA HÍDRICA E DE SANEAMENTO DA BAHIA | C37: CERB | D37: 13.529.136/0001-35 | E37: ATIVA | F37: SANEAMENTO | G37: SOCIEDADE DE ECONOMIA MISTA | H37: S.A. | I37: FECHADO | J37: NÃO | K37: NÃO | L37: DEPENDENTE | M37: 1055 | N37: SIM | O37: SIM | P37: SIM | Q37: http://www,cerb,ba,gov,br/sites/www,cerb,ba,gov,br/files/a_cerb/nosso_papel/page/files/CARTA_ANUAL_2024_VF,pdf | R37: 12267646 | S37: 40632220 | T37: 1.5975587e+08 | U37: 86292045 | V37: SIM | W37: 445266.58 | X37: 17139.34 | Y37: 0 | Z37: 14284705 | AA37: 7166576.2 | AB37: 0 | AC37: 0 | AD37: 1.2280125e+08 | AE37: 1.4710052e+08 | AF37: 0 | AG37: 59733784 | AH37: 0 | AI37: 0 | AJ37: 99.65 | AK37: 99.65 | AL37: 131206906 | AM37: 131206906 | AN37: 0 | AO37: 0 | AP37: =Z37*100/AA37 -> 199.32399
A38: BA | B38: COMPANHIA DE DESENVOLVIMENTO URBANO DO ESTADO DA BAHIA | C38: CONDER | D38: 13.595.251/0001-08 | E38: ATIVA | F38: HABITAÇÃO E URBANIZAÇÃO | G38: EMPRESA PÚBLICA | H38: OUTRAS | I38: FECHADO | J38: NÃO | K38: NÃO | L38: DEPENDENTE | M38: 347 | N38: SIM | O38: SIM | P38: NÃO | Q38: https://www,conder,ba,gov,br/sites/default/files/2024-04/CARTA GOVERNANÇA 2024_0,pdf | R38: 3.7690629e+08 | S38: 42386836 | T38: 3.9613606e+08 | U38: 0 | V38: NÃO | W38: 451672.48 | X38: 0 | Y38: 11888.24 | Z38: -14979511 | AA38: 1.7510069e+08 | AB38: 0 | AC38: 0 | AD38: 1.3169547e+09 | AE38: 1.1263136e+09 | AF38: 0 | AG38: 0 | AH38: 0 | AI38: 0 | AJ38: 16803754 | AK38: 16803754 | AL38: 16803753 | AM38: 16803754 | AN38: 0 | AO38: 0 | AP38: =Z38*100/AA38 -> -8.554798
A39: BA | B39: COMPANHIA DE TRANSPORTE DO ESTADO DA BAHIA | C39: CTB | D39: 03.231.999/0001-78 | E39: ATIVA | F39: TRANSPORTE | G39: EMPRESA PÚBLICA | H39: S.A. | I39: FECHADO | J39: NÃO | K39: NÃO | L39: DEPENDENTE | M39: 82 | N39: SIM | O39: SIM | P39: NÃO | R39: 5213305 | S39: 23508721 | T39: 2.6093772e+08 | U39: 237429000 | V39: NÃO | W39: 433360.48 | X39: 0 | Y39: 0 | Z39: -11730795 | AA39: 40896905 | AB39: 0 | AC39: 0 | AD39: 59945660 | AE39: 2.7735765e+08 | AF39: 0 | AG39: 0 | AH39: 0 | AI39: 0 | AJ39: 159700077 | AK39: 159700077 | AL39: 1.3965449e+08 | AM39: 1.3965449e+08 | AN39: 22737270 | AO39: 22737270 | AP39: =Z39*100/AA39 -> -28.68382
A40: BA | B40: COMPANHIA DE GÁS DA BAHIA | C40: BAHIAGÁS | D40: 34.432.153/0001-20 | E40: ATIVA | F40: GÁS E DERIVADOS | G40: SOCIEDADE DE ECONOMIA MISTA | H40: S.A. | I40: FECHADO | J40: NÃO | K40: NÃO | L40: NÃO DEPENDENTE | M40: 611 | N40: SIM | O40: SIM | P40: SIM | Q40: https://www,bahiagas,com,br/sobre-a-bahiagas/cartas-anuais | R40: 3.1283853e+09 | S40: 1.0301229e+08 | T40: 5.5297003e+08 | U40: 2.3625441e+08 | V40: SIM | W40: 560751.36 | X40: 103582.81 | Y40: 0 | Z40: 1.9768137e+08 | AA40: 1.1378639e+09 | AB40: 0 | AC40: 66931377 | AD40: 0 | AE40: 0 | AF40: 0 | AG40: 0 | AH40: 0 | AI40: 0 | AJ40: 13490874 | AK40: 15162188 | AL40: 3.1672674e+08 | AM40: 3.5596433e+08 | AN40: 0 | AO40: 0 | AP40: =Z40*100/AA40 -> 17.373023
A41: BA | B41: EMPRESA BAIANA DE ATIVOS S.A. | C41: BAHIAINVESTE | D41: 26.310.070/0001-30 | E41: ATIVA | F41: GESTÃO DE ATIVOS | G41: SOCIEDADE DE ECONOMIA MISTA | H41: S.A. | I41: FECHADO | J41: NÃO | K41: NÃO | L41: NÃO DEPENDENTE | M41: 36 | N41: SIM | O41: SIM | P41: NÃO | Q41: CARTA-ANUAL-BI-2024_2025_28_04_25-Assinada-compactado,pdf | R41: 6063811.6 | S41: 7903369.5 | T41: 10655651 | U41: 204804.5 | V41: NÃO | W41: 506760.26 | X41: 0 | Y41: 14325.42 | Z41: -7564609.5 | AA41: 64281864 | AB41: 0 | AC41: 0 | AD41: 0 | AE41: 0 | AF41: 0 | AG41: 0 | AH41: 8545000 | AI41: 5000000 | AJ41: 80735673 | AK41: 92280673 | AL41: 80735673 | AM41: 92280673 | AN41: 0 | AO41: 2000000 | AP41: =Z41*100/AA41 -> -11.767875
A42: BA | B42: AGÊNCIA DE FOMENTO DO ESTADO DA BAHIA | C42: DESENBAHIA | D42: 15.163.587/0001-27 | E42: ATIVA | F42: FINANCEIRO | G42: SOCIEDADE DE ECONOMIA MISTA | H42: S.A. | I42: FECHADO | J42: NÃO | K42: NÃO | L42: NÃO DEPENDENTE | M42: 249 | N42: SIM | O42: SIM | P42: SIM | Q42: https://www,desenbahia,ba,gov,br/wp-content/uploads/2024/05/carta-anual-politicas-publicas-e-governanca-corporativa-2023-revfinal,pdf | R42: 2.8465594e+08 | S42: 67101416 | T42: 1.894192e+08 | U42: 0 | V42: SIM | W42: 479397.25 | X42: 81554.61 | Y42: 24077.13 | Z42: 96535176 | AA42: 8.2753925e+08 | AB42: 0 | AC42: 33994927 | AD42: 0 | AE42: 0 | AF42: 0 | AG42: 0 | AH42: 0 | AI42: 0 | AJ42: 142301765100 | AK42: 142301765100 | AL42: 6.2389725e+08 | AM42: 6.2389725e+08 | AN42: 0 | AO42: 0 | AP42: =Z42*100/AA42 -> 11.665329
A43: BA | B43: EMPRESA GRÁFICA DA BAHIA | C43: EGBA | D43: 15.257.819/0001-06 | E43: ATIVA | F43: INFORMÁTICA E TECNOLOGIA DA INFORMAÇÃO | G43: EMPRESA PÚBLICA | H43: OUTRAS | I43: FECHADO | J43: NÃO | K43: NÃO | L43: NÃO DEPENDENTE | M43: 159 | N43: SIM | O43: SIM | P43: SIM | R43: 130963997 | S43: 17342286 | T43: 141706642 | U43: 0 | V43: NÃO | W43: 393665 | X43: 0 | Y43: 0 | Z43: 5291485 | AA43: 67555971 | AB43: 0 | AC43: 0 | AD43: 0 | AE43: 0 | AF43: 0 | AG43: 0 | AH43: 0 | AI43: 0 | AJ43: 0 | AK43: 0 | AL43: 44726598 | AM43: 44726598 | AN43: 0 | AO43: 0 | AP43: =Z43*100/AA43 -> 7.8327421
A44: BA | B44: EMPRESA BAIANA DE ÁGUAS E SANEAMENTO | C44: EMBASA | D44: 13.504.675/0001-10 | E44: ATIVA | F44: SANEAMENTO | G44: SOCIEDADE DE ECONOMIA MISTA | H44: S.A. | I44: FECHADO | J44: NÃO | K44: NÃO | L44: NÃO DEPENDENTE | M44: 4837 | N44: SIM | O44: SIM | P44: SIM | Q44: https://www,embasa,ba,gov,br/a-embasa/quem-somos/governanca/carta-anual-de-politicas-publicas-de-governanca-corporativa | R44: 5.7319573e+09 | S44: 1.0123312e+09 | T44: 5.8769016e+09 | U44: 1.1673332e+09 | V44: SIM | W44: 894298.57 | X44: 70401.29 | Y44: 18004.38 | Z44: 1.0074783e+09 | AA44: 8.2708979e+09 | AB44: 0 | AC44: 0 | AD44: 0 | AE44: 0 | AF44: 0 | AG44: 0 | AH44: 0 | AI44: 0 | AJ44: 698044720 | AK44: 713145896 | AL44: 4.9421566e+09 | AM44: 5.0490729e+09 | AN44: 1.0691633e+08 | AO44: 57503611 | AP44: =Z44*100/AA44 -> 12.181003
A45: BA | B45: COMPANHIA DE PROCESSAMENTO DE DADOS DO ESTADO DA BAHIA | C45: PRODEB | D45: 13.579.586/0001-32 | E45: ATIVA | F45: INFORMÁTICA E TECNOLOGIA DA INFORMAÇÃO | G45: SOCIEDADE DE ECONOMIA MISTA | H45: S.A. | I45: FECHADO | J45: NÃO | K45: NÃO | L45: NÃO DEPENDENTE | M45: 691 | N45: SIM | O45: SIM | P45: SIM | Q45: https://www,prodeb,ba,gov,br/transparencia/governanca-corporativa/carta-anual-de-politicas-publicas-e-governanca-corporativa | R45: 185116460 | S45: 1.0788131e+08 | T45: 154405800 | U45: 10868764 | V45: NÃO | W45: 556998.24 | X45: 0 | Y45: 0 | Z45: 18634675 | AA45: 119512584 | AB45: 0 | AC45: 0 | AD45: 0 | AE45: 0 | AF45: 0 | AG45: 0 | AH45: 0 | AI45: 0 | AJ45: 2.1180689e+10 | AK45: 2.1180689e+10 | AL45: 111887147 | AM45: 118292477 | AN45: 8829991 | AO45: 2424661 | AP45: =Z45*100/AA45 -> 15.592228
A46: BA | B46: HABITAÇÃO E URBANIZAÇÃO DA BAHIA S.A. | C46: URBIS | D46: 15.171.101/0001-00 | E46: EM LIQUIDAÇÃO | F46: HABITAÇÃO E URBANIZAÇÃO | G46: SOCIEDADE DE ECONOMIA MISTA | H46: S.A. | I46: FECHADO | J46: NÃO | K46: NÃO | L46: NÃO DEPENDENTE | M46: 51 | N46: SIM | O46: SIM | P46: NÃO | R46: 804650.42 | S46: 9675773 | T46: 84070079 | U46: 0 | V46: NÃO | W46: 348209.88 | X46: 0 | Y46: 0 | Z46: -72337245 | AA46: -1.104685e+08 | AB46: 0 | AC46: 0 | AD46: 0 | AE46: 0 | AF46: 0 | AG46: 0 | AH46: 0 | AI46: 0 | AJ46: 1764492195 | AK46: 1765390210 | AL46: 353078042 | AM46: 353078042 | AN46: 0 | AO46: 0 | AP46: =Z46*100/AA46 -> 65.482235
A47: CE | B47: Companhia de Habitação do Ceará | C47: COHAB | D47: 07.121.536/0001-04 | E47: EM LIQUIDAÇÃO | F47: HABITAÇÃO E URBANIZAÇÃO | G47: SOCIEDADE DE ECONOMIA MISTA | H47: S.A. | I47: FECHADO | J47: NÃO | K47: NÃO | L47: DEPENDENTE | M47: 45 | N47: NÃO | O47: SIM | P47: NÃO | R47: 889561.62 | S47: 2958289.8 | T47: 14936810 | U47: 66780 | V47: NÃO | W47: 121610.4 | X47: 0 | Y47: 0 | Z47: -10281440 | AA47: -3.1555923e+08 | AC47: 0 | AD47: 9400117.8 | AE47: 3685417.1 | AF47: 7.2494858e+08 | AG47: 7.3182139e+08 | AH47: 0 | AI47: 0 | AJ47: 29404405 | AK47: 29404405 | AL47: 29404405 | AM47: 29404405 | AN47: 0 | AO47: 0 | AP47: =Z47*100/AA47 -> 3.2581649
A48: CE | B48: Empresa de Assistência Técnica e Extensão Rural do Ceará | C48: EMATERCE | D48: 05.371.711/0001-96 | E48: ATIVA | F48: PESQUISA E ASSISTÊNCIA TÉCNICA AGROPECUÁRIA | G48: EMPRESA PÚBLICA | H48: OUTRAS | I48: FECHADO | J48: NÃO | K48: NÃO | L48: DEPENDENTE | M48: 743 | N48: SIM | O48: SIM | P48: NÃO | R48: 1.3563043e+08 | S48: 1.2130789e+08 | T48: 1.3608158e+08 | U48: 0 | V48: NÃO | W48: 503399.06 | X48: 0 | Y48: 0 | Z48: -476324.62 | AA48: -93996136 | AC48: 0 | AD48: 1.2584748e+08 | AE48: 1.3569886e+08 | AF48: 0 | AG48: 0 | AH48: 0 | AI48: 0 | AJ48: 0 | AK48: 0 | AL48: 2511583.8 | AM48: 2511583.8 | AN48: 0 | AO48: 0 | AP48: =Z48*100/AA48 -> 0.50674915
A49: CE | B49: Empresa de Tecnologia da Informação do Ceará | C49: ETICE | D49: 03.773.788/0001-67 | E49: ATIVA | F49: INFORMÁTICA E TECNOLOGIA DA INFORMAÇÃO | G49: EMPRESA PÚBLICA | H49: S.A. | I49: FECHADO | J49: NÃO | K49: NÃO | L49: DEPENDENTE | M49: 193 | N49: SIM | O49: SIM | P49: NÃO | Q49: https://www,etice,ce,gov,br/cartas-anuais-de-politicas-publicas-e-governanca-corporativa/ | R49: 336115591 | S49: 58947805 | T49: 315592968 | U49: 141910 | V49: NÃO | W49: 534130 | X49: 0 | Y49: 0 | Z49: 23493609 | AA49: 40007116 | AC49: 0 | AD49: 50337610 | AE49: 52846766 | AF49: 0 | AG49: 0 | AH49: 0 | AI49: 0 | AJ49: 100 | AK49: 100 | AL49: 50000 | AM49: 13748706 | AN49: 0 | AO49: 0 | AP49: =Z49*100/AA49 -> 58.723576
A50: CE | B50: Agência de Desenvolvimento do Estado do Ceará S/A | C50: ADECE | D50: 09.100.913/0001-54 | E50: ATIVA | F50: DESENVOLVIMENTO REGIONAL | G50: SOCIEDADE DE ECONOMIA MISTA | H50: S.A. | I50: FECHADO | J50: NÃO | K50: NÃO | L50: NÃO DEPENDENTE | M50: 139 | N50: SIM | O50: SIM | P50: NÃO | R50: 58806792 | S50: 22091401 | T50: 68162153 | U50: 26175954 | V50: NÃO | W50: 282690.4 | X50: 0 | Y50: 0 | Z50: 16820593 | AA50: 2.2757306e+08 | AC50: 0 | AD50: 0 | AE50: 0 | AF50: 0 | AG50: 0 | AH50: 0 | AI50: 18922127 | AJ50: 124633269 | AK50: 135966352 | AL50: 151568606 | AM50: 1.7049073e+08 | AN50: 0 | AO50: 0 | AP50: =Z50*100/AA50 -> 7.3912935
A51: CE | B51: Companhia de Água e Esgoto do Ceará | C51: CAGECE | D51: 07.040.108/0001-57 | E51: ATIVA | F51: SANEAMENTO | G51: SOCIEDADE DE ECONOMIA MISTA | H51: S.A. | I51: FECHADO | J51: NÃO | K51: NÃO | L51: NÃO DEPENDENTE | M51: 5769 | N51: SIM | O51: SIM | P51: SIM | Q51: https://www,cagece,com,br/wp-content/uploads/PDF/Governanca/Documentos/DocumentosdeRegulacaoInterna/CartaAnual/Carta-Anual-de-Politicas-Publicas-e-Governanca-Corporativa-2023,pdf | R51: 3.1370183e+09 | S51: 7.5056124e+08 | T51: 4.1028885e+09 | U51: 1.3199202e+09 | V51: SIM | W51: 796275.06 | X51: 51422.73 | Y51: 64733.55 | Z51: 3.5405001e+08 | AA51: 3.3176765e+09 | AC51: 0 | AD51: 0 | AE51: 0 | AF51: 0 | AG51: 0 | AH51: 38334496 | AI51: 82919565 | AJ51: 164603035 | AK51: 169275465 | AL51: 2.1691017e+09 | AM51: 2.3362592e+09 | AN51: 0 | AO51: 0 | AP51: =Z51*100/AA51 -> 10.671625
A52: CE | B52: Companhia de Participação de Ativos do Ceará | C52: CEARAPAR | D52: 44.062.163/0001-74 | E52: ATIVA | F52: GESTÃO DE ATIVOS | G52: SOCIEDADE DE ECONOMIA MISTA | H52: S.A. | I52: FECHADO | J52: NÃO | K52: NÃO | L52: NÃO DEPENDENTE | M52: 22 | N52: SIM | O52: SIM | P52: NÃO | Q52: https://cppub,cepart,com,br/upload/docInst/Carta_Anual_2023_cearapar,pdf | R52: 6085723.8 | S52: 4250289.7 | T52: 5176423.6 | U52: 88157.72 | V52: NÃO | W52: 193581.5 | X52: 0 | Y52: 0 | Z52: -245882.77 | AA52: 1042708.6 | AC52: 0 | AD52: 0 | AE52: 0 | AF52: 0 | AG52: 0 | AH52: 0 | AI52: 0 | AJ52: 4999999 | AK52: 4999999 | AL52: 5000000 | AM52: 5000000 | AN52: 0 | AO52: 0 | AP52: =Z52*100/AA52 -> -23.581158
A53: CE | B53: Centrais de Abastecimento do Ceará S/A | C53: CEASA | D53: 07.029.051/0001-95 | E53: ATIVA | F53: ABASTECIMENTO DE ALIMENTOS E OUTROS INSUMOS | G53: SOCIEDADE DE ECONOMIA MISTA | H53: S.A. | I53: FECHADO | J53: NÃO | K53: NÃO | L53: NÃO DEPENDENTE | M53: 265 | N53: SIM | O53: SIM | P53: NÃO | R53: 34174606 | S53: 18912827 | T53: 34254277 | U53: 0 | V53: NÃO | W53: 180982.64 | X53: 0 | Y53: 0 | Z53: 66798 | AA53: 7171691 | AC53: 0 | AD53: 0 | AE53: 0 | AF53: 0 | AG53: 0 | AH53: 0 | AI53: 0 | AJ53: 3729073 | AK53: 3729073 | AL53: 3729073 | AM53: 3729073 | AN53: 0 | AO53: 0 | AP53: =Z53*100/AA53 -> 0.93141213
A54: CE | B54: Companhia de Gás do Ceará | C54: CEGAS | D54: 73.759.185/0001-96 | E54: ATIVA | F54: GÁS E DERIVADOS | G54: SOCIEDADE DE ECONOMIA MISTA | H54: S.A. | I54: FECHADO | J54: NÃO | K54: NÃO | L54: NÃO DEPENDENTE | M54: 143 | N54: SIM | O54: SIM | P54: SIM | Q54: https://www,cegas,com,br | R54: 6.4790453e+08 | S54: 14145215 | T54: 7.186766e+08 | U54: 35321589 | V54: SIM | W54: 403935.4 | X54: 44869 | Y54: 0 | Z54: 53836635 | AA54: 2.7270945e+08 | AC54: 11982825 | AD54: 0 | AE54: 0 | AF54: 0 | AG54: 0 | AH54: 0 | AI54: 0 | AJ54: 11449572 | AK54: 11449572 | AL54: 54393290 | AM54: 58681100 | AN54: 0 | AO54: 0 | AP54: =Z54*100/AA54 -> 19.74139
A55: CE | B55: Companhia de Desenvolvimento do Complexo Industrial e Portuário do Pecém - CIPP S/A | C55: CIPP | D55: 01.256.678/0001-00 | E55: ATIVA | F55: PORTOS E HIDROVIAS | G55: SOCIEDADE DE ECONOMIA MISTA | H55: S.A. | I55: FECHADO | J55: NÃO | K55: NÃO | L55: NÃO DEPENDENTE | M55: 375 | N55: SIM | O55: SIM | P55: SIM | Q55: https://www,complexodopecem,com,br/wp-content/uploads/2021/10/Carta-Anual-2024,pdf | R55: 2.9110418e+08 | S55: 94346584 | T55: 2.0907628e+08 | U55: 49933261 | V55: NÃO | W55: 626720.41 | X55: 0 | Y55: 68522.29 | Z55: 98567135 | AA55: 1.3507565e+09 | AB55: 1.3507565e+09 | AC55: 17219203 | AD55: 0 | AE55: 0 | AF55: 600274.64 | AG55: 2645714.3 | AH55: 0 | AI55: 0 | AJ55: 123848859 | AK55: 123848859 | AL55: 7.4876065e+08 | AM55: 7.4876065e+08 | AN55: 0 | AO55: 0 | AP55: =Z55*100/AA55 -> 7.2971801
A56: CE | B56: Companhia de Gestão dos Recursos Hídricos | C56: COGERH | D56: 74.075.938/0001-07 | E56: ATIVA | F56: SANEAMENTO | G56: SOCIEDADE DE ECONOMIA MISTA | H56: S.A. | I56: FECHADO | J56: NÃO | K56: NÃO | L56: NÃO DEPENDENTE | M56: 952 | N56: SIM | O56: SIM | P56: SIM | Q56: https://portal,cogerh,com,br/wp-content/uploads/2024/10/ASGRC%202024%20CARTA%20ANUAL%20ano%20base%202023%20,pdf | R56: 228237130 | S56: 110210112 | T56: 221229629 | U56: 13273633 | V56: SIM | W56: 561341.06 | X56: 33292.64 | Y56: 0 | Z56: 14241975 | AA56: 275152984 | AB56: 275152984 | AC56: 1201000 | AD56: 0 | AE56: 0 | AF56: 0 | AG56: 0 | AH56: 3350355 | AI56: 5701731 | AJ56: 161410751 | AK56: 161410758 | AL56: 152912091 | AM56: 158613822 | AN56: 8498667 | AO56: 2796936 | AP56: =Z56*100/AA56 -> 5.1760206
A57: CE | B57: Companhia Cearense de Transportes Metropolitanos | C57: METROFOR | D57: 02.003.575/0001-93 | E57: ATIVA | F57: TRANSPORTE | G57: SOCIEDADE DE ECONOMIA MISTA | H57: S.A. | I57: FECHADO | J57: NÃO | K57: NÃO | L57: NÃO DEPENDENTE | M57: 1114 | N57: SIM | O57: SIM | P57: SIM | Q57: https://www,metrofor,ce,gov,br/wp-content/uploads/sites/32/2022/03/Carta_Poli%CC%81ticas_Pu%CC%81blicasGovernanc%CC%A7a-2021,pdf | R57: 2.4410182e+08 | S57: 1.3275466e+08 | T57: 3.6916145e+08 | U57: 8617638.5 | V57: NÃO | W57: 326294.08 | X57: 0 | Y57: 0 | Z57: -67338883 | AA57: 9.1595358e+08 | AC57: 0 | AD57: 1.9400167e+08 | AE57: 2.1501189e+08 | AF57: 0 | AG57: 0 | AH57: 4400000 | AI57: 4000000 | AJ57: 2995022400 | AK57: 3000302400 | AL57: 2495852000 | AM57: 2500252000 | AN57: 0 | AO57: 0 | AP57: =Z57*100/AA57 -> -7.351779
A58: CE | B58: ZPE Ceará | C58: ZPE | D58: 13.006.170/0001-25 | E58: ATIVA | F58: DESENVOLVIMENTO REGIONAL | G58: SOCIEDADE DE ECONOMIA MISTA | H58: S.A. | I58: FECHADO | J58: NÃO | K58: SIM | L58: NÃO DEPENDENTE | M58: 152 | N58: SIM | O58: SIM | P58: NÃO | Q58: https://zpeceara,com,br/wp-content/uploads/2024/05/Carta-Anual-2023_ZPE,pdf | R58: 44297903 | S58: 17924084 | T58: 29998260 | U58: 3495688.5 | V58: SIM | W58: 287117.16 | X58: 147625.3 | Y58: 0 | Z58: 13568036 | AA58: 35820464 | AC58: 0 | AD58: 0 | AE58: 0 | AF58: 0 | AG58: 0 | AH58: 0 | AI58: 0 | AJ58: 0 | AK58: 0 | AL58: 0 | AM58: 0 | AN58: 0 | AO58: 0 | AP58: =Z58*100/AA58 -> 37.87789
A59: DF | B59: Companhia de Planejamento do Distrito Federal | C59: CODEPLAN | D59: 00.046.060/0001-45 | E59: ATIVA | F59: GESTÃO DE ATIVOS | G59: EMPRESA PÚBLICA | H59: S.A. | I59: FECHADO | J59: NÃO | K59: SIM | L59: DEPENDENTE | M59: 5 | N59: SIM | O59: SIM | P59: NÃO | R59: 0 | S59: 1328051 | T59: 1363008.8 | U59: 0 | V59: NÃO | W59: 128223.55 | X59: 0 | Y59: 0 | Z59: -96518.78 | AA59: -355358.16 | AC59: 0 | AD59: 1480509.3 | AE59: 1363008.8 | AF59: 69761.27 | AG59: 95150.19 | AH59: 0 | AI59: 0 | AJ59: 1226666971 | AK59: 1226666971 | AL59: 1226666971 | AM59: 1226666971 | AN59: 0 | AO59: 0 | AP59: =Z59*100/AA59 -> 27.160986
A60: DF | B60: Companhia de Desenvolvimento Habitacional do Distrito Federal | C60: CODHAB/DF | D60: 09.335.575/0001-30 | E60: ATIVA | F60: HABITAÇÃO E URBANIZAÇÃO | G60: EMPRESA PÚBLICA | H60: OUTRAS | I60: FECHADO | J60: NÃO | K60: NÃO | L60: DEPENDENTE | M60: 457 | N60: SIM | O60: SIM | P60: SIM | R60: 12622752 | S60: 42072587 | T60: 69122330 | U60: 0 | V60: NÃO | W60: 242075.5 | X60: 0 | Y60: 0 | Z60: -56499579 | AA60: 2.3377602e+08 | AC60: 0 | AD60: 85133718 | AE60: 1.0078641e+08 | AF60: 0 | AG60: 0 | AH60: 0 | AI60: 0 | AJ60: 0 | AK60: 0 | AL60: 37029932 | AM60: 37029932 | AN60: 37029932 | AO60: 37029932 | AP60: =Z60*100/AA60 -> -24.168252
A61: DF | B61: Empresa de Assistência Técnica e Extensão Rural do Distrito Federal | C61: EMATER-DF | D61: 00.509.612/0001-04 | E61: ATIVA | F61: PESQUISA E ASSISTÊNCIA TÉCNICA AGROPECUÁRIA | G61: EMPRESA PÚBLICA | H61: OUTRAS | I61: FECHADO | J61: NÃO | K61: NÃO | L61: DEPENDENTE | M61: 309 | N61: SIM | O61: SIM | P61: SIM | Q61: https://emater,df,gov,br/category/carta-de-servicos/ | R61: 55522.87 | S61: 1.3937372e+08 | T61: 1.6118769e+08 | U61: 0 | V61: NÃO | W61: 712722.87 | X61: 0 | Y61: 0 | Z61: 19285188 | AA61: 677760.52 | AC61: 0 | AD61: 1.3379615e+08 | AE61: 1.4765586e+08 | AF61: 0 | AG61: 0 | AH61: 0 | AI61: 0 | AJ61: 0 | AK61: 0 | AL61: 677760.52 | AM61: 677760.52 | AN61: 10350559 | AO61: 10350559 | AP61: =Z61*100/AA61 -> 2845.4281
A62: DF | B62: Empresa de Regularização de Terras Rurais | C62: ETR S.A. | D62: 50.698.494/0001-06 | E62: ATIVA | F62: DESENVOLVIMENTO REGIONAL | G62: SOCIEDADE DE ECONOMIA MISTA | H62: S.A. | I62: FECHADO | J62: NÃO | K62: SIM | L62: DEPENDENTE | M62: 44 | N62: SIM | O62: SIM | P62: SIM | R62: 0 | S62: 7222325.6 | T62: 10203666 | U62: 859790 | V62: SIM | W62: 561405.34 | X62: 15889.45 | Y62: 33884.16 | Z62: -9380301 | AA62: 880741 | AC62: 0 | AD62: 0 | AE62: 0 | AF62: 0 | AG62: 0 | AH62: 5840466.3 | AI62: 10203666 | AJ62: 10 | AK62: 100 | AL62: 50000 | AM62: 50000 | AN62: 45000 | AO62: 0 | AP62: =Z62*100/AA62 -> -1065.0465
A63: DF | B63: Companhia do Metropolitano do Distrito Federal | C63: METRÔ-DF | D63: 38.070.074/0001-77 | E63: ATIVA | F63: TRANSPORTE | G63: EMPRESA PÚBLICA | H63: OUTRAS | I63: FECHADO | J63: NÃO | K63: NÃO | L63: DEPENDENTE | M63: 1201 | N63: SIM | O63: SIM | P63: NÃO | Q63: https://metro,df,gov,br/?page_id=37077 | R63: 1.9251064e+08 | S63: 3.1029168e+08 | T63: 1.1168942e+09 | U63: 51402372 | V63: NÃO | W63: 812490.74 | X63: 0 | Y63: 23512.62 | Z63: -5.4040019e+08 | AA63: 1.3684753e+09 | AC63: 0 | AD63: 3.6961595e+08 | AE63: 4.686674e+08 | AF63: 0 | AG63: 0 | AH63: 2233538.6 | AI63: 44635187 | AJ63: 30689692 | AK63: 30713387 | AL63: 2.8934242e+09 | AM63: 2.8956581e+09 | AN63: 2233538.6 | AO63: 44635187 | AP63: =Z63*100/AA63 -> -39.489219
A64: DF | B64: Companhia Urbanizadora da Nova Capital do Brasil | C64: NOVACAP | D64: 00.037.457/0001-70 | E64: ATIVA | F64: HABITAÇÃO E URBANIZAÇÃO | G64: EMPRESA PÚBLICA | H64: S.A. | I64: FECHADO | J64: NÃO | K64: NÃO | L64: DEPENDENTE | M64: 992 | N64: SIM | O64: SIM | P64: NÃO | R64: 0 | S64: 0 | T64: 536246883 | U64: 2827683.6 | V64: NÃO | W64: 539262.2 | X64: 0 | Y64: 0 | Z64: -35717756 | AA64: 8.2204447e+08 | AC64: 0 | AD64: 1.3940762e+09 | AE64: 2.0574368e+09 | AF64: 0 | AG64: 0 | AH64: 7272937 | AI64: 7272937 | AJ64: 280600 | AK64: 280600 | AL64: 26713076 | AM64: 26716076 | AN64: 0 | AO64: 0 | AP64: =Z64*100/AA64 -> -4.3449907
A65: DF | B65: Sociedade de Abastecimento de Brasília | C65: SAB | D65: 00.037.226/0001-67 | E65: EM LIQUIDAÇÃO | F65: SANEAMENTO | G65: EMPRESA PÚBLICA | H65: S.A. | I65: FECHADO | J65: NÃO | K65: NÃO | L65: DEPENDENTE | M65: 113 | N65: SIM | O65: SIM | P65: NÃO | R65: 21550612 | S65: 21157094 | T65: 21297960 | U65: 0 | V65: NÃO | W65: 287369.68 | X65: 0 | Y65: 0 | Z65: 252652.15 | AA65: -1727395.8 | AC65: 0 | AD65: 20598560 | AE65: 21416537 | AF65: 0 | AG65: 0 | AH65: 22.3 | AI65: 0 | AJ65: 1636885749 | AK65: 1636885749 | AL65: 16368857 | AM65: 16368857 | AN65: 0 | AO65: 0 | AP65: =Z65*100/AA65 -> -14.626188
A66: DF | B66: Sociedade de Transportes Coletivos de Brasília | C66: TCB | D66: 00.037.127/0001-85 | E66: ATIVA | F66: TRANSPORTE | G66: EMPRESA PÚBLICA | H66: LTDA | I66: FECHADO | J66: NÃO | K66: NÃO | L66: DEPENDENTE | M66: 552 | N66: SIM | O66: SIM | P66: NÃO | R66: 5775667.1 | S66: 10168034 | T66: 28236642 | U66: 0 | V66: NÃO | W66: 331624.15 | X66: 0 | Y66: 0 | Z66: -36494716 | AA66: 60677501 | AC66: 0 | AD66: 2.1512391e+08 | AE66: 2.669227e+08 | AF66: 75022399 | AG66: 1.3619987e+08 | AH66: 0 | AI66: 0 | AJ66: 37722.75 | AK66: 37722.75 | AL66: 43886200 | AM66: 43886200 | AN66: 0 | AO66: 0 | AP66: =Z66*100/AA66 -> -60.145383
A67: DF | B67: BIOTIC S.A. | C67: BIOTIC | D67: 29.580.134/0001-00 | E67: ATIVA | F67: DESENVOLVIMENTO REGIONAL | G67: EMPRESA PÚBLICA | H67: S.A. | I67: FECHADO | J67: NÃO | K67: SIM | L67: NÃO DEPENDENTE | M67: 69 | N67: SIM | O67: SIM | P67: NÃO | Q67: https://www,bioticsa,com,br/pdf/Carta_governanca_Bioti | R67: 0 | S67: 10021616 | T67: 18009638 | U67: 1515396.6 | V67: NÃO | W67: 532630.43 | X67: 0 | Y67: 0 | Z67: 28800626 | AA67: 1052610978 | AC67: 0 | AD67: 0 | AE67: 0 | AF67: 0 | AG67: 0 | AH67: 0 | AI67: 0 | AJ67: 9958047 | AK67: 9958047 | AL67: 995804700 | AM67: 995804700 | AN67: -5794655 | AO67: -5794655 | AP67: =Z67*100/AA67 -> 2.736113
A68: DF | B68: Banco Regional de Brasília | C68: BRB | D68: 00.000.208/0001-00 | E68: ATIVA | F68: FINANCEIRO | G68: SOCIEDADE DE ECONOMIA MISTA | H68: S.A. | I68: ABERTO | J68: SIM | K68: NÃO | L68: NÃO DEPENDENTE | M68: 3359 | N68: SIM | O68: SIM | P68: SIM | Q68: https://ri,brb,com,br/pt/carta-anual-de-politicas-publicas-e-governanca-corporativa | R68: 2.2933871e+08 | S68: 1.2153397e+09 | T68: 8.1566339e+09 | U68: 2.0608693e+08 | V68: SIM | W68: 837726.37 | X68: 324385.26 | Y68: 0 | Z68: 1.9571683e+08 | AA68: 3.6873314e+09 | AB68: 3.190606e+09 | AC68: 1206204.5 | AD68: 0 | AE68: 0 | AF68: 0 | AG68: 0 | AH68: 0 | AI68: 0 | AJ68: 71.92 | AK68: 65.63 | AL68: 0 | AM68: 0 | AN68: 0 | AO68: 0 | AP68: =Z68*100/AA68 -> 5.3078176
A69: DF | B69: BRB - Administradora e Corretora de Seguros S/A | C69: BRB Administradora | D69: 42.597.575/0001-83 | E69: ATIVA | F69: FINANCEIRO | G69: SOCIEDADE DE ECONOMIA MISTA | H69: S.A. | I69: FECHADO | J69: NÃO | K69: SIM | L69: NÃO DEPENDENTE | M69: 0 | N69: NÃO | O69: SIM | P69: NÃO | R69: 301617.51 | S69: 1490863.6 | T69: 2979003.3 | U69: 0 | V69: NÃO | W69: 0 | X69: 0 | Y69: 0 | Z69: 80614672 | AA69: 4.9954158e+08 | AC69: 0 | AD69: 0 | AE69: 0 | AF69: 0 | AG69: 0 | AH69: 0 | AI69: 0 | AJ69: 0 | AK69: 0 | AL69: 0 | AM69: 0 | AN69: 0 | AO69: 0 | AP69: =Z69*100/AA69 -> 16.13773
A70: DF | B70: BRB Distribuidora de Títulos e Valores Mobiliários | C70: BRB DVTM | D70: 33.850.686/0001-69 | E70: ATIVA | F70: FINANCEIRO | G70: SOCIEDADE DE ECONOMIA MISTA | H70: S.A. | I70: FECHADO | J70: NÃO | K70: SIM | L70: NÃO DEPENDENTE | M70: 38 | N70: SIM | O70: SIM | P70: SIM | R70: 11143665 | S70: 3082019.4 | T70: 26478526 | U70: 0 | V70: SIM | W70: 697595.69 | X70: 74146.85 | Y70: 0 | Z70: 5674698.7 | AA70: 62259026 | AC70: 0 | AD70: 0 | AE70: 0 | AF70: 0 | AG70: 0 | AH70: 0 | AI70: 0 | AJ70: 0 | AK70: 0 | AL70: 40000000 | AM70: 40000000 | AN70: 0 | AO70: 0 | AP70: =Z70*100/AA70 -> 9.1146603
A71: DF | B71: BRB Crédito, Financiamento e Investimento | C71: BRB Investimento | D71: 33.136.888/0001-43 | E71: ATIVA | F71: FINANCEIRO | G71: SOCIEDADE DE ECONOMIA MISTA | H71: S.A. | I71: FECHADO | J71: NÃO | K71: SIM | L71: NÃO DEPENDENTE | M71: 0 | N71: NÃO | O71: SIM | P71: NÃO | R71: 2.3411907e+08 | S71: 567953.8 | T71: 9.7787041e+08 | U71: 0 | V71: SIM | W71: 614208.7 | X71: 20796.97 | Y71: 0 | Z71: 1.4105431e+08 | AA71: 4.3372701e+08 | AC71: 0 | AD71: 0 | AE71: 0 | AF71: 0 | AG71: 0 | AH71: 0 | AI71: 0 | AJ71: 420 | AK71: 420 | AL71: 150000000 | AM71: 150000000 | AN71: 0 | AO71: 0 | AP71: =Z71*100/AA71 -> 32.52145
A72: DF | B72: BRB Participacoes | C72: BRB PAR | D72: 13.431.899/0001-49 | E72: ATIVA | F72: FINANCEIRO | G72: EMPRESA PÚBLICA | H72: S.A. | I72: FECHADO | J72: NÃO | K72: SIM | L72: NÃO DEPENDENTE | M72: 0 | N72: SIM | O72: NÃO | P72: NÃO | R72: 0 | S72: 0 | T72: 1032.94 | U72: 0 | V72: NÃO | W72: 0 | X72: 0 | Y72: 0 | Z72: 0 | AA72: 0 | AC72: 0 | AD72: 0 | AE72: 0 | AF72: 0 | AG72: 0 | AH72: 0 | AI72: 0 | AJ72: 0 | AK72: 0 | AL72: 0 | AM72: 0 | AN72: 0 | AO72: 0 | AP72: =Z72*100/AA72 -> #DIV/0!
A73: DF | B73: BRB Serviços | C73: BRB Serviços | D73: 12.875.569/0001-80 | E73: ATIVA | F73: FINANCEIRO | G73: SOCIEDADE DE ECONOMIA MISTA | H73: S.A. | I73: FECHADO | J73: NÃO | K73: SIM | L73: NÃO DEPENDENTE | M73: 1166 | N73: SIM | O73: SIM | P73: NÃO | R73: 100549726 | S73: 72223772 | T73: 1.0319979e+08 | U73: 0 | V73: SIM | W73: 673442.27 | X73: 66872.98 | Y73: 0 | Z73: -26500068 | AA73: 28906244 | AC73: 0 | AD73: 0 | AE73: 0 | AF73: 0 | AG73: 0 | AH73: 0 | AI73: 0 | AJ73: 248000 | AK73: 248000 | AL73: 29744203 | AM73: 30000000 | AN73: 255797 | AO73: 0 | AP73: =Z73*100/AA73 -> -91.67593
A74: DF | B74: Cartão BRB | C74: BRBCARD | D74: 01.984.199/0001-00 | E74: ATIVA | F74: FINANCEIRO | G74: SOCIEDADE DE ECONOMIA MISTA | H74: S.A. | I74: FECHADO | J74: NÃO | K74: SIM | L74: NÃO DEPENDENTE | M74: 263 | N74: SIM | O74: SIM | P74: NÃO | Q74: https://www,brbcard,com,br/wp-content/uploads/2024/09/Carta-Anual-Poli4cas-Publicas-Gov-Corpora4va-2023-vf,pdf | R74: 2.9950892e+08 | S74: 55122089 | T74: 6.8753458e+08 | U74: 1.2404669e+08 | V74: SIM | W74: 428014.97 | X74: 209404.05 | Y74: 311854.32 | Z74: 36771133 | AA74: 5.8667227e+08 | AC74: 0 | AD74: 0 | AE74: 0 | AF74: 0 | AG74: 0 | AH74: 0 | AI74: 0 | AJ74: 3941551 | AK74: 3941551 | AL74: 5.7479121e+08 | AM74: 5.2203472e+08 | AN74: 0 | AO74: 0 | AP74: =Z74*100/AA74 -> 6.2677469
A75: DF | B75: Companhia de Saneamento Ambiental do Distrito Federal | C75: CAESB | D75: 00.082.024/0001-37 | E75: ATIVA | F75: SANEAMENTO | G75: SOCIEDADE DE ECONOMIA MISTA | H75: S.A. | I75: FECHADO | J75: NÃO | K75: NÃO | L75: NÃO DEPENDENTE | M75: 1997 | N75: SIM | O75: SIM | P75: SIM | Q75: https://www,caesb,df,gov,br/empresa/governanca-corporativa/carta-anual,html | R75: 2.2927561e+09 | S75: 9.7515031e+08 | T75: 2.5299069e+09 | U75: 3.7253331e+08 | V75: SIM | W75: 896119.71 | X75: 24792.52 | Y75: 25755.86 | Z75: 90460720 | AA75: 2248240620 | AC75: 0 | AD75: 0 | AE75: 0 | AF75: 64529800 | AG75: 43607600 | AH75: 0 | AI75: 0 | AJ75: 929456430 | AK75: 929456430 | AL75: 2074068686 | AM75: 2074068686 | AN75: 0 | AO75: 0 | AP75: =Z75*100/AA75 -> 4.0236227
A76: DF | B76: Centrais de Abastecimento do Distrito Federal | C76: CEASA DF | D76: 00.314.310/0001-80 | E76: ATIVA | F76: ABASTECIMENTO DE ALIMENTOS E OUTROS INSUMOS | G76: SOCIEDADE DE ECONOMIA MISTA | H76: S.A. | I76: FECHADO | J76: NÃO | K76: NÃO | L76: NÃO DEPENDENTE | M76: 60 | N76: SIM | O76: SIM | P76: NÃO | R76: 15958077 | S76: 15729760 | T76: 20282200 | U76: 0 | V76: NÃO | W76: 327915.97 | X76: 0 | Y76: 0 | Z76: 1866174 | AA76: 60377797 | AC76: 0 | AD76: 0 | AE76: 0 | AF76: 0 | AG76: 0 | AH76: 0 | AI76: 18000000 | AJ76: 32197937 | AK76: 32197937 | AL76: 32197937 | AM76: 32197937 | AN76: 0 | AO76: 0 | AP76: =Z76*100/AA76 -> 3.0908282
A77: DF | B77: Companhia Energética de Brasília | C77: CEB | D77: 00.070.698/0001-11 | E77: ATIVA | F77: ENERGIA | G77: SOCIEDADE DE ECONOMIA MISTA | H77: S.A. | I77: ABERTO | J77: SIM | K77: NÃO | L77: NÃO DEPENDENTE | M77: 120 | N77: SIM | O77: SIM | P77: SIM | Q77: https://www,ceb,com,br/Download,aspx?Arquivo=8AtZ9IcMZPUukeHBXSgE3w==&IdCanal=D0mlLqYnKldOCQKkP4Skqg== | R77: 31181843 | S77: 35837829 | T77: 64043261 | U77: 0 | V77: SIM | W77: 716384.41 | X77: 104728.96 | Y77: 21395.24 | Z77: 1.7422804e+08 | AA77: 1.065393e+09 | AC77: 94835083 | AD77: 0 | AE77: 0 | AF77: 0 | AG77: 0 | AH77: 0 | AI77: 0 | AJ77: 57773215 | AK77: 57773215 | AL77: 5.6602536e+08 | AM77: 5.6602536e+08 | AN77: 0 | AO77: 0 | AP77: =Z77*100/AA77 -> 16.353406
A78: DF | B78: CEB Iluminação Pública e Serviços | C78: CEB IPES | D78: 39.683.726/0001-01 | E78: ATIVA | F78: ENERGIA | G78: SOCIEDADE DE ECONOMIA MISTA | H78: S.A. | I78: FECHADO | J78: NÃO | K78: SIM | L78: NÃO DEPENDENTE | M78: 77 | N78: NÃO | O78: SIM | P78: NÃO | R78: 51831969 | S78: 19629027 | T78: 60332472 | U78: 327950 | V78: SIM | W78: 591686.76 | X78: 75404.84 | Y78: 21395.23 | Z78: 14013462 | AA78: 1.975087e+08 | AC78: 5170071 | AD78: 0 | AE78: 0 | AF78: 0 | AG78: 0 | AH78: 0 | AI78: 0 | AJ78: 1.7408058e+08 | AK78: 1.7408058e+08 | AL78: 1.7408058e+08 | AM78: 1.7408058e+08 | AN78: 0 | AO78: 0 | AP78: =Z78*100/AA78 -> 7.0951112
A79: DF | B79: CEB Lajeado | C79: CEB L | D79: 03.677.638/0001-50 | E79: ATIVA | F79: ENERGIA | G79: SOCIEDADE DE ECONOMIA MISTA | H79: S.A. | I79: FECHADO | J79: NÃO | K79: SIM | L79: NÃO DEPENDENTE | M79: 16 | N79: SIM | O79: SIM | P79: SIM | R79: 2.3436596e+08 | S79: 6859542.1 | T79: 1.0902097e+08 | U79: 0 | V79: SIM | W79: 715997.49 | X79: 0 | Y79: 13777.72 | Z79: 1.0498987e+08 | AA79: 3.875624e+08 | AC79: 0 | AD79: 0 | AE79: 0 | AF79: 0 | AG79: 0 | AH79: 0 | AI79: 0 | AJ79: 136850013 | AK79: 136850013 | AL79: 1.12284e+08 | AM79: 1.12284e+08 | AN79: 0 | AO79: 0 | AP79: =Z79*100/AA79 -> 27.089798
A80: DF | B80: CEB Geração | C80: CEBG | D80: 04.232.314/0001-70 | E80: ATIVA | F80: ENERGIA | G80: SOCIEDADE DE ECONOMIA MISTA | H80: S.A. | I80: FECHADO | J80: NÃO | K80: SIM | L80: NÃO DEPENDENTE | M80: 17 | N80: NÃO | O80: SIM | P80: SIM | Q80: https://www,ceb,com,br/Documentos,aspx?IdCanal=hD8pqKNE+C5Xrd39y4J+Tg== | R80: 10065219 | S80: 5831363.8 | T80: 14208086 | U80: 768850.49 | V80: SIM | W80: 624558.16 | X80: 79594 | Y80: 21329.22 | Z80: -629528.41 | AA80: 14520897 | AC80: 0 | AD80: 0 | AE80: 0 | AF80: 0 | AG80: 0 | AH80: 0 | AI80: 0 | AJ80: 7575212 | AK80: 7575212 | AL80: 7575212.6 | AM80: 7575212.6 | AN80: 0 | AO80: 0 | AP80: =Z80*100/AA80 -> -4.3353273
A81: DF | B81: Companhia Brasiliense de Gás | C81: CEBGAS | D81: 04.363.670/0001-23 | E81: ATIVA | F81: GÁS E DERIVADOS | G81: SOCIEDADE DE ECONOMIA MISTA | H81: S.A. | I81: FECHADO | J81: NÃO | K81: NÃO | L81: NÃO DEPENDENTE | M81: 1 | N81: SIM | O81: SIM | P81: NÃO | R81: 386191.02 | S81: 378614.51 | T81: 1290646.2 | U81: 0 | V81: NÃO | W81: 199511.49 | X81: 0 | Y81: 0 | Z81: -1029544.4 | AA81: -1493762.4 | AC81: 0 | AD81: 0 | AE81: 0 | AF81: 0 | AG81: 0 | AH81: 318750 | AI81: 162500 | AJ81: 1930250 | AK81: 1930250 | AL81: 1930250 | AM81: 1930250 | AN81: 0 | AO81: 0 | AP81: =Z81*100/AA81 -> 68.922902
A82: DF | B82: CEB Participações | C82: CEBPAR | D82: 03.682.014/0001-20 | E82: ATIVA | F82: ENERGIA | G82: SOCIEDADE DE ECONOMIA MISTA | H82: S.A. | I82: FECHADO | J82: NÃO | K82: SIM | L82: NÃO DEPENDENTE | M82: 18 | N82: NÃO | O82: SIM | P82: NÃO | R82: 24475006 | S82: 3619219.3 | T82: 13752869 | U82: 1821286.3 | V82: SIM | W82: 610803.22 | X82: 0 | Y82: 0 | Z82: 17304562 | AA82: 42329035 | AC82: 0 | AD82: 0 | AE82: 0 | AF82: 0 | AG82: 0 | AH82: 0 | AI82: 0 | AJ82: 21270415 | AK82: 21270415 | AL82: 21270415 | AM82: 21270415 | AN82: 0 | AO82: 0 | AP82: =Z82*100/AA82 -> 40.881068
A83: DF | B83: PROFLORA | C83: PROFLORA | D83: 00.338.079/0001-65 | E83: EM LIQUIDAÇÃO | F83: DESENVOLVIMENTO REGIONAL | G83: SOCIEDADE DE ECONOMIA MISTA | H83: S.A. | I83: FECHADO | J83: NÃO | K83: NÃO | L83: NÃO DEPENDENTE | M83: 7 | N83: SIM | O83: SIM | P83: NÃO | R83: 1385020.3 | S83: 1209779.5 | T83: 1479461.8 | U83: 0 | V83: NÃO | W83: 187442.3 | X83: 0 | Y83: 0 | Z83: -7200331.1 | AA83: 8244998.9 | AC83: 0 | AD83: 0 | AE83: 0 | AF83: 0 | AG83: 0 | AH83: 0 | AI83: 0 | AJ83: 4024.42 | AK83: 4024.42 | AL83: 4024.42 | AM83: 4024.42 | AN83: 0 | AO83: 0 | AP83: =Z83*100/AA83 -> -87.32968
A84: DF | B84: Companhia Imobiliária de Brasília | C84: Terracap | D84: 00.359.877/0001-73 | E84: ATIVA | F84: HABITAÇÃO E URBANIZAÇÃO | G84: EMPRESA PÚBLICA | H84: S.A. | I84: FECHADO | J84: NÃO | K84: NÃO | L84: NÃO DEPENDENTE | M84: 1100 | N84: SIM | O84: SIM | P84: SIM | Q84: https://www,terracap,df,gov,br/index,php/carta-deservico/imprimaaqui-a-carta-deservico | R84: 6.5311442e+08 | S84: 3.3131808e+08 | T84: 8.1831793e+08 | U84: 241820000 | V84: SIM | W84: 928239.58 | X84: 32984.3 | Y84: 77201.9 | Z84: -1.6520351e+08 | AA84: 5.2870569e+09 | AC84: 0 | AD84: 0 | AE84: 0 | AF84: 0 | AG84: 0 | AH84: 0 | AI84: 0 | AJ84: 255000 | AK84: 255000 | AL84: 1.8510785e+09 | AM84: 1.8510785e+09 | AN84: 0 | AO84: 0 | AP84: =Z84*100/AA84 -> -3.1246781
A85: ES | B85: Ceasa - Centrais de Abastecimento do Espirito Santo S/A | C85: CEASA | D85: 27.064.062/0001-13 | E85: ATIVA | F85: ABASTECIMENTO DE ALIMENTOS E OUTROS INSUMOS | G85: SOCIEDADE DE ECONOMIA MISTA | H85: S.A. | I85: FECHADO | J85: NÃO | K85: NÃO | L85: DEPENDENTE | M85: 158 | N85: SIM | O85: SIM | P85: NÃO | Q85: https://ioes,dio,es,gov,br/portal/visualizacoes/pdf/10176#/p:47/e:10176?find=ceasa | R85: 19359297 | S85: 14516509 | T85: 23723451 | U85: 0 | V85: NÃO | W85: 4737029.6 | X85: 0 | Y85: 0 | Z85: 794552.61 | AA85: 10901902 | AB85: 0 | AC85: 0 | AD85: 0 | AE85: 0 | AF85: 0 | AG85: 0 | AH85: 0 | AI85: 0 | AJ85: 3159556 | AK85: 3159556 | AL85: 3159556.7 | AM85: 3159556.7 | AN85: 0 | AO85: 0 | AP85: =Z85*100/AA85 -> 7.2882017
A86: ES | B86: Bandes - Banco de Desenvolvimento do Espírito Santo S/A | C86: BANDES | D86: 28.145.829/0001-00 | E86: ATIVA | F86: FINANCEIRO | G86: SOCIEDADE DE ECONOMIA MISTA | H86: S.A. | I86: FECHADO | J86: NÃO | K86: NÃO | L86: NÃO DEPENDENTE | M86: 190 | N86: SIM | O86: SIM | P86: SIM | Q86: https://www,bandes,com,br/Site/Dinamico/Show/933/Governanca-Corporativa# | R86: 2.2843852e+08 | S86: 54800725 | T86: 1.8855088e+08 | U86: 4083775 | V86: SIM | W86: 35566517 | X86: 4879123 | Y86: 9110878.4 | Z86: 99380416 | AA86: 5.2040998e+08 | AB86: 5.2040998e+08 | AC86: 0 | AD86: 0 | AE86: 0 | AF86: 0 | AG86: 0 | AH86: 0 | AI86: 0 | AJ86: 25246979553 | AK86: 26742192753 | AL86: 439371000 | AM86: 4.6338e+08 | AN86: 0 | AO86: 0 | AP86: =Z86*100/AA86 -> 19.096562
A87: ES | B87: Banestes - Banco do Estado do Espirito Santo | C87: BANESTES | D87: 28.127.603/0001-78 | E87: ATIVA | F87: FINANCEIRO | G87: SOCIEDADE DE ECONOMIA MISTA | H87: S.A. | I87: ABERTO | J87: SIM | K87: NÃO | L87: NÃO DEPENDENTE | M87: 2164 | N87: SIM | O87: SIM | P87: SIM | Q87: https://ri,banestes,com,br | R87: 1.1853401e+09 | S87: 4.9193627e+08 | T87: 5.0652512e+09 | U87: 2.4996539e+08 | V87: SIM | W87: 763612.13 | X87: 158498.22 | Y87: 0 | Z87: 3.9248711e+08 | AA87: 2.3572137e+09 | AB87: 2706860802 | AC87: 1.9996934e+08 | AD87: 0 | AE87: 0 | AF87: 0 | AG87: 0 | AH87: 0 | AI87: 0 | AJ87: 291793529 | AK87: 291793529 | AL87: 1477920000 | AM87: 1600000000 | AN87: 0 | AO87: 0 | AP87: =Z87*100/AA87 -> 16.650468
A88: ES | B88: Cesan - Companhia Espirito Santense de Saneamento | C88: CESAN | D88: 28.151.363/0001-47 | E88: ATIVA | F88: SANEAMENTO | G88: SOCIEDADE DE ECONOMIA MISTA | H88: S.A. | I88: FECHADO | J88: NÃO | K88: NÃO | L88: NÃO DEPENDENTE | M88: 1274 | N88: SIM | O88: SIM | P88: SIM | Q88: https://www,cesan,com,br/wp-content/uploads/2024/07/Carta-Anual-de-Politicas-Publicas-3,pdf | R88: 1.2759444e+09 | S88: 3.1513607e+08 | T88: 1.2006939e+09 | U88: 0 | V88: SIM | W88: 722809.61 | X88: 54781.47 | Y88: 91704.99 | Z88: 2.0243866e+08 | AA88: 4218159000 | AB88: 0 | AC88: 0 | AD88: 0 | AE88: 0 | AF88: 0 | AG88: 0 | AH88: 249280703 | AI88: 1.7928997e+08 | AJ88: 3015250810 | AK88: 3413141853 | AL88: 390685165 | AM88: 397891043 | AN88: 0 | AO88: 0 | AP88: =Z88*100/AA88 -> 4.7992184
A89: ES | B89: Ceturb - Companhia Estadual de Transportes Coletivos de Passageiros do Espirito Santo | C89: CETURB | D89: 28.503.894/0001-51 | E89: ATIVA | F89: TRANSPORTE | G89: EMPRESA PÚBLICA | H89: S.A. | I89: FECHADO | J89: NÃO | K89: NÃO | L89: NÃO DEPENDENTE | M89: 244 | N89: SIM | O89: SIM | P89: NÃO | Q89: https://centraldebalancos,estaleiro,serpro,gov,br/centraldebalancos/#/ver-demonstracao/212163 | R89: 85695694 | S89: 36943692 | T89: 87620575 | U89: 799246.52 | V89: NÃO | W89: 453088.04 | X89: 0 | Y89: 0 | Z89: 2119642.4 | AA89: 21912715 | AB89: 0 | AC89: 0 | AD89: 0 | AE89: 0 | AF89: 0 | AG89: 0 | AH89: 0 | AI89: 1500000 | AJ89: 93473015 | AK89: 120370891 | AL89: 93473015 | AM89: 1.2037089e+08 | AN89: 1.0652698e+08 | AO89: 79629108 | AP89: =Z89*100/AA89 -> 9.6731163
A90: ES | B90: COHAB - Companhia de Habitação e Urbanização do Estado do Espirito Santo - Em Liquidação | C90: COHAB | D90: 28.139.012/0001-10 | E90: EM LIQUIDAÇÃO | F90: HABITAÇÃO E URBANIZAÇÃO | G90: SOCIEDADE DE ECONOMIA MISTA | H90: S.A. | I90: FECHADO | J90: NÃO | K90: NÃO | L90: NÃO DEPENDENTE | M90: 20 | N90: SIM | O90: SIM | P90: SIM | Q90: https://seger,es,gov,br/autarquias | R90: 3827365.2 | S90: 1430113.2 | T90: 3974715.2 | U90: 0 | V90: NÃO | W90: 95433.59 | X90: 0 | Y90: 632934.79 | Z90: -147350.05 | AA90: 14717292 | AB90: 14717292 | AC90: 0 | AD90: 0 | AE90: 0 | AF90: 0 | AG90: 0 | AH90: 0 | AI90: 0 | AJ90: 68602271495 | AK90: 68602271495 | AL90: 4525000 | AM90: 4525000 | AN90: 0 | AO90: 0 | AP90: =Z90*100/AA90 -> -1.0012036
A91: ES | B91: Fundação Carmelia Maria de Souza Cultura e Comunicação Pública | C91: FUNDAÇÃO CARMELIA | D91: 54.715.094/0001-04 | E91: ATIVA | F91: COMUNICAÇÃO | G91: EMPRESA PÚBLICA | H91: LTDA | I91: FECHADO | J91: NÃO | K91: NÃO | L91: NÃO DEPENDENTE | M91: 30 | N91: SIM | O91: SIM | P91: NÃO | Q91: não se aplica | R91: 240576 | S91: 2240252.6 | T91: 2343475.6 | U91: 0 | V91: NÃO | W91: 1787799.9 | X91: 0 | Y91: 0 | Z91: 1815812.4 | AA91: 8445906.6 | AB91: 0 | AC91: 0 | AD91: 0 | AE91: 0 | AF91: 0 | AG91: 0 | AH91: 0 | AI91: 0 | AJ91: 0 | AK91: 0 | AL91: 0 | AM91: 10261719 | AN91: 0 | AO91: 42000000 | AP91: =Z91*100/AA91 -> 21.499319
A92: GO | B92: Agência Goiana de Habitação S/A | C92: AGEHAB | D92: 01.274.240/0001-47 | E92: ATIVA | F92: HABITAÇÃO E URBANIZAÇÃO | G92: SOCIEDADE DE ECONOMIA MISTA | H92: S.A. | I92: FECHADO | J92: NÃO | K92: NÃO | L92: DEPENDENTE | M92: 400 | N92: SIM | O92: SIM | P92: SIM | Q92: https://goias,gov,br/agehab/carta-anual-de-governanca-corporativa/ | R92: 3768285.3 | S92: 67137142 | T92: 6.0134887e+08 | U92: 2.9177899e+08 | V92: NÃO | W92: 1108154.3 | X92: 0 | Y92: 0 | Z92: 1.4695064e+08 | AA92: 5.2220426e+08 | AB92: 0 | AC92: 0 | AD92: 3.5185835e+08 | AE92: 3.128984e+08 | AF92: 0 | AG92: 0 | AH92: 0 | AI92: 0 | AJ92: 1.9604092e+08 | AK92: 1.9604092e+08 | AL92: 1.8716377e+08 | AM92: 1.8716377e+08 | AN92: 8877149.1 | AO92: 8877149.1 | AP92: =Z92*100/AA92 -> 28.140451
A93: GO | B93: Goiás Telecomunicções S/A | C93: GOIAS TELECOM | D93: 10.268.439/0001-53 | E93: ATIVA | F93: COMUNICAÇÃO | G93: SOCIEDADE DE ECONOMIA MISTA | H93: S.A. | I93: FECHADO | J93: NÃO | K93: NÃO | L93: DEPENDENTE | M93: 43 | N93: SIM | O93: SIM | P93: SIM | Q93: https://goiastelecom,go,gov,br | R93: -112059.96 | S93: 5762687.9 | T93: 6600428.4 | U93: 0 | V93: NÃO | W93: 509842.36 | X93: 0 | Y93: 0 | Z93: 1310016 | AA93: 1972373.9 | AB93: 0 | AC93: 0 | AD93: 4558969.2 | AE93: 8094138.9 | AF93: 0 | AG93: 0 | AH93: 0 | AI93: 0 | AJ93: 9000000 | AK93: 9000000 | AL93: 9000000 | AM93: 9000000 | AN93: 0 | AO93: 0 | AP93: =Z93*100/AA93 -> 66.41824
A94: GO | B94: Indústria Química do Estado de Goiás | C94: IQUEGO | D94: 01.541.283/0001-41 | E94: ATIVA | F94: SAÚDE | G94: SOCIEDADE DE ECONOMIA MISTA | H94: S.A. | I94: FECHADO | J94: NÃO | K94: NÃO | L94: DEPENDENTE | M94: 244 | N94: SIM | O94: SIM | P94: SIM | Q94: https://goias,gov,br/iquego/balancos-contabeis/ | R94: 3285584.5 | S94: 38864423 | T94: 54343376 | U94: 0 | V94: NÃO | W94: 240497.4 | X94: 0 | Y94: 0 | Z94: -185231.32 | AA94: -47199478 | AB94: 0 | AC94: 0 | AD94: 27650145 | AE94: 74543497 | AF94: 0 | AG94: 0 | AH94: 0 | AI94: 0 | AJ94: 239994409 | AK94: 239995200 | AL94: 240000000 | AM94: 223479277 | AN94: 16516253 | AO94: 16516253 | AP94: =Z94*100/AA94 -> 0.39244358
A95: GO | B95: Metrobus Transporte Coletivo S/A | C95: METROBUS | D95: 02.392.459/0001-03 | E95: ATIVA | F95: TRANSPORTE | G95: SOCIEDADE DE ECONOMIA MISTA | H95: S.A. | I95: FECHADO | J95: NÃO | K95: NÃO | L95: DEPENDENTE | M95: 633 | N95: SIM | O95: SIM | P95: NÃO | Q95: https://goias,gov,br/metrobus/ | R95: 1.3744039e+08 | S95: 46402937 | T95: 64601972 | U95: 0 | V95: NÃO | W95: 479198.33 | X95: 0 | Y95: 0 | Z95: -1963928.8 | AA95: 8758323.8 | AB95: 8758323.8 | AC95: 0 | AD95: 23951018 | AE95: 84446717 | AF95: 0 | AG95: 0 | AH95: 0 | AI95: 0 | AJ95: 2.2170247e+08 | AK95: 2.2170247e+08 | AL95: 2.2170247e+08 | AM95: 2.2170247e+08 | AN95: 0 | AO95: 2024 | AP95: =Z95*100/AA95 -> -22.423569
A96: GO | B96: Caixa Econômica do Estado de Goiás | C96: CAIXEGO | D96: 01.600.204/0001-26 | E96: EM LIQUIDAÇÃO | F96: FINANCEIRO | G96: EMPRESA PÚBLICA | H96: OUTRAS | I96: FECHADO | J96: NÃO | K96: NÃO | L96: NÃO DEPENDENTE | M96: 0 | N96: NÃO | O96: NÃO | P96: NÃO | R96: 0 | S96: 0 | T96: 0 | U96: 0 | V96: NÃO | W96: 0 | X96: 0 | Y96: 0 | Z96: 0 | AA96: -4.2519722e+08 | AB96: 0 | AC96: 0 | AD96: 0 | AE96: 0 | AF96: 0 | AG96: 0 | AH96: 0 | AI96: 0 | AJ96: 1 | AK96: 1 | AL96: 1.24 | AM96: 1.24 | AN96: 0 | AO96: 0 | AP96: =Z96*100/AA96 -> 0
A97: GO | B97: Centrais de Abastecimento de Goiás S/A | C97: CEASA-GO | D97: 01.098.797/0001-74 | E97: ATIVA | F97: ABASTECIMENTO DE ALIMENTOS E OUTROS INSUMOS | G97: SOCIEDADE DE ECONOMIA MISTA | H97: S.A. | I97: FECHADO | J97: NÃO | K97: NÃO | L97: NÃO DEPENDENTE | M97: 93 | N97: SIM | O97: SIM | P97: SIM | Q97: https://goias,gov,br/ceasa/carta-anual-de-governanca-corporativa/ | R97: 36113028 | S97: 14671227 | T97: 34890671 | U97: 1830220.8 | V97: NÃO | W97: 426408.06 | X97: 0 | Y97: 168386.46 | Z97: 823698.66 | AA97: 2.5220218e+08 | AB97: 0 | AC97: 0 | AD97: 0 | AE97: 0 | AF97: 0 | AG97: 0 | AH97: 0 | AI97: 0 | AJ97: 23435690 | AK97: 23376622 | AL97: 23376622 | AM97: 23435690 | AN97: 0 | AO97: 0 | AP97: =Z97*100/AA97 -> 0.32660251
A98: GO | B98: Companhia Celg de Participações | C98: CELGPAR | D98: 08.560.444/0001-93 | E98: ATIVA | F98: ENERGIA | G98: SOCIEDADE DE ECONOMIA MISTA | H98: S.A. | I98: ABERTO | J98: SIM | K98: NÃO | L98: NÃO DEPENDENTE | M98: 113 | N98: SIM | O98: SIM | P98: SIM | Q98: https://ri,celgpar,com/BuscaPagina,aspx?ID={41799EC4-9CB4-4F81-BC75-64087B8BE678} | R98: 19287585 | S98: 25061326 | T98: 58565486 | U98: 21027359 | V98: NÃO | W98: 888466.76 | X98: 0 | Y98: 0 | Z98: 37486205 | AA98: 7.8355891e+08 | AB98: 0 | AC98: 0 | AD98: 0 | AE98: 0 | AF98: 0 | AG98: 0 | AH98: 0 | AI98: 0 | AJ98: 79676502 | AK98: 79676502 | AL98: 6.023507e+08 | AM98: 6.023507e+08 | AN98: 0 | AO98: 0 | AP98: =Z98*100/AA98 -> 4.7840953
A99: GO | B99: Companhia Metropolitana de Transportes Coletivos | C99: CMTC | D99: 05.787.273/0001-41 | E99: ATIVA | F99: TRANSPORTE | G99: EMPRESA PÚBLICA | H99: OUTRAS | I99: FECHADO | J99: NÃO | K99: NÃO | L99: NÃO DEPENDENTE | M99: 94 | N99: SIM | O99: SIM | P99: NÃO | Q99: https://cmtcrmg,com,br/pasta/prestacao-de-contas/ | R99: 10685127 | S99: 10859558 | T99: 17278101 | U99: 0 | V99: NÃO | W99: 267005.07 | X99: 0 | Y99: 14836.94 | Z99: -6592973.2 | AA99: 1465632.2 | AB99: 0 | AC99: 0 | AD99: 0 | AE99: 0 | AF99: 0 | AG99: 0 | AH99: 0 | AI99: 3380000 | AJ99: 0 | AK99: 10000000 | AL99: 0 | AM99: 4130000 | AN99: 0 | AO99: 5870000 | AP99: =Z99*100/AA99 -> -449.83816
A100: GO | B100: Companhia de Desenvolvimento Econômico de Goiás | C100: CODEGO | D100: 01.285.170/0001-22 | E100: ATIVA | F100: DESENVOLVIMENTO REGIONAL | G100: SOCIEDADE DE ECONOMIA MISTA | H100: S.A. | I100: FECHADO | J100: NÃO | K100: NÃO | L100: NÃO DEPENDENTE | M100: 414 | N100: SIM | O100: SIM | P100: SIM | Q100: https://www,codego,com,br/acesso-a-informacao/carta-anual-de-politicas-publicas-e-governanca-corporativa/ | R100: 68588577 | S100: 58285765 | T100: 62508621 | U100: 0 | V100: NÃO | W100: 420000 | X100: 0 | Y100: 132000 | Z100: -52937445 | AA100: 220753873 | AB100: 0 | AC100: 0 | AD100: 0 | AE100: 0 | AF100: 0 | AG100: 0 | AH100: 0 | AI100: 0 | AJ100: 285854692 | AK100: 328022634 | AL100: 4.2044704e+08 | AM100: 481302976 | AN100: 0 | AO100: 0 | AP100: =Z100*100/AA100 -> -23.980302
...

Sheet ex2024 (fórmulas)
A1: Liana | B1: UF | C1: Estatal | D1: Sigla | E1: CNPJ | F1: Situação | G1: Setor | H1: Espécie | I1: Organização jurídica | J1: Tipo de Capital | K1: Listada em Bolsa | L1: É Subsidiária | M1: Dependência | N1: Número de Empregados (incluindo temporários e terceirizados) | O1: Checagem de empragados | P1: Possui Conselho de Administração | Q1: Possui Conselho Fiscal | R1: Possui Comitê de Autidoria | S1: Link Carta Anual | T1: Receita Líquida Operacional | U1: Despesa com Pessoal, incluindo temporários e terceirizados (por competência) | V1: Checagem de Despesa com pessoal | W1: Despesa Total (por competência) | X1: Investimento (por competência) | Y1: Foi Distribuído PLR ou RVA no exercício | Z1: Remuneração bruta total paga no ano (empregado que recebeu a maior remuneração) | AA1: PLR ou RVA pagos no ano (empregado que recebeu a maior remuneração) | AB1: Indenizações pagas no ano (empregado que recebeu a maior remuneração) | AC1: Lucro / Prejuízo Líquido do Exercício | AD1: Distribuiu PLR tendo prejuízo | AE1: Patrimônio Líquido | AF1: Valor de Mercado | AG1: Dividendos e Juros sobre Capital Próprio pagos ao Tesouro Estadual / Municipal (pago) | AH1: Subvenções - Exercício anterior | AI1: Subvenções - Exercício | AJ1: INDÍCIO DE DEPENDÊNCIA - SUBVENÇÃO | AK1: Passivos - Exercício anterior | AL1: Passivos - exercício | AM1: Reforço de Capital - Exercício anterior | AN1: Reforço de Capital - Exercício | AO1: Ações ou cotas - Exercício anterior | AP1: Ações ou cotas - Exercício | AQ1: Variação das Ações | AR1: Capital Social Integralizado - Exercício anterior | AS1: Capital Social Integralizado - Exercício | AT1: Capital Social a Integralizar -Exercício anterior | AU1: Capital Social a Integralizar - Exercício | AV1: Variação do Capital Social | AW1: Aumento do Capital ou Participação Acionária | AX1: Não dependente com aporte de capital | AY1: INDÍCIO DE DEPENDÊNCIA - APORTE DE CAPITAL | AZ1: Rentabilidade
B2: AC | C2: Empresa de Processamento de Dados do Acre - ACREDATA | D2: ACREDATA | E2: 04.088.985/0001-00 | F2: ATIVA | G2: INFORMÁTICA E TECNOLOGIA DA INFORMAÇÃO | H2: EMPRESA PÚBLICA | I2: S.A. | J2: FECHADO | K2: NÃO | L2: NÃO | M2: DEPENDENTE | N2: 84 | O2: =IF(AND(F2="ATIVA",VALUE(N2)=0),"VERIFICAR","OK") -> OK | P2: SIM | Q2: SIM | R2: NÃO | T2: 13107416 | U2: 6325167.2 | V2: =IF(AND(VALUE(N2)=0,VALUE(U2)>0),"VERIFICAR","OK") -> OK | W2: 13107416 | X2: 0 | Y2: SIM | Z2: 0 | AA2: 0 | AB2: 0 | AC2: 11811972 | AD2: =IF(AND(Y2="SIM",VALUE(AC2)<0),"VERIFICAR","OK") -> OK | AE2: 1.037203e+08 | AF2: 0 | AG2: 0 | AH2: 11684206 | AI2: 13107416 | AJ2: =IF(AND(M2="NÃO DEPENDENTE",VALUE(AI2)>0),"INDÍCIO DE DEPENDÊNCIA POR SUBVENÇÃO","OK") -> OK | AK2: 0 | AL2: 0 | AM2: 0 | AN2: 0 | AO2: 4396687.6 | AP2: 4396687.6 | AQ2: =AP2-AO2 -> 0 | AR2: 4396687.6 | AS2: 4396687.6 | AT2: 0 | AU2: 0 | AV2: =(AS2-AR2)+(AU2) -> 0 | AW2: =IF(OR(VALUE(AQ2)>0,VALUE(AV2)>0),"SIM","NÃO") -> NÃO | AX2: =IF(AND(M2="NÃO DEPENDENTE",VALUE(AN2)>0),"VER CAPITAL","OK") -> OK | AY2: =IF(AND(AX2="VER CAPITAL",AW2="NÃO"),"INDÍCIO DE DEPENDÊNCIA POR CAPITAL","OK") -> OK | AZ2: =AC2*100/AE2 -> 11.388293
B3: AC | C3: Agencia de Negócios do Estado do Acre - ANAC | D3: ANAC | E3: 05.899.982/0001-19 | F3: ATIVA | G3: OUTROS | H3: SOCIEDADE DE ECONOMIA MISTA | I3: S.A. | J3: FECHADO | K3: NÃO | L3: NÃO | M3: DEPENDENTE | N3: 12 | O3: =IF(AND(F3="ATIVA",VALUE(N3)=0),"VERIFICAR","OK") -> OK | P3: SIM | Q3: SIM | R3: NÃO | T3: 8531737.6 | U3: 7155806.2 | V3: =IF(AND(VALUE(N3)=0,VALUE(U3)>0),"VERIFICAR","OK") -> OK | W3: 10314428 | X3: 0 | Y3: NÃO | Z3: 407932.32 | AA3: 0 | AB3: 99128.6 | AC3: -10051186 | AD3: =IF(AND(Y3="SIM",VALUE(AC3)<0),"VERIFICAR","OK") -> OK | AE3: 39712876 | AF3: 0 | AG3: 0 | AH3: 0 | AI3: 0 | AJ3: =IF(AND(M3="NÃO DEPENDENTE",VALUE(AI3)>0),"INDÍCIO DE DEPENDÊNCIA POR SUBVENÇÃO","OK") -> OK | AK3: 0 | AL3: 0 | AM3: 5563422.4 | AN3: 8531737.6 | AO3: 0 | AP3: 0 | AQ3: =AP3-AO3 -> 0 | AR3: 1.5620548e+08 | AS3: 1.6473722e+08 | AT3: 3794518.8 | AU3: 9762781.2 | AV3: =(AS3-AR3)+(AU3) -> 18294519 | AW3: =IF(OR(VALUE(AQ3)>0,VALUE(AV3)>0),"SIM","NÃO") -> SIM | AX3: =IF(AND(M3="NÃO DEPENDENTE",VALUE(AN3)>0),"VER CAPITAL","OK") -> OK | AY3: =IF(AND(AX3="VER CAPITAL",AW3="NÃO"),"INDÍCIO DE DEPENDÊNCIA POR CAPITAL","OK") -> OK | AZ3: =AC3*100/AE3 -> -25.309639
B4: AC | C4: Administradora da Zona de Processamento de Exportação do Acre - AZPE/AC | D4: AZPE | E4: 12.467.990/0001-51 | F4: ATIVA | G4: DESENVOLVIMENTO REGIONAL | H4: SOCIEDADE DE ECONOMIA MISTA | I4: S.A. | J4: FECHADO | K4: NÃO | L4: NÃO | M4: DEPENDENTE | N4: 0 | O4: =IF(AND(F4="ATIVA",VALUE(N4)=0),"VERIFICAR","OK") -> VERIFICAR | P4: SIM | Q4: SIM | R4: NÃO | T4: 0 | U4: 0 | V4: =IF(AND(VALUE(N4)=0,VALUE(U4)>0),"VERIFICAR","OK") -> OK | W4: 0 | X4: 0 | Y4: NÃO | Z4: 0 | AA4: 0 | AB4: 0 | AC4: 0 | AD4: =IF(AND(Y4="SIM",VALUE(AC4)<0),"VERIFICAR","OK") -> OK | AE4: 0 | AF4: 0 | AG4: 0 | AH4: 0 | AI4: 0 | AJ4: =IF(AND(M4="NÃO DEPENDENTE",VALUE(AI4)>0),"INDÍCIO DE DEPENDÊNCIA POR SUBVENÇÃO","OK") -> OK | AK4: 0 | AL4: 0 | AM4: 0 | AN4: 0 | AO4: 0 | AP4: 0 | AQ4: =AP4-AO4 -> 0 | AR4: 0 | AS4: 0 | AT4: 0 | AU4: 0 | AV4: =(AS4-AR4)+(AU4) -> 0 | AW4: =IF(OR(VALUE(AQ4)>0,VALUE(AV4)>0),"SIM","NÃO") -> NÃO | AX4: =IF(AND(M4="NÃO DEPENDENTE",VALUE(AN4)>0),"VER CAPITAL","OK") -> OK | AY4: =IF(AND(AX4="VER CAPITAL",AW4="NÃO"),"INDÍCIO DE DEPENDÊNCIA POR CAPITAL","OK") -> OK | AZ4: =AC4*100/AE4 -> #DIV/0!
B5: AC | C5: Banco do Estado do Acre - BANACRE | D5: BANACRE | E5: 04.064.077/0001-86 | F5: EM LIQUIDAÇÃO | G5: FINANCEIRO | H5: SOCIEDADE DE ECONOMIA MISTA | I5: S.A. | J5: FECHADO | K5: NÃO | L5: NÃO | M5: DEPENDENTE | N5: 12 | O5: =IF(AND(F5="ATIVA",VALUE(N5)=0),"VERIFICAR","OK") -> OK | P5: SIM | Q5: SIM | R5: NÃO | T5: 1776184.3 | U5: 1444341.2 | V5: =IF(AND(VALUE(N5)=0,VALUE(U5)>0),"VERIFICAR","OK") -> OK | W5: 1643842.5 | X5: 2348.39 | Y5: NÃO | Z5: 109184.47 | AA5: 0 | AB5: 0 | AC5: -2514600.7 | AD5: =IF(AND(Y5="SIM",VALUE(AC5)<0),"VERIFICAR","OK") -> OK | AE5: -1.9934195e+08 | AF5: 0 | AG5: 0 | AH5: 1780362.8 | AI5: 1774049 | AJ5: =IF(AND(M5="NÃO DEPENDENTE",VALUE(AI5)>0),"INDÍCIO DE DEPENDÊNCIA POR SUBVENÇÃO","OK") -> OK | AK5: 0 | AL5: 0 | AM5: 0 | AN5: 0 | AO5: 0 | AP5: 0 | AQ5: =AP5-AO5 -> 0 | AR5: 24365821 | AS5: 24365821 | AT5: 0 | AU5: 0 | AV5: =(AS5-AR5)+(AU5) -> 0 | AW5: =IF(OR(VALUE(AQ5)>0,VALUE(AV5)>0),"SIM","NÃO") -> NÃO | AX5: =IF(AND(M5="NÃO DEPENDENTE",VALUE(AN5)>0),"VER CAPITAL","OK") -> OK | AY5: =IF(AND(AX5="VER CAPITAL",AW5="NÃO"),"INDÍCIO DE DEPENDÊNCIA POR CAPITAL","OK") -> OK | AZ5: =AC5*100/AE5 -> 1.2614508
B6: AC | C6: Companhia de Armazéns e Entrepostos do Acre - CAGEACRE | D6: CAGEACRE | E6: 04.043.493/0001-06 | F6: ATIVA | G6: ABASTECIMENTO DE ALIMENTOS E OUTROS INSUMOS | H6: EMPRESA PÚBLICA | I6: OUTRAS | J6: FECHADO | K6: NÃO | L6: NÃO | M6: DEPENDENTE | N6: 155 | O6: =IF(AND(F6="ATIVA",VALUE(N6)=0),"VERIFICAR","OK") -> OK | P6: NÃO | Q6: SIM | R6: NÃO | T6: 14729465 | U6: 13419884 | V6: =IF(AND(VALUE(N6)=0,VALUE(U6)>0),"VERIFICAR","OK") -> OK | W6: 14759182 | X6: 0 | Y6: NÃO | Z6: 215350.25 | AA6: 0 | AB6: 548258.13 | AC6: 678045.71 | AD6: =IF(AND(Y6="SIM",VALUE(AC6)<0),"VERIFICAR","OK") -> OK | AE6: 7447035.2 | AF6: 0 | AG6: 0 | AH6: 19543507 | AI6: 14729465 | AJ6: =IF(AND(M6="NÃO DEPENDENTE",VALUE(AI6)>0),"INDÍCIO DE DEPENDÊNCIA POR SUBVENÇÃO","OK") -> OK | AK6: 305753.42 | AL6: 170846.03 | AM6: 0 | AN6: 0 | AO6: 727.45 | AP6: 727.45 | AQ6: =AP6-AO6 -> 0 | AR6: 8219091 | AS6: 8219091 | AT6: 0 | AU6: 0 | AV6: =(AS6-AR6)+(AU6) -> 0 | AW6: =IF(OR(VALUE(AQ6)>0,VALUE(AV6)>0),"SIM","NÃO") -> NÃO | AX6: =IF(AND(M6="NÃO DEPENDENTE",VALUE(AN6)>0),"VER CAPITAL","OK") -> OK | AY6: =IF(AND(AX6="VER CAPITAL",AW6="NÃO"),"INDÍCIO DE DEPENDÊNCIA POR CAPITAL","OK") -> OK | AZ6: =AC6*100/AE6 -> 9.1049081
B7: AC | C7: Companhia Agência de Desenvolvimento e Serviços Ambientais do Estado do Acre - CDSA | D7: CDSA | E7: 16.864.341/0001-45 | F7: ATIVA | G7: DESENVOLVIMENTO REGIONAL | H7: SOCIEDADE DE ECONOMIA MISTA | I7: S.A. | J7: FECHADO | K7: NÃO | L7: NÃO | M7: DEPENDENTE | N7: 13 | O7: =IF(AND(F7="ATIVA",VALUE(N7)=0),"VERIFICAR","OK") -> OK | P7: SIM | Q7: SIM | R7: NÃO | T7: 1521027 | U7: 1483227 | V7: =IF(AND(VALUE(N7)=0,VALUE(U7)>0),"VERIFICAR","OK") -> OK | W7: 1483227 | X7: 0 | Y7: NÃO | Z7: 233705.73 | AA7: 0 | AB7: 0 | AC7: -24631.91 | AD7: =IF(AND(Y7="SIM",VALUE(AC7)<0),"VERIFICAR","OK") -> OK | AE7: 3.0056081e+09 | AF7: 0 | AG7: 0 | AH7: 957768.34 | AI7: 1521027 | AJ7: =IF(AND(M7="NÃO DEPENDENTE",VALUE(AI7)>0),"INDÍCIO DE DEPENDÊNCIA POR SUBVENÇÃO","OK") -> OK | AK7: 973545.94 | AL7: 1483227 | AM7: 2447100 | AN7: 2400000 | AO7: 3003209100 | AP7: 3005609100 | AQ7: =AP7-AO7 -> 2400000 | AR7: 3003209100 | AS7: 3005609100 | AT7: 3397100 | AU7: 997100 | AV7: =(AS7-AR7)+(AU7) -> 3397100 | AW7: =IF(OR(VALUE(AQ7)>0,VALUE(AV7)>0),"SIM","NÃO") -> SIM | AX7: =IF(AND(M7="NÃO DEPENDENTE",VALUE(AN7)>0),"VER CAPITAL","OK") -> OK | AY7: =IF(AND(AX7="VER CAPITAL",AW7="NÃO"),"INDÍCIO DE DEPENDÊNCIA POR CAPITAL","OK") -> OK | AZ7: =AC7*100/AE7 -> -0.00081953166
B8: AC | C8: Companhia Industrial de Laticínios do Acre - CILA | D8: CILA | E8: 04.061.693/0001-83 | F8: ATIVA | G8: ABASTECIMENTO DE ALIMENTOS E OUTROS INSUMOS | H8: EMPRESA PÚBLICA | I8: S.A. | J8: FECHADO | K8: NÃO | L8: SIM | M8: DEPENDENTE | N8: 29 | O8: =IF(AND(F8="ATIVA",VALUE(N8)=0),"VERIFICAR","OK") -> OK | P8: SIM | Q8: SIM | R8: NÃO | T8: 2820871.2 | U8: 2497093.8 | V8: =IF(AND(VALUE(N8)=0,VALUE(U8)>0),"VERIFICAR","OK") -> OK | W8: 2820871.2 | X8: 1686.87 | Y8: NÃO | Z8: 2183003.7 | AA8: 0 | AB8: 0 | AC8: 142443.37 | AD8: =IF(AND(Y8="SIM",VALUE(AC8)<0),"VERIFICAR","OK") -> OK | AE8: -88773663 | AF8: 0 | AG8: 0 | AH8: 2317412.3 | AI8: 2820871.2 | AJ8: =IF(AND(M8="NÃO DEPENDENTE",VALUE(AI8)>0),"INDÍCIO DE DEPENDÊNCIA POR SUBVENÇÃO","OK") -> OK | AK8: 2147999.3 | AL8: 1996951.8 | AM8: 0 | AN8: 0 | AO8: 0 | AP8: 0 | AQ8: =AP8-AO8 -> 0 | AR8: 416.44 | AS8: 416.44 | AT8: 0 | AU8: 0 | AV8: =(AS8-AR8)+(AU8) -> 0 | AW8: =IF(OR(VALUE(AQ8)>0,VALUE(AV8)>0),"SIM","NÃO") -> NÃO | AX8: =IF(AND(M8="NÃO DEPENDENTE",VALUE(AN8)>0),"VER CAPITAL","OK") -> OK | AY8: =IF(AND(AX8="VER CAPITAL",AW8="NÃO"),"INDÍCIO DE DEPENDÊNCIA POR CAPITAL","OK") -> OK | AZ8: =AC8*100/AE8 -> -0.16045679
B9: AC | C9: Companhia de Desenvolvimento Industrial do Acre - CODISACRE | D9: CODISACRE | E9: 04.039.277/0001-89 | F9: ATIVA | G9: DESENVOLVIMENTO REGIONAL | H9: EMPRESA PÚBLICA | I9: OUTRAS | J9: FECHADO | K9: NÃO | L9: SIM | M9: DEPENDENTE | N9: 37 | O9: =IF(AND(F9="ATIVA",VALUE(N9)=0),"VERIFICAR","OK") -> OK | P9: SIM | Q9: SIM | R9: NÃO | T9: 5026604.3 | U9: 3944525.1 | V9: =IF(AND(VALUE(N9)=0,VALUE(U9)>0),"VERIFICAR","OK") -> OK | W9: 5010921 | X9: 244185.81 | Y9: NÃO | Z9: 198405.6 | AA9: 0 | AB9: 0 | AC9: 693377.74 | AD9: =IF(AND(Y9="SIM",VALUE(AC9)<0),"VERIFICAR","OK") -> OK | AE9: 6665321.6 | AF9: 0 | AG9: 0 | AH9: 4779201.4 | AI9: 5010921 | AJ9: =IF(AND(M9="NÃO DEPENDENTE",VALUE(AI9)>0),"INDÍCIO DE DEPENDÊNCIA POR SUBVENÇÃO","OK") -> OK | AK9: 410259.38 | AL9: 397316.62 | AM9: 0 | AN9: 0 | AO9: 0 | AP9: 0 | AQ9: =AP9-AO9 -> 0 | AR9: 3791691 | AS9: 3791691 | AT9: 0 | AU9: 0 | AV9: =(AS9-AR9)+(AU9) -> 0 | AW9: =IF(OR(VALUE(AQ9)>0,VALUE(AV9)>0),"SIM","NÃO") -> NÃO | AX9: =IF(AND(M9="NÃO DEPENDENTE",VALUE(AN9)>0),"VER CAPITAL","OK") -> OK | AY9: =IF(AND(AX9="VER CAPITAL",AW9="NÃO"),"INDÍCIO DE DEPENDÊNCIA POR CAPITAL","OK") -> OK | AZ9: =AC9*100/AE9 -> 10.402765
B10: AC | C10: Companhia de Habitação do Acre - COHAB/ACRE | D10: COHAB | E10: 04.066.007/0001-67 | F10: ATIVA | G10: HABITAÇÃO E URBANIZAÇÃO | H10: SOCIEDADE DE ECONOMIA MISTA | I10: OUTRAS | J10: FECHADO | K10: NÃO | L10: NÃO | M10: DEPENDENTE | N10: 63 | O10: =IF(AND(F10="ATIVA",VALUE(N10)=0),"VERIFICAR","OK") -> OK | P10: SIM | Q10: SIM | R10: NÃO | T10: 7431327.1 | U10: 6325167.2 | V10: =IF(AND(VALUE(N10)=0,VALUE(U10)>0),"VERIFICAR","OK") -> OK | W10: 9499084.6 | X10: 0 | Y10: NÃO | Z10: 270124.92 | AA10: 0 | AB10: 0 | AC10: 3953141.1 | AD10: =IF(AND(Y10="SIM",VALUE(AC10)<0),"VERIFICAR","OK") -> OK | AE10: 79307669 | AF10: 0 | AG10: 0 | AH10: 6949505.2 | AI10: 8771679.9 | AJ10: =IF(AND(M10="NÃO DEPENDENTE",VALUE(AI10)>0),"INDÍCIO DE DEPENDÊNCIA POR SUBVENÇÃO","OK") -> OK | AK10: 8064674.4 | AL10: 7204783.3 | AM10: 0 | AN10: 0 | AO10: 0.99 | AP10: 0.99 | AQ10: =AP10-AO10 -> 0 | AR10: 62840607 | AS10: 62840607 | AT10: 0 | AU10: 0 | AV10: =(AS10-AR10)+(AU10) -> 0 | AW10: =IF(OR(VALUE(AQ10)>0,VALUE(AV10)>0),"SIM","NÃO") -> NÃO | AX10: =IF(AND(M10="NÃO DEPENDENTE",VALUE(AN10)>0),"VER CAPITAL","OK") -> OK | AY10: =IF(AND(AX10="VER CAPITAL",AW10="NÃO"),"INDÍCIO DE DEPENDÊNCIA POR CAPITAL","OK") -> OK | AZ10: =AC10*100/AE10 -> 4.9845635
B11: AC | C11: Companhia de Colonização do Acre - COLONACRE | D11: COLONACRE | E11: 04.039.673/0001-06 | F11: EM LIQUIDAÇÃO | G11: DESENVOLVIMENTO REGIONAL | H11: EMPRESA PÚBLICA | I11: OUTRAS | J11: FECHADO | K11: NÃO | L11: SIM | M11: DEPENDENTE | N11: 17 | O11: =IF(AND(F11="ATIVA",VALUE(N11)=0),"VERIFICAR","OK") -> OK | P11: NÃO | Q11: SIM | R11: NÃO | T11: 1705223.6 | U11: 1658046.4 | V11: =IF(AND(VALUE(N11)=0,VALUE(U11)>0),"VERIFICAR","OK") -> OK | W11: 1658621.4 | X11: 0 | Y11: NÃO | Z11: 1040941.4 | AA11: 0 | AB11: 0 | AC11: 46963.39 | AD11: =IF(AND(Y11="SIM",VALUE(AC11)<0),"VERIFICAR","OK") -> OK | AE11: 5690130.8 | AF11: 0 | AG11: 0 | AH11: 1397964.1 | AI11: 1705223.6 | AJ11: =IF(AND(M11="NÃO DEPENDENTE",VALUE(AI11)>0),"INDÍCIO DE DEPENDÊNCIA POR SUBVENÇÃO","OK") -> OK | AK11: 0 | AL11: 0 | AM11: 0 | AN11: 0 | AO11: 3958917.2 | AP11: 3595917.2 | AQ11: =AP11-AO11 -> -363000 | AR11: 3598917.2 | AS11: 3598917.2 | AT11: 0 | AU11: 0 | AV11: =(AS11-AR11)+(AU11) -> 0 | AW11: =IF(OR(VALUE(AQ11)>0,VALUE(AV11)>0),"SIM","NÃO") -> NÃO | AX11: =IF(AND(M11="NÃO DEPENDENTE",VALUE(AN11)>0),"VER CAPITAL","OK") -> OK | AY11: =IF(AND(AX11="VER CAPITAL",AW11="NÃO"),"INDÍCIO DE DEPENDÊNCIA POR CAPITAL","OK") -> OK | AZ11: =AC11*100/AE11 -> 0.82534816
B12: AC | C12: Empresa de Assistência Técnica e Extensão Rural do Acre - EMATER | D12: EMATER | E12: 04.044.244/0001-27 | F12: ATIVA | G12: PESQUISA E ASSISTÊNCIA TÉCNICA AGROPECUÁRIA | H12: EMPRESA PÚBLICA | I12: OUTRAS | J12: FECHADO | K12: NÃO | L12: NÃO | M12: DEPENDENTE | N12: 152 | O12: =IF(AND(F12="ATIVA",VALUE(N12)=0),"VERIFICAR","OK") -> OK | P12: SIM | Q12: SIM | R12: NÃO | T12: 23737121 | U12: 18707804 | V12: =IF(AND(VALUE(N12)=0,VALUE(U12)>0),"VERIFICAR","OK") -> OK | W12: 22994301 | X12: 0 | Y12: NÃO | Z12: 349852.72 | AA12: 0 | AB12: 5040 | AC12: 167735.68 | AD12: =IF(AND(Y12="SIM",VALUE(AC12)<0),"VERIFICAR","OK") -> OK | AE12: -8249.79 | AF12: 0 | AG12: 0 | AH12: 21676919 | AI12: 23737121 | AJ12: =IF(AND(M12="NÃO DEPENDENTE",VALUE(AI12)>0),"INDÍCIO DE DEPENDÊNCIA POR SUBVENÇÃO","OK") -> OK | AK12: 0 | AL12: 0 | AM12: 2052870.8 | AN12: 2149510.2 | AO12: 0 | AP12: 0 | AQ12: =AP12-AO12 -> 0 | AR12: 0 | AS12: 0 | AT12: 0 | AU12: 0 | AV12: =(AS12-AR12)+(AU12) -> 0 | AW12: =IF(OR(VALUE(AQ12)>0,VALUE(AV12)>0),"SIM","NÃO") -> NÃO | AX12: =IF(AND(M12="NÃO DEPENDENTE",VALUE(AN12)>0),"VER CAPITAL","OK") -> OK | AY12: =IF(AND(AX12="VER CAPITAL",AW12="NÃO"),"INDÍCIO DE DEPENDÊNCIA POR CAPITAL","OK") -> OK | AZ12: =AC12*100/AE12 -> -2033.2115
B13: AC | C13: Companhia de Saneamento do Acre - SANACRE | D13: SANACRE | E13: 04.003.232/0001-54 | F13: ATIVA | G13: SANEAMENTO | H13: SOCIEDADE DE ECONOMIA MISTA | I13: OUTRAS | J13: FECHADO | K13: NÃO | L13: NÃO | M13: DEPENDENTE | N13: 189 | O13: =IF(AND(F13="ATIVA",VALUE(N13)=0),"VERIFICAR","OK") -> OK | P13: SIM | Q13: SIM | R13: NÃO | T13: 0 | U13: 22880993 | V13: =IF(AND(VALUE(N13)=0,VALUE(U13)>0),"VERIFICAR","OK") -> OK | W13: 22972686 | X13: 0 | Y13: NÃO | Z13: 0 | AA13: 0 | AB13: 0 | AC13: 91692.53 | AD13: =IF(AND(Y13="SIM",VALUE(AC13)<0),"VERIFICAR","OK") -> OK | AE13: 19805481 | AF13: 0 | AG13: 0 | AH13: 3364776.2 | AI13: 3547857.4 | AJ13: =IF(AND(M13="NÃO DEPENDENTE",VALUE(AI13)>0),"INDÍCIO DE DEPENDÊNCIA POR SUBVENÇÃO","OK") -> OK | AK13: 0 | AL13: 0 | AM13: 0 | AN13: 0 | AO13: 0 | AP13: 0 | AQ13: =AP13-AO13 -> 0 | AR13: 0 | AS13: 0 | AT13: 0 | AU13: 0 | AV13: =(AS13-AR13)+(AU13) -> 0 | AW13: =IF(OR(VALUE(AQ13)>0,VALUE(AV13)>0),"SIM","NÃO") -> NÃO | AX13: =IF(AND(M13="NÃO DEPENDENTE",VALUE(AN13)>0),"VER CAPITAL","OK") -> OK | AY13: =IF(AND(AX13="VER CAPITAL",AW13="NÃO"),"INDÍCIO DE DEPENDÊNCIA POR CAPITAL","OK") -> OK | AZ13: =AC13*100/AE13 -> 0.46296543
B14: AL | C14: Agência de Fomento de Alagoas - Desenvolve | D14: AFAL | E14: 10.769.660/0001-95 | F14: ATIVA | G14: FINANCEIRO | H14: SOCIEDADE DE ECONOMIA MISTA | I14: S.A. | J14: FECHADO | K14: NÃO | L14: SIM | M14: DEPENDENTE | N14: 57 | O14: =IF(AND(F14="ATIVA",VALUE(N14)=0),"VERIFICAR","OK") -> OK | P14: SIM | Q14: SIM | R14: NÃO | T14: -7615000 | U14: 651000 | V14: =IF(AND(VALUE(N14)=0,VALUE(U14)>0),"VERIFICAR","OK") -> OK | W14: 8475000 | X14: 0 | Y14: NÃO | Z14: 119587 | AA14: 0 | AB14: 0 | AC14: -7444000 | AD14: =IF(AND(Y14="SIM",VALUE(AC14)<0),"VERIFICAR","OK") -> OK | AE14: 45079000 | AG14: 0 | AH14: 0 | AI14: 0 | AJ14: =IF(AND(M14="NÃO DEPENDENTE",VALUE(AI14)>0),"INDÍCIO DE DEPENDÊNCIA POR SUBVENÇÃO","OK") -> OK | AK14: 0 | AL14: 0 | AM14: 0 | AN14: 0 | AO14: 8041 | AP14: 8041 | AQ14: =AP14-AO14 -> 0 | AR14: 80414000 | AS14: 80414000 | AT14: 0 | AU14: 0 | AV14: =(AS14-AR14)+(AU14) -> 0 | AW14: =IF(OR(VALUE(AQ14)>0,VALUE(AV14)>0),"SIM","NÃO") -> NÃO | AX14: =IF(AND(M14="NÃO DEPENDENTE",VALUE(AN14)>0),"VER CAPITAL","OK") -> OK | AY14: =IF(AND(AX14="VER CAPITAL",AW14="NÃO"),"INDÍCIO DE DEPENDÊNCIA POR CAPITAL","OK") -> OK | AZ14: =AC14*100/AE14 -> -16.513232
B15: AL | C15: Alagoas Ativos S.A | D15: ALAtivos | E15: 29.218.037/0001-72 | F15: ATIVA | G15: GESTÃO DE ATIVOS | H15: EMPRESA PÚBLICA | I15: S.A. | J15: FECHADO | K15: NÃO | L15: NÃO | M15: NÃO DEPENDENTE | N15: 19 | O15: =IF(AND(F15="ATIVA",VALUE(N15)=0),"VERIFICAR","OK") -> OK | P15: SIM | Q15: SIM | R15: NÃO | T15: 5313174.6 | U15: 2192507.7 | V15: =IF(AND(VALUE(N15)=0,VALUE(U15)>0),"VERIFICAR","OK") -> OK | W15: 7586434.2 | X15: 0 | Y15: NÃO | Z15: 405711.63 | AA15: 0 | AB15: 0 | AC15: 646243.59 | AD15: =IF(AND(Y15="SIM",VALUE(AC15)<0),"VERIFICAR","OK") -> OK | AE15: 1354881.7 | AG15: 0 | AH15: 0 | AI15: 0 | AJ15: =IF(AND(M15="NÃO DEPENDENTE",VALUE(AI15)>0),"INDÍCIO DE DEPENDÊNCIA POR SUBVENÇÃO","OK") -> OK | AK15: 0 | AL15: 0 | AM15: 0 | AN15: 0 | AO15: 0 | AP15: 0 | AQ15: =AP15-AO15 -> 0 | AR15: 10000000 | AS15: 0 | AT15: 0 | AU15: 0 | AV15: =(AS15-AR15)+(AU15) -> -10000000 | AW15: =IF(OR(VALUE(AQ15)>0,VALUE(AV15)>0),"SIM","NÃO") -> NÃO | AX15: =IF(AND(M15="NÃO DEPENDENTE",VALUE(AN15)>0),"VER CAPITAL","OK") -> OK | AY15: =IF(AND(AX15="VER CAPITAL",AW15="NÃO"),"INDÍCIO DE DEPENDÊNCIA POR CAPITAL","OK") -> OK | AZ15: =AC15*100/AE15 -> 47.697419
B16: AL | C16: Gás de Alagoas S.A | D16: ALGÁS | E16: 69.983.484/0001-32 | F16: ATIVA | G16: GÁS E DERIVADOS | H16: SOCIEDADE DE ECONOMIA MISTA | I16: S.A. | J16: FECHADO | K16: NÃO | L16: NÃO | M16: NÃO DEPENDENTE | N16: 161 | O16: =IF(AND(F16="ATIVA",VALUE(N16)=0),"VERIFICAR","OK") -> OK | P16: SIM | Q16: SIM | R16: SIM | S16: https://governanca,algas,com,br/carta-anual-de-politicas-publicas-e-governanca-corporativa | T16: 4.5279713e+08 | U16: 25539770 | V16: =IF(AND(VALUE(N16)=0,VALUE(U16)>0),"VERIFICAR","OK") -> OK | W16: 4.5719368e+08 | X16: 34430658 | Y16: NÃO | Z16: 398267.27 | AA16: 0 | AB16: 0 | AC16: 40882910 | AD16: =IF(AND(Y16="SIM",VALUE(AC16)<0),"VERIFICAR","OK") -> OK | AE16: 1.4065218e+08 | AG16: 10638724 | AH16: 0 | AI16: 0 | AJ16: =IF(AND(M16="NÃO DEPENDENTE",VALUE(AI16)>0),"INDÍCIO DE DEPENDÊNCIA POR SUBVENÇÃO","OK") -> OK | AK16: 0 | AL16: 0 | AM16: 0 | AN16: 0 | AO16: 2873893 | AP16: 3212493.4 | AQ16: =AP16-AO16 -> 338600.4 | AR16: 23729600 | AS16: 26525400 | AT16: 0 | AU16: 0 | AV16: =(AS16-AR16)+(AU16) -> 2795799.8 | AW16: =IF(OR(VALUE(AQ16)>0,VALUE(AV16)>0),"SIM","NÃO") -> SIM | AX16: =IF(AND(M16="NÃO DEPENDENTE",VALUE(AN16)>0),"VER CAPITAL","OK") -> OK | AY16: =IF(AND(AX16="VER CAPITAL",AW16="NÃO"),"INDÍCIO DE DEPENDÊNCIA POR CAPITAL","OK") -> OK | AZ16: =AC16*100/AE16 -> 29.066674
B17: AL | C17: Companhia Alagoana de Recursos Humanos e Patrimoniais | D17: CARHP | E17: 12.291.274/0001-66 | F17: EM LIQUIDAÇÃO | G17: HABITAÇÃO E URBANIZAÇÃO | H17: SOCIEDADE DE ECONOMIA MISTA | I17: S.A. | J17: FECHADO | K17: NÃO | L17: NÃO | M17: DEPENDENTE | N17: 1 | O17: =IF(AND(F17="ATIVA",VALUE(N17)=0),"VERIFICAR","OK") -> OK | P17: NÃO | Q17: SIM | R17: NÃO | T17: 918583.9 | U17: 16778.87 | V17: =IF(AND(VALUE(N17)=0,VALUE(U17)>0),"VERIFICAR","OK") -> OK | W17: 376826.32 | X17: 323632.27 | Y17: NÃO | Z17: 218125.31 | AA17: 0 | AB17: 0 | AC17: -22558098 | AD17: =IF(AND(Y17="SIM",VALUE(AC17)<0),"VERIFICAR","OK") -> OK | AE17: 19491992 | AG17: 0 | AH17: 5776972.9 | AI17: 2734522 | AJ17: =IF(AND(M17="NÃO DEPENDENTE",VALUE(AI17)>0),"INDÍCIO DE DEPENDÊNCIA POR SUBVENÇÃO","OK") -> OK | AK17: 1.0955497e+08 | AL17: 1.0961923e+08 | AM17: 0 | AN17: 0 | AO17: 0 | AP17: 0 | AQ17: =AP17-AO17 -> 0 | AR17: 20251521 | AS17: 20251521 | AT17: 0 | AU17: 0 | AV17: =(AS17-AR17)+(AU17) -> 0 | AW17: =IF(OR(VALUE(AQ17)>0,VALUE(AV17)>0),"SIM","NÃO") -> NÃO | AX17: =IF(AND(M17="NÃO DEPENDENTE",VALUE(AN17)>0),"VER CAPITAL","OK") -> OK | AY17: =IF(AND(AX17="VER CAPITAL",AW17="NÃO"),"INDÍCIO DE DEPENDÊNCIA POR CAPITAL","OK") -> OK | AZ17: =AC17*100/AE17 -> -115.73008
B18: AL | C18: Companhia de Saneamento de Alagoas | D18: CASAL | E18: 12.294.708/0001-81 | F18: ATIVA | G18: SANEAMENTO | H18: SOCIEDADE DE ECONOMIA MISTA | I18: S.A. | J18: FECHADO | K18: NÃO | L18: NÃO | M18: NÃO DEPENDENTE | N18: 856 | O18: =IF(AND(F18="ATIVA",VALUE(N18)=0),"VERIFICAR","OK") -> OK | P18: SIM | Q18: SIM | R18: SIM | S18: https://www,casal,al,gov,br/arquivos/carta-anual-de-politicas-publicas-e-governanca-corporativa-2024/ | T18: 464911233 | U18: 109360615 | V18: =IF(AND(VALUE(N18)=0,VALUE(U18)>0),"VERIFICAR","OK") -> OK | W18: 5.4383181e+08 | X18: 11453707 | Y18: NÃO | Z18: 475077.99 | AA18: 0 | AB18: 23628.57 | AC18: 76660074 | AD18: =IF(AND(Y18="SIM",VALUE(AC18)<0),"VERIFICAR","OK") -> OK | AE18: 6571826958 | AG18: 0 | AH18: 0 | AI18: 0 | AJ18: =IF(AND(M18="NÃO DEPENDENTE",VALUE(AI18)>0),"INDÍCIO DE DEPENDÊNCIA POR SUBVENÇÃO","OK") -> OK | AK18: 0 | AL18: 0 | AM18: 44880272 | AN18: 51271902 | AO18: 1.364436e+09 | AP18: 1.364436e+09 | AQ18: =AP18-AO18 -> 0 | AR18: 4.6968194e+08 | AS18: 5.2557004e+08 | AT18: 2.8769973e+08 | AU18: 2.3181163e+08 | AV18: =(AS18-AR18)+(AU18) -> 2.8769973e+08 | AW18: =IF(OR(VALUE(AQ18)>0,VALUE(AV18)>0),"SIM","NÃO") -> SIM | AX18: =IF(AND(M18="NÃO DEPENDENTE",VALUE(AN18)>0),"VER CAPITAL","OK") -> VER CAPITAL | AY18: =IF(AND(AX18="VER CAPITAL",AW18="NÃO"),"INDÍCIO DE DEPENDÊNCIA POR CAPITAL","OK") -> OK | AZ18: =AC18*100/AE18 -> 1.1664956
B19: AL | C19: Companhia de Edição Impressão e Publicação de Alagoas | D19: CEPAL | E19: 04.308.836/0001-09 | F19: ATIVA | G19: COMUNICAÇÃO | H19: SOCIEDADE DE ECONOMIA MISTA | I19: S.A. | J19: FECHADO | K19: NÃO | L19: NÃO | M19: NÃO DEPENDENTE | N19: 119 | O19: =IF(AND(F19="ATIVA",VALUE(N19)=0),"VERIFICAR","OK") -> OK | P19: SIM | Q19: SIM | R19: NÃO | S19: https://www,imprensaoficial,al,gov,br/storage/files/2025/04/Carta_Anual_de_Políticas_Públicas_CEPAL_Aprovada_Conselho_2024,pdf | T19: 17985778 | U19: 12885086 | V19: =IF(AND(VALUE(N19)=0,VALUE(U19)>0),"VERIFICAR","OK") -> OK | W19: 20957137 | X19: 0 | Y19: NÃO | Z19: 298779.51 | AA19: 0 | AB19: 0 | AC19: -5899240.4 | AD19: =IF(AND(Y19="SIM",VALUE(AC19)<0),"VERIFICAR","OK") -> OK | AE19: 217370.56 | AG19: 0 | AH19: 0 | AI19: 0 | AJ19: =IF(AND(M19="NÃO DEPENDENTE",VALUE(AI19)>0),"INDÍCIO DE DEPENDÊNCIA POR SUBVENÇÃO","OK") -> OK | AK19: 0 | AL19: 0 | AM19: 0 | AN19: 0 | AO19: 10083000 | AP19: 10083000 | AQ19: =AP19-AO19 -> 0 | AR19: 10083000 | AS19: 10083000 | AT19: 0 | AU19: 0 | AV19: =(AS19-AR19)+(AU19) -> 0 | AW19: =IF(OR(VALUE(AQ19)>0,VALUE(AV19)>0),"SIM","NÃO") -> NÃO | AX19: =IF(AND(M19="NÃO DEPENDENTE",VALUE(AN19)>0),"VER CAPITAL","OK") -> OK | AY19: =IF(AND(AX19="VER CAPITAL",AW19="NÃO"),"INDÍCIO DE DEPENDÊNCIA POR CAPITAL","OK") -> OK | AZ19: =AC19*100/AE19 -> -2713.9096
B20: AL | C20: Laboratório Industrial Farmacêutico | D20: LIFAL | E20: 12.343.158/0001-43 | F20: EM LIQUIDAÇÃO | G20: SAÚDE | H20: SOCIEDADE DE ECONOMIA MISTA | I20: S.A. | J20: FECHADO | K20: NÃO | L20: NÃO | M20: DEPENDENTE | N20: 0 | O20: =IF(AND(F20="ATIVA",VALUE(N20)=0),"VERIFICAR","OK") -> OK | P20: NÃO | Q20: SIM | R20: NÃO | T20: 416573.91 | U20: 4793.94 | V20: =IF(AND(VALUE(N20)=0,VALUE(U20)>0),"VERIFICAR","OK") -> VERIFICAR | W20: 4793.94 | X20: 0 | Y20: NÃO | Z20: 62321.22 | AA20: 0 | AB20: 152320.29 | AC20: 86544.66 | AD20: =IF(AND(Y20="SIM",VALUE(AC20)<0),"VERIFICAR","OK") -> OK | AE20: -50970.82 | AG20: 0 | AH20: 354932.54 | AI20: 430375.27 | AJ20: =IF(AND(M20="NÃO DEPENDENTE",VALUE(AI20)>0),"INDÍCIO DE DEPENDÊNCIA POR SUBVENÇÃO","OK") -> OK | AK20: 837615.8 | AL20: 837615.8 | AM20: 0 | AN20: 0 | AO20: 0 | AP20: 0 | AQ20: =AP20-AO20 -> 0 | AR20: 0 | AS20: 0 | AT20: 0 | AU20: 0 | AV20: =(AS20-AR20)+(AU20) -> 0 | AW20: =IF(OR(VALUE(AQ20)>0,VALUE(AV20)>0),"SIM","NÃO") -> NÃO | AX20: =IF(AND(M20="NÃO DEPENDENTE",VALUE(AN20)>0),"VER CAPITAL","OK") -> OK | AY20: =IF(AND(AX20="VER CAPITAL",AW20="NÃO"),"INDÍCIO DE DEPENDÊNCIA POR CAPITAL","OK") -> OK | AZ20: =AC20*100/AE20 -> -169.79256
B21: AL | C21: Banco do Estado de Alagoas S.A | D21: PRODUBAN | E21: 12.275.749/0001-20 | F21: EM LIQUIDAÇÃO | G21: FINANCEIRO | H21: SOCIEDADE DE ECONOMIA MISTA | I21: S.A. | J21: FECHADO | K21: NÃO | L21: NÃO | M21: DEPENDENTE | N21: 3 | O21: =IF(AND(F21="ATIVA",VALUE(N21)=0),"VERIFICAR","OK") -> OK | P21: NÃO | Q21: SIM | R21: NÃO | T21: 538686.32 | U21: 554179.85 | V21: =IF(AND(VALUE(N21)=0,VALUE(U21)>0),"VERIFICAR","OK") -> OK | W21: 20349597 | X21: 0 | Y21: NÃO | Z21: 325324.89 | AA21: 0 | AB21: 0 | AC21: -20349597 | AD21: =IF(AND(Y21="SIM",VALUE(AC21)<0),"VERIFICAR","OK") -> OK | AE21: 1.2073279e+08 | AG21: 0 | AH21: 100000 | AI21: 100000 | AJ21: =IF(AND(M21="NÃO DEPENDENTE",VALUE(AI21)>0),"INDÍCIO DE DEPENDÊNCIA POR SUBVENÇÃO","OK") -> OK | AK21: 0 | AL21: 0 | AM21: 0 | AN21: 16000000 | AO21: 6750 | AP21: 6750 | AQ21: =AP21-AO21 -> 0 | AR21: 4.998111e+08 | AS21: 4.998111e+08 | AT21: 0 | AU21: 0 | AV21: =(AS21-AR21)+(AU21) -> 0 | AW21: =IF(OR(VALUE(AQ21)>0,VALUE(AV21)>0),"SIM","NÃO") -> NÃO | AX21: =IF(AND(M21="NÃO DEPENDENTE",VALUE(AN21)>0),"VER CAPITAL","OK") -> OK | AY21: =IF(AND(AX21="VER CAPITAL",AW21="NÃO"),"INDÍCIO DE DEPENDÊNCIA POR CAPITAL","OK") -> OK | AZ21: =AC21*100/AE21 -> -16.855071
B22: AL | C22: Serviços de Engenharia de Alagoas S.A | D22: SERVEAL | E22: 12.318.887/0001-40 | F22: EM LIQUIDAÇÃO | G22: OUTROS | H22: SOCIEDADE DE ECONOMIA MISTA | I22: S.A. | J22: FECHADO | K22: NÃO | L22: NÃO | M22: DEPENDENTE | N22: 5 | O22: =IF(AND(F22="ATIVA",VALUE(N22)=0),"VERIFICAR","OK") -> OK | P22: NÃO | Q22: SIM | R22: NÃO | T22: 539804.76 | U22: 41523.44 | V22: =IF(AND(VALUE(N22)=0,VALUE(U22)>0),"VERIFICAR","OK") -> OK | W22: 42358.91 | X22: 0 | Y22: NÃO | Z22: 539804.72 | AA22: 0 | AB22: 0 | AC22: 0 | AD22: =IF(AND(Y22="SIM",VALUE(AC22)<0),"VERIFICAR","OK") -> OK | AE22: -1653049.8 | AG22: 0 | AH22: 1018063.9 | AI22: 387314.54 | AJ22: =IF(AND(M22="NÃO DEPENDENTE",VALUE(AI22)>0),"INDÍCIO DE DEPENDÊNCIA POR SUBVENÇÃO","OK") -> OK | AK22: 3889423.1 | AL22: 3855251.4 | AM22: 0 | AN22: 0 | AO22: 0 | AP22: 0 | AQ22: =AP22-AO22 -> 0 | AR22: -505486.95 | AS22: -505486.95 | AT22: 0 | AU22: 0 | AV22: =(AS22-AR22)+(AU22) -> 0 | AW22: =IF(OR(VALUE(AQ22)>0,VALUE(AV22)>0),"SIM","NÃO") -> NÃO | AX22: =IF(AND(M22="NÃO DEPENDENTE",VALUE(AN22)>0),"VER CAPITAL","OK") -> OK | AY22: =IF(AND(AX22="VER CAPITAL",AW22="NÃO"),"INDÍCIO DE DEPENDÊNCIA POR CAPITAL","OK") -> OK | AZ22: =AC22*100/AE22 -> 0
B23: AM | C23: Agência de Desenvolvimento Sustentável do Amazonas | D23: ADS | E23: 05.867.581/0001-87 | F23: ATIVA | G23: DESENVOLVIMENTO REGIONAL | H23: EMPRESA PÚBLICA | I23: S.A. | J23: FECHADO | K23: NÃO | L23: NÃO | M23: DEPENDENTE | N23: 83 | O23: =IF(AND(F23="ATIVA",VALUE(N23)=0),"VERIFICAR","OK") -> OK | P23: SIM | Q23: SIM | R23: NÃO | S23: Não possui | T23: 1890024 | U23: 4164370.4 | V23: =IF(AND(VALUE(N23)=0,VALUE(U23)>0),"VERIFICAR","OK") -> OK | W23: 1.3566569e+08 | X23: 0 | Y23: NÃO | Z23: 180416.58 | AA23: 0 | AB23: 133966.4 | AC23: -4743532 | AD23: =IF(AND(Y23="SIM",VALUE(AC23)<0),"VERIFICAR","OK") -> OK | AE23: 795178.7 | AF23: 0 | AG23: 0 | AH23: 1.0214802e+08 | AI23: 1.2582989e+08 | AJ23: =IF(AND(M23="NÃO DEPENDENTE",VALUE(AI23)>0),"INDÍCIO DE DEPENDÊNCIA POR SUBVENÇÃO","OK") -> OK | AK23: 0 | AL23: 0 | AM23: 0 | AN23: 0 | AO23: 0 | AP23: 0 | AQ23: =AP23-AO23 -> 0 | AR23: 10000000 | AS23: 10000000 | AT23: 0 | AU23: 0 | AV23: =(AS23-AR23)+(AU23) -> 0 | AW23: =IF(OR(VALUE(AQ23)>0,VALUE(AV23)>0),"SIM","NÃO") -> NÃO | AX23: =IF(AND(M23="NÃO DEPENDENTE",VALUE(AN23)>0),"VER CAPITAL","OK") -> OK | AY23: =IF(AND(AX23="VER CAPITAL",AW23="NÃO"),"INDÍCIO DE DEPENDÊNCIA POR CAPITAL","OK") -> OK | AZ23: =AC23*100/AE23 -> -596.5366
B24: AM | C24: Agência de Fomento do Estado do Amazonas | D24: AFEAM | E24: 03.183.937/0001-38 | F24: ATIVA | G24: FINANCEIRO | H24: EMPRESA PÚBLICA | I24: S.A. | J24: FECHADO | K24: NÃO | L24: NÃO | M24: NÃO DEPENDENTE | N24: 253 | O24: =IF(AND(F24="ATIVA",VALUE(N24)=0),"VERIFICAR","OK") -> OK | P24: SIM | Q24: SIM | R24: SIM | S24: https://www,afeam,am,gov,br/wpcontent/ uploads/2025/04/CARTAANUAL¿ 2024,pdf | T24: 26835089 | U24: 50347133 | V24: =IF(AND(VALUE(N24)=0,VALUE(U24)>0),"VERIFICAR","OK") -> OK | W24: 3.723726e+08 | X24: 3.2202546e+08 | Y24: NÃO | Z24: 567085.72 | AA24: 0 | AB24: 34305.43 | AC24: 14463130 | AD24: =IF(AND(Y24="SIM",VALUE(AC24)<0),"VERIFICAR","OK") -> OK | AE24: 1.2578599e+08 | AF24: 0 | AG24: 0 | AH24: 0 | AI24: 0 | AJ24: =IF(AND(M24="NÃO DEPENDENTE",VALUE(AI24)>0),"INDÍCIO DE DEPENDÊNCIA POR SUBVENÇÃO","OK") -> OK | AK24: 0 | AL24: 0 | AM24: 0 | AN24: 0 | AO24: 103963256 | AP24: 106465046 | AQ24: =AP24-AO24 -> 2501790 | AR24: 103963256 | AS24: 106465046 | AT24: 0 | AU24: 0 | AV24: =(AS24-AR24)+(AU24) -> 2501790 | AW24: =IF(OR(VALUE(AQ24)>0,VALUE(AV24)>0),"SIM","NÃO") -> SIM | AX24: =IF(AND(M24="NÃO DEPENDENTE",VALUE(AN24)>0),"VER CAPITAL","OK") -> OK | AY24: =IF(AND(AX24="VER CAPITAL",AW24="NÃO"),"INDÍCIO DE DEPENDÊNCIA POR CAPITAL","OK") -> OK | AZ24: =AC24*100/AE24 -> 11.498204
B25: AM | C25: Empresa Estadual de Turismo | D25: AMAZONASTUR | E25: 05.662.046/0001-90 | F25: ATIVA | G25: TURISMO | H25: EMPRESA PÚBLICA | I25: OUTRAS | J25: FECHADO | K25: NÃO | L25: NÃO | M25: DEPENDENTE | N25: 144 | O25: =IF(AND(F25="ATIVA",VALUE(N25)=0),"VERIFICAR","OK") -> OK | P25: SIM | Q25: SIM | R25: SIM | S25: https://www,amazonastur,am,gov,br/wpcontent/ uploads/2024/10/amazonastur-cartaservicos- 2024,pdf | T25: 631607.64 | U25: 13648435 | V25: =IF(AND(VALUE(N25)=0,VALUE(U25)>0),"VERIFICAR","OK") -> OK | W25: 1.0485808e+08 | X25: 38772283 | Y25: NÃO | Z25: 407740 | AA25: 0 | AB25: 0 | AC25: -803617.85 | AD25: =IF(AND(Y25="SIM",VALUE(AC25)<0),"VERIFICAR","OK") -> OK | AE25: 4189166.1 | AF25: 0 | AG25: 0 | AH25: 71978546 | AI25: 1.0425863e+08 | AJ25: =IF(AND(M25="NÃO DEPENDENTE",VALUE(AI25)>0),"INDÍCIO DE DEPENDÊNCIA POR SUBVENÇÃO","OK") -> OK | AK25: 2807045.4 | AL25: 6734566.2 | AM25: 0 | AN25: 0 | AO25: 1 | AP25: 1 | AQ25: =AP25-AO25 -> 0 | AR25: 27123375 | AS25: 27123375 | AT25: 0 | AU25: 0 | AV25: =(AS25-AR25)+(AU25) -> 0 | AW25: =IF(OR(VALUE(AQ25)>0,VALUE(AV25)>0),"SIM","NÃO") -> NÃO | AX25: =IF(AND(M25="NÃO DEPENDENTE",VALUE(AN25)>0),"VER CAPITAL","OK") -> OK | AY25: =IF(AND(AX25="VER CAPITAL",AW25="NÃO"),"INDÍCIO DE DEPENDÊNCIA POR CAPITAL","OK") -> OK | AZ25: =AC25*100/AE25 -> -19.183242
B26: AM | C26: Cia. Amazonense de Desenvolvimento e Mobilização de Ativos | D26: CADA | E26: 40.182.478/0001-02 | F26: ATIVA | G26: GESTÃO DE ATIVOS | H26: EMPRESA PÚBLICA | I26: S.A. | J26: FECHADO | K26: NÃO | L26: NÃO | M26: NÃO DEPENDENTE | N26: 26 | O26: =IF(AND(F26="ATIVA",VALUE(N26)=0),"VERIFICAR","OK") -> OK | P26: SIM | Q26: SIM | R26: SIM | S26: https://www,cada,am,gov,br/wpcontent/uploads/2025/02/Carta-Anual-2025-Data-Base-2024,pdf | T26: 765121 | U26: 4383063 | V26: =IF(AND(VALUE(N26)=0,VALUE(U26)>0),"VERIFICAR","OK") -> OK | W26: 4974652 | X26: 0 | Y26: NÃO | Z26: 439200 | AA26: 0 | AB26: 6500 | AC26: 6811743 | AD26: =IF(AND(Y26="SIM",VALUE(AC26)<0),"VERIFICAR","OK") -> OK | AE26: 153408 | AF26: 0 | AG26: 0 | AH26: 0 | AI26: 0 | AJ26: =IF(AND(M26="NÃO DEPENDENTE",VALUE(AI26)>0),"INDÍCIO DE DEPENDÊNCIA POR SUBVENÇÃO","OK") -> OK | AK26: 0 | AL26: 0 | AM26: 6000000 | AN26: 4000000 | AO26: 15000000 | AP26: 19000000 | AQ26: =AP26-AO26 -> 4000000 | AR26: 15000000 | AS26: 19000000 | AT26: 0 | AU26: 0 | AV26: =(AS26-AR26)+(AU26) -> 4000000 | AW26: =IF(OR(VALUE(AQ26)>0,VALUE(AV26)>0),"SIM","NÃO") -> SIM | AX26: =IF(AND(M26="NÃO DEPENDENTE",VALUE(AN26)>0),"VER CAPITAL","OK") -> VER CAPITAL | AY26: =IF(AND(AX26="VER CAPITAL",AW26="NÃO"),"INDÍCIO DE DEPENDÊNCIA POR CAPITAL","OK") -> OK | AZ26: =AC26*100/AE26 -> 4440.2789
B27: AM | C27: Cia. de Desenvolvimento do Estado do Amazonas | D27: CIAMA | E27: 00.624.961/0001-77 | F27: ATIVA | G27: DESENVOLVIMENTO REGIONAL | H27: SOCIEDADE DE ECONOMIA MISTA | I27: S.A. | J27: FECHADO | K27: NÃO | L27: NÃO | M27: DEPENDENTE | N27: 191 | O27: =IF(AND(F27="ATIVA",VALUE(N27)=0),"VERIFICAR","OK") -> OK | P27: SIM | Q27: SIM | R27: NÃO | S27: www,ciama,am,gov,br | T27: 0 | U27: 30883607 | V27: =IF(AND(VALUE(N27)=0,VALUE(U27)>0),"VERIFICAR","OK") -> OK | W27: 35833134 | X27: 0 | Y27: NÃO | Z27: 758106.55 | AA27: 0 | AB27: 6500 | AC27: -18991279 | AD27: =IF(AND(Y27="SIM",VALUE(AC27)<0),"VERIFICAR","OK") -> OK | AE27: 53266635 | AF27: 0 | AG27: 0 | AH27: 30817836 | AI27: 17074546 | AJ27: =IF(AND(M27="NÃO DEPENDENTE",VALUE(AI27)>0),"INDÍCIO DE DEPENDÊNCIA POR SUBVENÇÃO","OK") -> OK | AK27: 0 | AL27: 0 | AM27: 0 | AN27: 16526312 | AO27: 62880631 | AP27: 66058773 | AQ27: =AP27-AO27 -> 3178142 | AR27: 3.2697928e+08 | AS27: 3.4350559e+08 | AT27: 49020720 | AU27: 32494407 | AV27: =(AS27-AR27)+(AU27) -> 49020720 | AW27: =IF(OR(VALUE(AQ27)>0,VALUE(AV27)>0),"SIM","NÃO") -> SIM | AX27: =IF(AND(M27="NÃO DEPENDENTE",VALUE(AN27)>0),"VER CAPITAL","OK") -> OK | AY27: =IF(AND(AX27="VER CAPITAL",AW27="NÃO"),"INDÍCIO DE DEPENDÊNCIA POR CAPITAL","OK") -> OK | AZ27: =AC27*100/AE27 -> -35.653235
B28: AM | C28: Cia. de Gás do Amazonas | D28: CIGAS | E28: 00.624.964/0001-00 | F28: ATIVA | G28: GÁS E DERIVADOS | H28: SOCIEDADE DE ECONOMIA MISTA | I28: S.A. | J28: FECHADO | K28: NÃO | L28: NÃO | M28: NÃO DEPENDENTE | N28: 230 | O28: =IF(AND(F28="ATIVA",VALUE(N28)=0),"VERIFICAR","OK") -> OK | P28: SIM | Q28: SIM | R28: NÃO | S28: https://www,cigas-am,com,br/relatorio-de-sustentabilidade | T28: 3.5530374e+09 | U28: 2056766.3 | V28: =IF(AND(VALUE(N28)=0,VALUE(U28)>0),"VERIFICAR","OK") -> OK | W28: 3.3761082e+09 | X28: 22339240 | Y28: SIM | Z28: 765000 | AA28: 45000 | AB28: 14048 | AC28: 1.9728408e+08 | AD28: =IF(AND(Y28="SIM",VALUE(AC28)<0),"VERIFICAR","OK") -> OK | AE28: 5.0508971e+08 | AF28: 0 | AG28: 11365846 | AH28: 0 | AI28: 0 | AJ28: =IF(AND(M28="NÃO DEPENDENTE",VALUE(AI28)>0),"INDÍCIO DE DEPENDÊNCIA POR SUBVENÇÃO","OK") -> OK | AK28: 0 | AL28: 0 | AM28: 0 | AN28: 0 | AO28: 12059543 | AP28: 12059543 | AQ28: =AP28-AO28 -> 0 | AR28: 45042129 | AS28: 58100045 | AT28: 0 | AU28: 0 | AV28: =(AS28-AR28)+(AU28) -> 13057916 | AW28: =IF(OR(VALUE(AQ28)>0,VALUE(AV28)>0),"SIM","NÃO") -> SIM | AX28: =IF(AND(M28="NÃO DEPENDENTE",VALUE(AN28)>0),"VER CAPITAL","OK") -> OK | AY28: =IF(AND(AX28="VER CAPITAL",AW28="NÃO"),"INDÍCIO DE DEPENDÊNCIA POR CAPITAL","OK") -> OK | AZ28: =AC28*100/AE28 -> 39.059216
B29: AM | C29: Cia. de Saneamento do Amazonas | D29: COSAMA | E29: 04.406.195/0001-25 | F29: ATIVA | G29: SANEAMENTO | H29: SOCIEDADE DE ECONOMIA MISTA | I29: S.A. | J29: FECHADO | K29: NÃO | L29: NÃO | M29: DEPENDENTE | N29: 522 | O29: =IF(AND(F29="ATIVA",VALUE(N29)=0),"VERIFICAR","OK") -> OK | P29: SIM | Q29: SIM | R29: NÃO | S29: Não foi publicada carta anual, | T29: 73990521 | U29: 45340671 | V29: =IF(AND(VALUE(N29)=0,VALUE(U29)>0),"VERIFICAR","OK") -> OK | W29: 83896774 | X29: 4303097.2 | Y29: NÃO | Z29: 469688.87 | AA29: 0 | AB29: 4525.34 | AC29: -8231341.9 | AD29: =IF(AND(Y29="SIM",VALUE(AC29)<0),"VERIFICAR","OK") -> OK | AE29: -22972209 | AF29: 0 | AG29: 0 | AH29: 47283701 | AI29: 49576266 | AJ29: =IF(AND(M29="NÃO DEPENDENTE",VALUE(AI29)>0),"INDÍCIO DE DEPENDÊNCIA POR SUBVENÇÃO","OK") -> OK | AK29: 0 | AL29: 0 | AM29: 4042877 | AN29: 1290000 | AO29: 22094870827 | AP29: 22094870827 | AQ29: =AP29-AO29 -> 0 | AR29: 5.3386274e+08 | AS29: 5.3386274e+08 | AT29: 0 | AU29: 0 | AV29: =(AS29-AR29)+(AU29) -> 0 | AW29: =IF(OR(VALUE(AQ29)>0,VALUE(AV29)>0),"SIM","NÃO") -> NÃO | AX29: =IF(AND(M29="NÃO DEPENDENTE",VALUE(AN29)>0),"VER CAPITAL","OK") -> OK | AY29: =IF(AND(AX29="VER CAPITAL",AW29="NÃO"),"INDÍCIO DE DEPENDÊNCIA POR CAPITAL","OK") -> OK | AZ29: =AC29*100/AE29 -> 35.831739
B30: AM | C30: Processamento de Dados do Amazonas | D30: PRODAM | E30: 04.407.920/0001-80 | F30: ATIVA | G30: INFORMÁTICA E TECNOLOGIA DA INFORMAÇÃO | H30: SOCIEDADE DE ECONOMIA MISTA | I30: S.A. | J30: FECHADO | K30: NÃO | L30: NÃO | M30: NÃO DEPENDENTE | N30: 446 | O30: =IF(AND(F30="ATIVA",VALUE(N30)=0),"VERIFICAR","OK") -> OK | P30: SIM | Q30: SIM | R30: SIM | S30: https://prodam,am,gov,br/acesso-a-informacao/carta-de-governanca-2024/ | T30: 136009915 | U30: 69725561 | V30: =IF(AND(VALUE(N30)=0,VALUE(U30)>0),"VERIFICAR","OK") -> OK | W30: 78824023 | X30: 9098462 | Y30: NÃO | Z30: 730797.6 | AA30: 0 | AB30: 23926.98 | AC30: 9749845 | AD30: =IF(AND(Y30="SIM",VALUE(AC30)<0),"VERIFICAR","OK") -> OK | AE30: 25157069 | AF30: 0 | AG30: 0 | AH30: 0 | AI30: 0 | AJ30: =IF(AND(M30="NÃO DEPENDENTE",VALUE(AI30)>0),"INDÍCIO DE DEPENDÊNCIA POR SUBVENÇÃO","OK") -> OK | AK30: 0 | AL30: 0 | AM30: 0 | AN30: 0 | AO30: 99.89 | AP30: 99.89 | AQ30: =AP30-AO30 -> 0 | AR30: 45193991 | AS30: 45193991 | AT30: 0 | AU30: 0 | AV30: =(AS30-AR30)+(AU30) -> 0 | AW30: =IF(OR(VALUE(AQ30)>0,VALUE(AV30)>0),"SIM","NÃO") -> NÃO | AX30: =IF(AND(M30="NÃO DEPENDENTE",VALUE(AN30)>0),"VER CAPITAL","OK") -> OK | AY30: =IF(AND(AX30="VER CAPITAL",AW30="NÃO"),"INDÍCIO DE DEPENDÊNCIA POR CAPITAL","OK") -> OK | AZ30: =AC30*100/AE30 -> 38.755886
B31: AP | C31: AGÊNCIA DE FOMENTO POPULAR | D31: AFAP | E31: 02.929.977/0001-13 | F31: ATIVA | G31: FINANCEIRO | H31: EMPRESA PÚBLICA | I31: S.A. | J31: FECHADO | K31: NÃO | L31: NÃO | M31: NÃO DEPENDENTE | N31: 99 | O31: =IF(AND(F31="ATIVA",VALUE(N31)=0),"VERIFICAR","OK") -> OK | P31: SIM | Q31: SIM | R31: NÃO | T31: 11665247 | U31: 4546633.4 | V31: =IF(AND(VALUE(N31)=0,VALUE(U31)>0),"VERIFICAR","OK") -> OK | W31: 13015641 | X31: 0 | Y31: NÃO | Z31: 204363.69 | AA31: 0 | AB31: 63428.18 | AC31: -1045966.9 | AD31: =IF(AND(Y31="SIM",VALUE(AC31)<0),"VERIFICAR","OK") -> OK | AE31: 16811614 | AF31: 0 | AG31: 0 | AH31: 0 | AI31: 0 | AJ31: =IF(AND(M31="NÃO DEPENDENTE",VALUE(AI31)>0),"INDÍCIO DE DEPENDÊNCIA POR SUBVENÇÃO","OK") -> OK | AK31: 0 | AL31: 0 | AM31: 0 | AN31: 0 | AO31: 39255740 | AP31: 39255740 | AQ31: =AP31-AO31 -> 0 | AR31: 34455740 | AS31: 39255740 | AT31: 34455740 | AU31: 39255740 | AV31: =(AS31-AR31)+(AU31) -> 44055740 | AW31: =IF(OR(VALUE(AQ31)>0,VALUE(AV31)>0),"SIM","NÃO") -> SIM | AX31: =IF(AND(M31="NÃO DEPENDENTE",VALUE(AN31)>0),"VER CAPITAL","OK") -> OK | AY31: =IF(AND(AX31="VER CAPITAL",AW31="NÃO"),"INDÍCIO DE DEPENDÊNCIA POR CAPITAL","OK") -> OK | AZ31: =AC31*100/AE31 -> -6.2216926
B32: AP | C32: COMPANHIA DE ÁGUA E ESGOTO DO AMAPÁ | D32: CAESA | E32: 05.976.311/0001-04 | F32: ATIVA | G32: SANEAMENTO | H32: SOCIEDADE DE ECONOMIA MISTA | I32: S.A. | J32: FECHADO | K32: NÃO | L32: NÃO | M32: DEPENDENTE | N32: 298 | O32: =IF(AND(F32="ATIVA",VALUE(N32)=0),"VERIFICAR","OK") -> OK | P32: SIM | Q32: SIM | R32: NÃO | S32: caesa,portal,ap,gov,br | T32: 2764377.3 | U32: 45689258 | V32: =IF(AND(VALUE(N32)=0,VALUE(U32)>0),"VERIFICAR","OK") -> OK | W32: 1.2608268e+08 | X32: 519101.98 | Y32: NÃO | Z32: 284698.07 | AA32: 0 | AB32: 200076.6 | AC32: -1.233183e+08 | AD32: =IF(AND(Y32="SIM",VALUE(AC32)<0),"VERIFICAR","OK") -> OK | AE32: 1.2129848e+08 | AF32: 0 | AG32: 0 | AH32: 51326173 | AI32: 51535695 | AJ32: =IF(AND(M32="NÃO DEPENDENTE",VALUE(AI32)>0),"INDÍCIO DE DEPENDÊNCIA POR SUBVENÇÃO","OK") -> OK | AK32: 1.5857231e+08 | AL32: 1.1186538e+08 | AM32: 51326173 | AN32: 51535695 | AO32: 5245225458 | AP32: 5245225458 | AQ32: =AP32-AO32 -> 0 | AR32: 5.0695917e+08 | AS32: 5.5982014e+08 | AT32: 52860967 | AU32: 52607136 | AV32: =(AS32-AR32)+(AU32) -> 1.054681e+08 | AW32: =IF(OR(VALUE(AQ32)>0,VALUE(AV32)>0),"SIM","NÃO") -> SIM | AX32: =IF(AND(M32="NÃO DEPENDENTE",VALUE(AN32)>0),"VER CAPITAL","OK") -> OK | AY32: =IF(AND(AX32="VER CAPITAL",AW32="NÃO"),"INDÍCIO DE DEPENDÊNCIA POR CAPITAL","OK") -> OK | AZ32: =AC32*100/AE32 -> -101.66516
B33: AP | C33: COMPANHIA DE GÁS DO AMAPÁ | D33: GASAP | E33: 05.943.400/0001-54 | F33: ATIVA | G33: GÁS E DERIVADOS | H33: SOCIEDADE DE ECONOMIA MISTA | I33: S.A. | J33: FECHADO | K33: NÃO | L33: NÃO | M33: NÃO DEPENDENTE | N33: 2 | O33: =IF(AND(F33="ATIVA",VALUE(N33)=0),"VERIFICAR","OK") -> OK | P33: SIM | Q33: SIM | R33: NÃO | S33: https://gasap,com,br/acesso-a-informacao/governanca/carta-anual-de-governanca | T33: 0 | U33: 169282.13 | V33: =IF(AND(VALUE(N33)=0,VALUE(U33)>0),"VERIFICAR","OK") -> OK | W33: 312664.81 | X33: 0 | Y33: NÃO | Z33: 58275 | AA33: 0 | AB33: 0 | AC33: 332463.03 | AD33: =IF(AND(Y33="SIM",VALUE(AC33)<0),"VERIFICAR","OK") -> OK | AE33: 135120.81 | AF33: 0 | AG33: 0 | AH33: 0 | AI33: 0 | AJ33: =IF(AND(M33="NÃO DEPENDENTE",VALUE(AI33)>0),"INDÍCIO DE DEPENDÊNCIA POR SUBVENÇÃO","OK") -> OK | AK33: 0 | AL33: 0 | AM33: 0 | AN33: 0 | AO33: 790500 | AP33: 790500 | AQ33: =AP33-AO33 -> 0 | AR33: 2999000 | AS33: 31000 | AT33: 101000 | AU33: 0 | AV33: =(AS33-AR33)+(AU33) -> -2968000 | AW33: =IF(OR(VALUE(AQ33)>0,VALUE(AV33)>0),"SIM","NÃO") -> NÃO | AX33: =IF(AND(M33="NÃO DEPENDENTE",VALUE(AN33)>0),"VER CAPITAL","OK") -> OK | AY33: =IF(AND(AX33="VER CAPITAL",AW33="NÃO"),"INDÍCIO DE DEPENDÊNCIA POR CAPITAL","OK") -> OK | AZ33: =AC33*100/AE33 -> 246.04872
B34: BA | C34: COMPANHIA DE GÁS DA BAHIA | D34: BAHIAGÁS | E34: 34.432.153/0001-20 | F34: ATIVA | G34: GÁS E DERIVADOS | H34: SOCIEDADE DE ECONOMIA MISTA | I34: S.A. | J34: FECHADO | K34: NÃO | L34: NÃO | M34: NÃO DEPENDENTE | N34: 611 | O34: =IF(AND(F34="ATIVA",VALUE(N34)=0),"VERIFICAR","OK") -> OK | P34: SIM | Q34: SIM | R34: SIM | S34: https://www,bahiagas,com,br/sobre-a-bahiagas/cartas-anuais | T34: 3.1283853e+09 | U34: 1.0301229e+08 | V34: =IF(AND(VALUE(N34)=0,VALUE(U34)>0),"VERIFICAR","OK") -> OK | W34: 5.5297003e+08 | X34: 2.3625441e+08 | Y34: SIM | Z34: 560751.36 | AA34: 103582.81 | AB34: 0 | AC34: 1.9768137e+08 | AD34: =IF(AND(Y34="SIM",VALUE(AC34)<0),"VERIFICAR","OK") -> OK | AE34: 1.1378639e+09 | AF34: 0 | AG34: 66931377 | AH34: 0 | AI34: 0 | AJ34: =IF(AND(M34="NÃO DEPENDENTE",VALUE(AI34)>0),"INDÍCIO DE DEPENDÊNCIA POR SUBVENÇÃO","OK") -> OK | AK34: 0 | AL34: 0 | AM34: 0 | AN34: 0 | AO34: 13490874 | AP34: 15162188 | AQ34: =AP34-AO34 -> 1671314 | AR34: 3.1672674e+08 | AS34: 3.5596433e+08 | AT34: 0 | AU34: 0 | AV34: =(AS34-AR34)+(AU34) -> 39237592 | AW34: =IF(OR(VALUE(AQ34)>0,VALUE(AV34)>0),"SIM","NÃO") -> SIM | AX34: =IF(AND(M34="NÃO DEPENDENTE",VALUE(AN34)>0),"VER CAPITAL","OK") -> OK | AY34: =IF(AND(AX34="VER CAPITAL",AW34="NÃO"),"INDÍCIO DE DEPENDÊNCIA POR CAPITAL","OK") -> OK | AZ34: =AC34*100/AE34 -> 17.373023
B35: BA | C35: EMPRESA BAIANA DE ATIVOS S.A. | D35: BAHIAINVESTE | E35: 26.310.070/0001-30 | F35: ATIVA | G35: GESTÃO DE ATIVOS | H35: SOCIEDADE DE ECONOMIA MISTA | I35: S.A. | J35: FECHADO | K35: NÃO | L35: NÃO | M35: NÃO DEPENDENTE | N35: 36 | O35: =IF(AND(F35="ATIVA",VALUE(N35)=0),"VERIFICAR","OK") -> OK | P35: SIM | Q35: SIM | R35: NÃO | S35: CARTA-ANUAL-BI-2024_2025_28_04_25-Assinada-compactado,pdf | T35: 6063811.6 | U35: 7903369.5 | V35: =IF(AND(VALUE(N35)=0,VALUE(U35)>0),"VERIFICAR","OK") -> OK | W35: 10655651 | X35: 204804.5 | Y35: NÃO | Z35: 506760.26 | AA35: 0 | AB35: 14325.42 | AC35: -7564609.5 | AD35: =IF(AND(Y35="SIM",VALUE(AC35)<0),"VERIFICAR","OK") -> OK | AE35: 64281864 | AF35: 0 | AG35: 0 | AH35: 0 | AI35: 0 | AJ35: =IF(AND(M35="NÃO DEPENDENTE",VALUE(AI35)>0),"INDÍCIO DE DEPENDÊNCIA POR SUBVENÇÃO","OK") -> OK | AK35: 0 | AL35: 0 | AM35: 8545000 | AN35: 5000000 | AO35: 80735673 | AP35: 92280673 | AQ35: =AP35-AO35 -> 11545000 | AR35: 80735673 | AS35: 92280673 | AT35: 0 | AU35: 2000000 | AV35: =(AS35-AR35)+(AU35) -> 13545000 | AW35: =IF(OR(VALUE(AQ35)>0,VALUE(AV35)>0),"SIM","NÃO") -> SIM | AX35: =IF(AND(M35="NÃO DEPENDENTE",VALUE(AN35)>0),"VER CAPITAL","OK") -> VER CAPITAL | AY35: =IF(AND(AX35="VER CAPITAL",AW35="NÃO"),"INDÍCIO DE DEPENDÊNCIA POR CAPITAL","OK") -> OK | AZ35: =AC35*100/AE35 -> -11.767875
B36: BA | C36: BAHIA PESCA S.A. | D36: BAHIAPESCA | E36: 13.187.745/0001-53 | F36: ATIVA | G36: ABASTECIMENTO DE ALIMENTOS E OUTROS INSUMOS | H36: SOCIEDADE DE ECONOMIA MISTA | I36: S.A. | J36: FECHADO | K36: NÃO | L36: NÃO | M36: DEPENDENTE | N36: 110 | O36: =IF(AND(F36="ATIVA",VALUE(N36)=0),"VERIFICAR","OK") -> OK | P36: SIM | Q36: SIM | R36: NÃO | S36: https://www,ba,gov,br/bahiapesca/sites/site-bahiapesca/files/2024-12/Carta%20Anual%20exerc%C3%ADcio%202023,pdf | T36: 83617 | U36: 13857900 | V36: =IF(AND(VALUE(N36)=0,VALUE(U36)>0),"VERIFICAR","OK") -> OK | W36: 28561678 | X36: 865276 | Y36: NÃO | Z36: 379709.85 | AA36: 0 | AB36: 0 | AC36: 3377901 | AD36: =IF(AND(Y36="SIM",VALUE(AC36)<0),"VERIFICAR","OK") -> OK | AE36: -3362003 | AF36: 0 | AG36: 0 | AH36: 5400883 | AI36: 6890791.4 | AJ36: =IF(AND(M36="NÃO DEPENDENTE",VALUE(AI36)>0),"INDÍCIO DE DEPENDÊNCIA POR SUBVENÇÃO","OK") -> OK | AK36: 2558600 | AL36: 2762929 | AM36: 0 | AN36: 0 | AO36: 16079007 | AP36: 16079007 | AQ36: =AP36-AO36 -> 0 | AR36: 4824688.6 | AS36: 4824688.6 | AT36: 0 | AU36: 0 | AV36: =(AS36-AR36)+(AU36) -> 0 | AW36: =IF(OR(VALUE(AQ36)>0,VALUE(AV36)>0),"SIM","NÃO") -> NÃO | AX36: =IF(AND(M36="NÃO DEPENDENTE",VALUE(AN36)>0),"VER CAPITAL","OK") -> OK | AY36: =IF(AND(AX36="VER CAPITAL",AW36="NÃO"),"INDÍCIO DE DEPENDÊNCIA POR CAPITAL","OK") -> OK | AZ36: =AC36*100/AE36 -> -100.47287
B37: BA | C37: COMPANHA DE DESENVOLVIMENTO E AÇÃO REGIONAL | D37: CAR | E37: 13.221.247/0001-80 | F37: ATIVA | G37: DESENVOLVIMENTO REGIONAL | H37: EMPRESA PÚBLICA | I37: S.A. | J37: FECHADO | K37: NÃO | L37: NÃO | M37: DEPENDENTE | N37: 375 | O37: =IF(AND(F37="ATIVA",VALUE(N37)=0),"VERIFICAR","OK") -> OK | P37: SIM | Q37: SIM | R37: NÃO | S37: https://www,car,ba,gov,br/sites/default/files/2025-01/Carta%20Anual%202025,pdf | T37: 63124352 | U37: 43114341 | V37: =IF(AND(VALUE(N37)=0,VALUE(U37)>0),"VERIFICAR","OK") -> OK | W37: 60917575 | X37: 0 | Y37: NÃO | Z37: 463700.92 | AA37: 0 | AB37: 4892.8 | AC37: 2270183.7 | AD37: =IF(AND(Y37="SIM",VALUE(AC37)<0),"VERIFICAR","OK") -> OK | AE37: -37037212 | AF37: 0 | AG37: 0 | AH37: 51115067 | AI37: 62005726 | AJ37: =IF(AND(M37="NÃO DEPENDENTE",VALUE(AI37)>0),"INDÍCIO DE DEPENDÊNCIA POR SUBVENÇÃO","OK") -> OK | AK37: 0 | AL37: 0 | AM37: 0 | AN37: 0 | AO37: 13542532 | AP37: 13542532 | AQ37: =AP37-AO37 -> 0 | AR37: 13542532 | AS37: 13542532 | AT37: 12549846 | AU37: 12513332 | AV37: =(AS37-AR37)+(AU37) -> 12513332 | AW37: =IF(OR(VALUE(AQ37)>0,VALUE(AV37)>0),"SIM","NÃO") -> SIM | AX37: =IF(AND(M37="NÃO DEPENDENTE",VALUE(AN37)>0),"VER CAPITAL","OK") -> OK | AY37: =IF(AND(AX37="VER CAPITAL",AW37="NÃO"),"INDÍCIO DE DEPENDÊNCIA POR CAPITAL","OK") -> OK | AZ37: =AC37*100/AE37 -> -6.1294669
B38: BA | C38: COMPANHIA BAIANA DE PESQUISA MINERAL | D38: CBPM | E38: 13.554.910/0001-68 | F38: ATIVA | G38: MINERAÇÃO | H38: SOCIEDADE DE ECONOMIA MISTA | I38: S.A. | J38: FECHADO | K38: NÃO | L38: NÃO | M38: DEPENDENTE | N38: 141 | O38: =IF(AND(F38="ATIVA",VALUE(N38)=0),"VERIFICAR","OK") -> OK | P38: SIM | Q38: SIM | R38: NÃO | S38: http://www,cbpm,ba,gov,br/transparencia/carta-anual-de-politicas-publicas-e-governanca-corporativa/ | T38: 57231013 | U38: 53051335 | V38: =IF(AND(VALUE(N38)=0,VALUE(U38)>0),"VERIFICAR","OK") -> OK | W38: 95695329 | X38: 787226 | Y38: NÃO | Z38: 463398.48 | AA38: 0 | AB38: 16133.11 | AC38: -10532826 | AD38: =IF(AND(Y38="SIM",VALUE(AC38)<0),"VERIFICAR","OK") -> OK | AE38: -83137845 | AF38: 0 | AG38: 0 | AH38: 6087023.9 | AI38: 8346554.7 | AJ38: =IF(AND(M38="NÃO DEPENDENTE",VALUE(AI38)>0),"INDÍCIO DE DEPENDÊNCIA POR SUBVENÇÃO","OK") -> OK | AK38: 0 | AL38: 0 | AM38: 0 | AN38: 0 | AO38: 99991387 | AP38: 99991387 | AQ38: =AP38-AO38 -> 0 | AR38: 100000000 | AS38: 100000000 | AT38: 0 | AU38: 0 | AV38: =(AS38-AR38)+(AU38) -> 0 | AW38: =IF(OR(VALUE(AQ38)>0,VALUE(AV38)>0),"SIM","NÃO") -> NÃO | AX38: =IF(AND(M38="NÃO DEPENDENTE",VALUE(AN38)>0),"VER CAPITAL","OK") -> OK | AY38: =IF(AND(AX38="VER CAPITAL",AW38="NÃO"),"INDÍCIO DE DEPENDÊNCIA POR CAPITAL","OK") -> OK | AZ38: =AC38*100/AE38 -> 12.669111
B39: BA | C39: COMPANHIA DE ENGENHARIA HÍDRICA E DE SANEAMENTO DA BAHIA | D39: CERB | E39: 13.529.136/0001-35 | F39: ATIVA | G39: SANEAMENTO | H39: SOCIEDADE DE ECONOMIA MISTA | I39: S.A. | J39: FECHADO | K39: NÃO | L39: NÃO | M39: DEPENDENTE | N39: 1055 | O39: =IF(AND(F39="ATIVA",VALUE(N39)=0),"VERIFICAR","OK") -> OK | P39: SIM | Q39: SIM | R39: SIM | S39: http://www,cerb,ba,gov,br/sites/www,cerb,ba,gov,br/files/a_cerb/nosso_papel/page/files/CARTA_ANUAL_2024_VF,pdf | T39: 12267646 | U39: 40632220 | V39: =IF(AND(VALUE(N39)=0,VALUE(U39)>0),"VERIFICAR","OK") -> OK | W39: 1.5975587e+08 | X39: 86292045 | Y39: SIM | Z39: 445266.58 | AA39: 17139.34 | AB39: 0 | AC39: 14284705 | AD39: =IF(AND(Y39="SIM",VALUE(AC39)<0),"VERIFICAR","OK") -> OK | AE39: 7166576.2 | AF39: 0 | AG39: 0 | AH39: 1.2280125e+08 | AI39: 1.4710052e+08 | AJ39: =IF(AND(M39="NÃO DEPENDENTE",VALUE(AI39)>0),"INDÍCIO DE DEPENDÊNCIA POR SUBVENÇÃO","OK") -> OK | AK39: 0 | AL39: 59733784 | AM39: 0 | AN39: 0 | AO39: 99.65 | AP39: 99.65 | AQ39: =AP39-AO39 -> 0 | AR39: 131206906 | AS39: 131206906 | AT39: 0 | AU39: 0 | AV39: =(AS39-AR39)+(AU39) -> 0 | AW39: =IF(OR(VALUE(AQ39)>0,VALUE(AV39)>0),"SIM","NÃO") -> NÃO | AX39: =IF(AND(M39="NÃO DEPENDENTE",VALUE(AN39)>0),"VER CAPITAL","OK") -> OK | AY39: =IF(AND(AX39="VER CAPITAL",AW39="NÃO"),"INDÍCIO DE DEPENDÊNCIA POR CAPITAL","OK") -> OK | AZ39: =AC39*100/AE39 -> 199.32399
B40: BA | C40: COMPANHIA DE DESENVOLVIMENTO URBANO DO ESTADO DA BAHIA | D40: CONDER | E40: 13.595.251/0001-08 | F40: ATIVA | G40: HABITAÇÃO E URBANIZAÇÃO | H40: EMPRESA PÚBLICA | I40: OUTRAS | J40: FECHADO | K40: NÃO | L40: NÃO | M40: DEPENDENTE | N40: 347 | O40: =IF(AND(F40="ATIVA",VALUE(N40)=0),"VERIFICAR","OK") -> OK | P40: SIM | Q40: SIM | R40: NÃO | S40: https://www,conder,ba,gov,br/sites/default/files/2024-04/CARTA GOVERNANÇA 2024_0,pdf | T40: 3.7690629e+08 | U40: 42386836 | V40: =IF(AND(VALUE(N40)=0,VALUE(U40)>0),"VERIFICAR","OK") -> OK | W40: 3.9613606e+08 | X40: 0 | Y40: NÃO | Z40: 451672.48 | AA40: 0 | AB40: 11888.24 | AC40: -14979511 | AD40: =IF(AND(Y40="SIM",VALUE(AC40)<0),"VERIFICAR","OK") -> OK | AE40: 1.7510069e+08 | AF40: 0 | AG40: 0 | AH40: 1.3169547e+09 | AI40: 1.1263136e+09 | AJ40: =IF(AND(M40="NÃO DEPENDENTE",VALUE(AI40)>0),"INDÍCIO DE DEPENDÊNCIA POR SUBVENÇÃO","OK") -> OK | AK40: 0 | AL40: 0 | AM40: 0 | AN40: 0 | AO40: 16803754 | AP40: 16803754 | AQ40: =AP40-AO40 -> 0 | AR40: 16803753 | AS40: 16803754 | AT40: 0 | AU40: 0 | AV40: =(AS40-AR40)+(AU40) -> 0.66 | AW40: =IF(OR(VALUE(AQ40)>0,VALUE(AV40)>0),"SIM","NÃO") -> SIM | AX40: =IF(AND(M40="NÃO DEPENDENTE",VALUE(AN40)>0),"VER CAPITAL","OK") -> OK | AY40: =IF(AND(AX40="VER CAPITAL",AW40="NÃO"),"INDÍCIO DE DEPENDÊNCIA POR CAPITAL","OK") -> OK | AZ40: =AC40*100/AE40 -> -8.554798
B41: BA | C41: COMPANHIA DE TRANSPORTE DO ESTADO DA BAHIA | D41: CTB | E41: 03.231.999/0001-78 | F41: ATIVA | G41: TRANSPORTE | H41: EMPRESA PÚBLICA | I41: S.A. | J41: FECHADO | K41: NÃO | L41: NÃO | M41: DEPENDENTE | N41: 82 | O41: =IF(AND(F41="ATIVA",VALUE(N41)=0),"VERIFICAR","OK") -> OK | P41: SIM | Q41: SIM | R41: NÃO | T41: 5213305 | U41: 23508721 | V41: =IF(AND(VALUE(N41)=0,VALUE(U41)>0),"VERIFICAR","OK") -> OK | W41: 2.6093772e+08 | X41: 237429000 | Y41: NÃO | Z41: 433360.48 | AA41: 0 | AB41: 0 | AC41: -11730795 | AD41: =IF(AND(Y41="SIM",VALUE(AC41)<0),"VERIFICAR","OK") -> OK | AE41: 40896905 | AF41: 0 | AG41: 0 | AH41: 59945660 | AI41: 2.7735765e+08 | AJ41: =IF(AND(M41="NÃO DEPENDENTE",VALUE(AI41)>0),"INDÍCIO DE DEPENDÊNCIA POR SUBVENÇÃO","OK") -> OK | AK41: 0 | AL41: 0 | AM41: 0 | AN41: 0 | AO41: 159700077 | AP41: 159700077 | AQ41: =AP41-AO41 -> 0 | AR41: 1.3965449e+08 | AS41: 1.3965449e+08 | AT41: 22737270 | AU41: 22737270 | AV41: =(AS41-AR41)+(AU41) -> 22737270 | AW41: =IF(OR(VALUE(AQ41)>0,VALUE(AV41)>0),"SIM","NÃO") -> SIM | AX41: =IF(AND(M41="NÃO DEPENDENTE",VALUE(AN41)>0),"VER CAPITAL","OK") -> OK | AY41: =IF(AND(AX41="VER CAPITAL",AW41="NÃO"),"INDÍCIO DE DEPENDÊNCIA POR CAPITAL","OK") -> OK | AZ41: =AC41*100/AE41 -> -28.68382
B42: BA | C42: AGÊNCIA DE FOMENTO DO ESTADO DA BAHIA | D42: DESENBAHIA | E42: 15.163.587/0001-27 | F42: ATIVA | G42: FINANCEIRO | H42: SOCIEDADE DE ECONOMIA MISTA | I42: S.A. | J42: FECHADO | K42: NÃO | L42: NÃO | M42: NÃO DEPENDENTE | N42: 249 | O42: =IF(AND(F42="ATIVA",VALUE(N42)=0),"VERIFICAR","OK") -> OK | P42: SIM | Q42: SIM | R42: SIM | S42: https://www,desenbahia,ba,gov,br/wp-content/uploads/2024/05/carta-anual-politicas-publicas-e-governanca-corporativa-2023-revfinal,pdf | T42: 2.8465594e+08 | U42: 67101416 | V42: =IF(AND(VALUE(N42)=0,VALUE(U42)>0),"VERIFICAR","OK") -> OK | W42: 1.894192e+08 | X42: 0 | Y42: SIM | Z42: 479397.25 | AA42: 81554.61 | AB42: 24077.13 | AC42: 96535176 | AD42: =IF(AND(Y42="SIM",VALUE(AC42)<0),"VERIFICAR","OK") -> OK | AE42: 8.2753925e+08 | AF42: 0 | AG42: 33994927 | AH42: 0 | AI42: 0 | AJ42: =IF(AND(M42="NÃO DEPENDENTE",VALUE(AI42)>0),"INDÍCIO DE DEPENDÊNCIA POR SUBVENÇÃO","OK") -> OK | AK42: 0 | AL42: 0 | AM42: 0 | AN42: 0 | AO42: 142301765100 | AP42: 142301765100 | AQ42: =AP42-AO42 -> 0 | AR42: 6.2389725e+08 | AS42: 6.2389725e+08 | AT42: 0 | AU42: 0 | AV42: =(AS42-AR42)+(AU42) -> 0 | AW42: =IF(OR(VALUE(AQ42)>0,VALUE(AV42)>0),"SIM","NÃO") -> NÃO | AX42: =IF(AND(M42="NÃO DEPENDENTE",VALUE(AN42)>0),"VER CAPITAL","OK") -> OK | AY42: =IF(AND(AX42="VER CAPITAL",AW42="NÃO"),"INDÍCIO DE DEPENDÊNCIA POR CAPITAL","OK") -> OK | AZ42: =AC42*100/AE42 -> 11.665329
B43: BA | C43: EMPRESA GRÁFICA DA BAHIA | D43: EGBA | E43: 15.257.819/0001-06 | F43: ATIVA | G43: INFORMÁTICA E TECNOLOGIA DA INFORMAÇÃO | H43: EMPRESA PÚBLICA | I43: OUTRAS | J43: FECHADO | K43: NÃO | L43: NÃO | M43: NÃO DEPENDENTE | N43: 159 | O43: =IF(AND(F43="ATIVA",VALUE(N43)=0),"VERIFICAR","OK") -> OK | P43: SIM | Q43: SIM | R43: SIM | T43: 130963997 | U43: 17342286 | V43: =IF(AND(VALUE(N43)=0,VALUE(U43)>0),"VERIFICAR","OK") -> OK | W43: 141706642 | X43: 0 | Y43: NÃO | Z43: 393665 | AA43: 0 | AB43: 0 | AC43: 5291485 | AD43: =IF(AND(Y43="SIM",VALUE(AC43)<0),"VERIFICAR","OK") -> OK | AE43: 67555971 | AF43: 0 | AG43: 0 | AH43: 0 | AI43: 0 | AJ43: =IF(AND(M43="NÃO DEPENDENTE",VALUE(AI43)>0),"INDÍCIO DE DEPENDÊNCIA POR SUBVENÇÃO","OK") -> OK | AK43: 0 | AL43: 0 | AM43: 0 | AN43: 0 | AO43: 0 | AP43: 0 | AQ43: =AP43-AO43 -> 0 | AR43: 44726598 | AS43: 44726598 | AT43: 0 | AU43: 0 | AV43: =(AS43-AR43)+(AU43) -> 0 | AW43: =IF(OR(VALUE(AQ43)>0,VALUE(AV43)>0),"SIM","NÃO") -> NÃO | AX43: =IF(AND(M43="NÃO DEPENDENTE",VALUE(AN43)>0),"VER CAPITAL","OK") -> OK | AY43: =IF(AND(AX43="VER CAPITAL",AW43="NÃO"),"INDÍCIO DE DEPENDÊNCIA POR CAPITAL","OK") -> OK | AZ43: =AC43*100/AE43 -> 7.8327421
B44: BA | C44: EMPRESA BAIANA DE ÁGUAS E SANEAMENTO | D44: EMBASA | E44: 13.504.675/0001-10 | F44: ATIVA | G44: SANEAMENTO | H44: SOCIEDADE DE ECONOMIA MISTA | I44: S.A. | J44: FECHADO | K44: NÃO | L44: NÃO | M44: NÃO DEPENDENTE | N44: 4837 | O44: =IF(AND(F44="ATIVA",VALUE(N44)=0),"VERIFICAR","OK") -> OK | P44: SIM | Q44: SIM | R44: SIM | S44: https://www,embasa,ba,gov,br/a-embasa/quem-somos/governanca/carta-anual-de-politicas-publicas-de-governanca-corporativa | T44: 5.7319573e+09 | U44: 1.0123312e+09 | V44: =IF(AND(VALUE(N44)=0,VALUE(U44)>0),"VERIFICAR","OK") -> OK | W44: 5.8769016e+09 | X44: 1.1673332e+09 | Y44: SIM | Z44: 894298.57 | AA44: 70401.29 | AB44: 18004.38 | AC44: 1.0074783e+09 | AD44: =IF(AND(Y44="SIM",VALUE(AC44)<0),"VERIFICAR","OK") -> OK | AE44: 8.2708979e+09 | AF44: 0 | AG44: 0 | AH44: 0 | AI44: 0 | AJ44: =IF(AND(M44="NÃO DEPENDENTE",VALUE(AI44)>0),"INDÍCIO DE DEPENDÊNCIA POR SUBVENÇÃO","OK") -> OK | AK44: 0 | AL44: 0 | AM44: 0 | AN44: 0 | AO44: 698044720 | AP44: 713145896 | AQ44: =AP44-AO44 -> 15101176 | AR44: 4.9421566e+09 | AS44: 5.0490729e+09 | AT44: 1.0691633e+08 | AU44: 57503611 | AV44: =(AS44-AR44)+(AU44) -> 1.6441994e+08 | AW44: =IF(OR(VALUE(AQ44)>0,VALUE(AV44)>0),"SIM","NÃO") -> SIM | AX44: =IF(AND(M44="NÃO DEPENDENTE",VALUE(AN44)>0),"VER CAPITAL","OK") -> OK | AY44: =IF(AND(AX44="VER CAPITAL",AW44="NÃO"),"INDÍCIO DE DEPENDÊNCIA POR CAPITAL","OK") -> OK | AZ44: =AC44*100/AE44 -> 12.181003
B45: BA | C45: COMPANHIA DE PROCESSAMENTO DE DADOS DO ESTADO DA BAHIA | D45: PRODEB | E45: 13.579.586/0001-32 | F45: ATIVA | G45: INFORMÁTICA E TECNOLOGIA DA INFORMAÇÃO | H45: SOCIEDADE DE ECONOMIA MISTA | I45: S.A. | J45: FECHADO | K45: NÃO | L45: NÃO | M45: NÃO DEPENDENTE | N45: 691 | O45: =IF(AND(F45="ATIVA",VALUE(N45)=0),"VERIFICAR","OK") -> OK | P45: SIM | Q45: SIM | R45: SIM | S45: https://www,prodeb,ba,gov,br/transparencia/governanca-corporativa/carta-anual-de-politicas-publicas-e-governanca-corporativa | T45: 185116460 | U45: 1.0788131e+08 | V45: =IF(AND(VALUE(N45)=0,VALUE(U45)>0),"VERIFICAR","OK") -> OK | W45: 154405800 | X45: 10868764 | Y45: NÃO | Z45: 556998.24 | AA45: 0 | AB45: 0 | AC45: 18634675 | AD45: =IF(AND(Y45="SIM",VALUE(AC45)<0),"VERIFICAR","OK") -> OK | AE45: 119512584 | AF45: 0 | AG45: 0 | AH45: 0 | AI45: 0 | AJ45: =IF(AND(M45="NÃO DEPENDENTE",VALUE(AI45)>0),"INDÍCIO DE DEPENDÊNCIA POR SUBVENÇÃO","OK") -> OK | AK45: 0 | AL45: 0 | AM45: 0 | AN45: 0 | AO45: 2.1180689e+10 | AP45: 2.1180689e+10 | AQ45: =AP45-AO45 -> 0 | AR45: 111887147 | AS45: 118292477 | AT45: 8829991 | AU45: 2424661 | AV45: =(AS45-AR45)+(AU45) -> 8829991 | AW45: =IF(OR(VALUE(AQ45)>0,VALUE(AV45)>0),"SIM","NÃO") -> SIM | AX45: =IF(AND(M45="NÃO DEPENDENTE",VALUE(AN45)>0),"VER CAPITAL","OK") -> OK | AY45: =IF(AND(AX45="VER CAPITAL",AW45="NÃO"),"INDÍCIO DE DEPENDÊNCIA POR CAPITAL","OK") -> OK | AZ45: =AC45*100/AE45 -> 15.592228
B46: BA | C46: HABITAÇÃO E URBANIZAÇÃO DA BAHIA S.A. | D46: URBIS | E46: 15.171.101/0001-00 | F46: EM LIQUIDAÇÃO | G46: HABITAÇÃO E URBANIZAÇÃO | H46: SOCIEDADE DE ECONOMIA MISTA | I46: S.A. | J46: FECHADO | K46: NÃO | L46: NÃO | M46: NÃO DEPENDENTE | N46: 51 | O46: =IF(AND(F46="ATIVA",VALUE(N46)=0),"VERIFICAR","OK") -> OK | P46: SIM | Q46: SIM | R46: NÃO | T46: 804650.42 | U46: 9675773 | V46: =IF(AND(VALUE(N46)=0,VALUE(U46)>0),"VERIFICAR","OK") -> OK | W46: 84070079 | X46: 0 | Y46: NÃO | Z46: 348209.88 | AA46: 0 | AB46: 0 | AC46: -72337245 | AD46: =IF(AND(Y46="SIM",VALUE(AC46)<0),"VERIFICAR","OK") -> OK | AE46: -1.104685e+08 | AF46: 0 | AG46: 0 | AH46: 0 | AI46: 0 | AJ46: =IF(AND(M46="NÃO DEPENDENTE",VALUE(AI46)>0),"INDÍCIO DE DEPENDÊNCIA POR SUBVENÇÃO","OK") -> OK | AK46: 0 | AL46: 0 | AM46: 0 | AN46: 0 | AO46: 1764492195 | AP46: 1765390210 | AQ46: =AP46-AO46 -> 898015 | AR46: 353078042 | AS46: 353078042 | AT46: 0 | AU46: 0 | AV46: =(AS46-AR46)+(AU46) -> 0 | AW46: =IF(OR(VALUE(AQ46)>0,VALUE(AV46)>0),"SIM","NÃO") -> SIM | AX46: =IF(AND(M46="NÃO DEPENDENTE",VALUE(AN46)>0),"VER CAPITAL","OK") -> OK | AY46: =IF(AND(AX46="VER CAPITAL",AW46="NÃO"),"INDÍCIO DE DEPENDÊNCIA POR CAPITAL","OK") -> OK | AZ46: =AC46*100/AE46 -> 65.482235
B47: CE | C47: Agência de Desenvolvimento do Estado do Ceará S/A | D47: ADECE | E47: 09.100.913/0001-54 | F47: ATIVA | G47: DESENVOLVIMENTO REGIONAL | H47: SOCIEDADE DE ECONOMIA MISTA | I47: S.A. | J47: FECHADO | K47: NÃO | L47: NÃO | M47: NÃO DEPENDENTE | N47: 139 | O47: =IF(AND(F47="ATIVA",VALUE(N47)=0),"VERIFICAR","OK") -> OK | P47: SIM | Q47: SIM | R47: NÃO | T47: 58806792 | U47: 22091401 | V47: =IF(AND(VALUE(N47)=0,VALUE(U47)>0),"VERIFICAR","OK") -> OK | W47: 68162153 | X47: 26175954 | Y47: NÃO | Z47: 282690.4 | AA47: 0 | AB47: 0 | AC47: 16820593 | AD47: =IF(AND(Y47="SIM",VALUE(AC47)<0),"VERIFICAR","OK") -> OK | AE47: 2.2757306e+08 | AG47: 0 | AH47: 0 | AI47: 0 | AJ47: =IF(AND(M47="NÃO DEPENDENTE",VALUE(AI47)>0),"INDÍCIO DE DEPENDÊNCIA POR SUBVENÇÃO","OK") -> OK | AK47: 0 | AL47: 0 | AM47: 0 | AN47: 18922127 | AO47: 124633269 | AP47: 135966352 | AQ47: =AP47-AO47 -> 11333083 | AR47: 151568606 | AS47: 1.7049073e+08 | AT47: 0 | AU47: 0 | AV47: =(AS47-AR47)+(AU47) -> 18922127 | AW47: =IF(OR(VALUE(AQ47)>0,VALUE(AV47)>0),"SIM","NÃO") -> SIM | AX47: =IF(AND(M47="NÃO DEPENDENTE",VALUE(AN47)>0),"VER CAPITAL","OK") -> VER CAPITAL | AY47: =IF(AND(AX47="VER CAPITAL",AW47="NÃO"),"INDÍCIO DE DEPENDÊNCIA POR CAPITAL","OK") -> OK | AZ47: =AC47*100/AE47 -> 7.3912935
B48: CE | C48: Companhia de Água e Esgoto do Ceará | D48: CAGECE | E48: 07.040.108/0001-57 | F48: ATIVA | G48: SANEAMENTO | H48: SOCIEDADE DE ECONOMIA MISTA | I48: S.A. | J48: FECHADO | K48: NÃO | L48: NÃO | M48: NÃO DEPENDENTE | N48: 5769 | O48: =IF(AND(F48="ATIVA",VALUE(N48)=0),"VERIFICAR","OK") -> OK | P48: SIM | Q48: SIM | R48: SIM | S48: https://www,cagece,com,br/wp-content/uploads/PDF/Governanca/Documentos/DocumentosdeRegulacaoInterna/CartaAnual/Carta-Anual-de-Politicas-Publicas-e-Governanca-Corporativa-2023,pdf | T48: 3.1370183e+09 | U48: 7.5056124e+08 | V48: =IF(AND(VALUE(N48)=0,VALUE(U48)>0),"VERIFICAR","OK") -> OK | W48: 4.1028885e+09 | X48: 1.3199202e+09 | Y48: SIM | Z48: 796275.06 | AA48: 51422.73 | AB48: 64733.55 | AC48: 3.5405001e+08 | AD48: =IF(AND(Y48="SIM",VALUE(AC48)<0),"VERIFICAR","OK") -> OK | AE48: 3.3176765e+09 | AG48: 0 | AH48: 0 | AI48: 0 | AJ48: =IF(AND(M48="NÃO DEPENDENTE",VALUE(AI48)>0),"INDÍCIO DE DEPENDÊNCIA POR SUBVENÇÃO","OK") -> OK | AK48: 0 | AL48: 0 | AM48: 38334496 | AN48: 82919565 | AO48: 164603035 | AP48: 169275465 | AQ48: =AP48-AO48 -> 4672430 | AR48: 2.1691017e+09 | AS48: 2.3362592e+09 | AT48: 0 | AU48: 0 | AV48: =(AS48-AR48)+(AU48) -> 1.6715749e+08 | AW48: =IF(OR(VALUE(AQ48)>0,VALUE(AV48)>0),"SIM","NÃO") -> SIM | AX48: =IF(AND(M48="NÃO DEPENDENTE",VALUE(AN48)>0),"VER CAPITAL","OK") -> VER CAPITAL | AY48: =IF(AND(AX48="VER CAPITAL",AW48="NÃO"),"INDÍCIO DE DEPENDÊNCIA POR CAPITAL","OK") -> OK | AZ48: =AC48*100/AE48 -> 10.671625
B49: CE | C49: Companhia de Participação de Ativos do Ceará | D49: CEARAPAR | E49: 44.062.163/0001-74 | F49: ATIVA | G49: GESTÃO DE ATIVOS | H49: SOCIEDADE DE ECONOMIA MISTA | I49: S.A. | J49: FECHADO | K49: NÃO | L49: NÃO | M49: NÃO DEPENDENTE | N49: 22 | O49: =IF(AND(F49="ATIVA",VALUE(N49)=0),"VERIFICAR","OK") -> OK | P49: SIM | Q49: SIM | R49: NÃO | S49: https://cppub,cepart,com,br/upload/docInst/Carta_Anual_2023_cearapar,pdf | T49: 6085723.8 | U49: 4250289.7 | V49: =IF(AND(VALUE(N49)=0,VALUE(U49)>0),"VERIFICAR","OK") -> OK | W49: 5176423.6 | X49: 88157.72 | Y49: NÃO | Z49: 193581.5 | AA49: 0 | AB49: 0 | AC49: -245882.77 | AD49: =IF(AND(Y49="SIM",VALUE(AC49)<0),"VERIFICAR","OK") -> OK | AE49: 1042708.6 | AG49: 0 | AH49: 0 | AI49: 0 | AJ49: =IF(AND(M49="NÃO DEPENDENTE",VALUE(AI49)>0),"INDÍCIO DE DEPENDÊNCIA POR SUBVENÇÃO","OK") -> OK | AK49: 0 | AL49: 0 | AM49: 0 | AN49: 0 | AO49: 4999999 | AP49: 4999999 | AQ49: =AP49-AO49 -> 0 | AR49: 5000000 | AS49: 5000000 | AT49: 0 | AU49: 0 | AV49: =(AS49-AR49)+(AU49) -> 0 | AW49: =IF(OR(VALUE(AQ49)>0,VALUE(AV49)>0),"SIM","NÃO") -> NÃO | AX49: =IF(AND(M49="NÃO DEPENDENTE",VALUE(AN49)>0),"VER CAPITAL","OK") -> OK | AY49: =IF(AND(AX49="VER CAPITAL",AW49="NÃO"),"INDÍCIO DE DEPENDÊNCIA POR CAPITAL","OK") -> OK | AZ49: =AC49*100/AE49 -> -23.581158
B50: CE | C50: Centrais de Abastecimento do Ceará S/A | D50: CEASA | E50: 07.029.051/0001-95 | F50: ATIVA | G50: ABASTECIMENTO DE ALIMENTOS E OUTROS INSUMOS | H50: SOCIEDADE DE ECONOMIA MISTA | I50: S.A. | J50: FECHADO | K50: NÃO | L50: NÃO | M50: NÃO DEPENDENTE | N50: 265 | O50: =IF(AND(F50="ATIVA",VALUE(N50)=0),"VERIFICAR","OK") -> OK | P50: SIM | Q50: SIM | R50: NÃO | T50: 34174606 | U50: 18912827 | V50: =IF(AND(VALUE(N50)=0,VALUE(U50)>0),"VERIFICAR","OK") -> OK | W50: 34254277 | X50: 0 | Y50: NÃO | Z50: 180982.64 | AA50: 0 | AB50: 0 | AC50: 66798 | AD50: =IF(AND(Y50="SIM",VALUE(AC50)<0),"VERIFICAR","OK") -> OK | AE50: 7171691 | AG50: 0 | AH50: 0 | AI50: 0 | AJ50: =IF(AND(M50="NÃO DEPENDENTE",VALUE(AI50)>0),"INDÍCIO DE DEPENDÊNCIA POR SUBVENÇÃO","OK") -> OK | AK50: 0 | AL50: 0 | AM50: 0 | AN50: 0 | AO50: 3729073 | AP50: 3729073 | AQ50: =AP50-AO50 -> 0 | AR50: 3729073 | AS50: 3729073 | AT50: 0 | AU50: 0 | AV50: =(AS50-AR50)+(AU50) -> 0 | AW50: =IF(OR(VALUE(AQ50)>0,VALUE(AV50)>0),"SIM","NÃO") -> NÃO | AX50: =IF(AND(M50="NÃO DEPENDENTE",VALUE(AN50)>0),"VER CAPITAL","OK") -> OK | AY50: =IF(AND(AX50="VER CAPITAL",AW50="NÃO"),"INDÍCIO DE DEPENDÊNCIA POR CAPITAL","OK") -> OK | AZ50: =AC50*100/AE50 -> 0.93141213
B51: CE | C51: Companhia de Gás do Ceará | D51: CEGAS | E51: 73.759.185/0001-96 | F51: ATIVA | G51: GÁS E DERIVADOS | H51: SOCIEDADE DE ECONOMIA MISTA | I51: S.A. | J51: FECHADO | K51: NÃO | L51: NÃO | M51: NÃO DEPENDENTE | N51: 143 | O51: =IF(AND(F51="ATIVA",VALUE(N51)=0),"VERIFICAR","OK") -> OK | P51: SIM | Q51: SIM | R51: SIM | S51: https://www,cegas,com,br | T51: 6.4790453e+08 | U51: 14145215 | V51: =IF(AND(VALUE(N51)=0,VALUE(U51)>0),"VERIFICAR","OK") -> OK | W51: 7.186766e+08 | X51: 35321589 | Y51: SIM | Z51: 403935.4 | AA51: 44869 | AB51: 0 | AC51: 53836635 | AD51: =IF(AND(Y51="SIM",VALUE(AC51)<0),"VERIFICAR","OK") -> OK | AE51: 2.7270945e+08 | AG51: 11982825 | AH51: 0 | AI51: 0 | AJ51: =IF(AND(M51="NÃO DEPENDENTE",VALUE(AI51)>0),"INDÍCIO DE DEPENDÊNCIA POR SUBVENÇÃO","OK") -> OK | AK51: 0 | AL51: 0 | AM51: 0 | AN51: 0 | AO51: 11449572 | AP51: 11449572 | AQ51: =AP51-AO51 -> 0 | AR51: 54393290 | AS51: 58681100 | AT51: 0 | AU51: 0 | AV51: =(AS51-AR51)+(AU51) -> 4287809.5 | AW51: =IF(OR(VALUE(AQ51)>0,VALUE(AV51)>0),"SIM","NÃO") -> SIM | AX51: =IF(AND(M51="NÃO DEPENDENTE",VALUE(AN51)>0),"VER CAPITAL","OK") -> OK | AY51: =IF(AND(AX51="VER CAPITAL",AW51="NÃO"),"INDÍCIO DE DEPENDÊNCIA POR CAPITAL","OK") -> OK | AZ51: =AC51*100/AE51 -> 19.74139
B52: CE | C52: Companhia de Desenvolvimento do Complexo Industrial e Portuário do Pecém - CIPP S/A | D52: CIPP | E52: 01.256.678/0001-00 | F52: ATIVA | G52: PORTOS E HIDROVIAS | H52: SOCIEDADE DE ECONOMIA MISTA | I52: S.A. | J52: FECHADO | K52: NÃO | L52: NÃO | M52: NÃO DEPENDENTE | N52: 375 | O52: =IF(AND(F52="ATIVA",VALUE(N52)=0),"VERIFICAR","OK") -> OK | P52: SIM | Q52: SIM | R52: SIM | S52: https://www,complexodopecem,com,br/wp-content/uploads/2021/10/Carta-Anual-2024,pdf | T52: 2.9110418e+08 | U52: 94346584 | V52: =IF(AND(VALUE(N52)=0,VALUE(U52)>0),"VERIFICAR","OK") -> OK | W52: 2.0907628e+08 | X52: 49933261 | Y52: NÃO | Z52: 626720.41 | AA52: 0 | AB52: 68522.29 | AC52: 98567135 | AD52: =IF(AND(Y52="SIM",VALUE(AC52)<0),"VERIFICAR","OK") -> OK | AE52: 1.3507565e+09 | AF52: 1.3507565e+09 | AG52: 17219203 | AH52: 0 | AI52: 0 | AJ52: =IF(AND(M52="NÃO DEPENDENTE",VALUE(AI52)>0),"INDÍCIO DE DEPENDÊNCIA POR SUBVENÇÃO","OK") -> OK | AK52: 600274.64 | AL52: 2645714.3 | AM52: 0 | AN52: 0 | AO52: 123848859 | AP52: 123848859 | AQ52: =AP52-AO52 -> 0 | AR52: 7.4876065e+08 | AS52: 7.4876065e+08 | AT52: 0 | AU52: 0 | AV52: =(AS52-AR52)+(AU52) -> 0 | AW52: =IF(OR(VALUE(AQ52)>0,VALUE(AV52)>0),"SIM","NÃO") -> NÃO | AX52: =IF(AND(M52="NÃO DEPENDENTE",VALUE(AN52)>0),"VER CAPITAL","OK") -> OK | AY52: =IF(AND(AX52="VER CAPITAL",AW52="NÃO"),"INDÍCIO DE DEPENDÊNCIA POR CAPITAL","OK") -> OK | AZ52: =AC52*100/AE52 -> 7.2971801
B53: CE | C53: Companhia de Gestão dos Recursos Hídricos | D53: COGERH | E53: 74.075.938/0001-07 | F53: ATIVA | G53: SANEAMENTO | H53: SOCIEDADE DE ECONOMIA MISTA | I53: S.A. | J53: FECHADO | K53: NÃO | L53: NÃO | M53: NÃO DEPENDENTE | N53: 952 | O53: =IF(AND(F53="ATIVA",VALUE(N53)=0),"VERIFICAR","OK") -> OK | P53: SIM | Q53: SIM | R53: SIM | S53: https://portal,cogerh,com,br/wp-content/uploads/2024/10/ASGRC%202024%20CARTA%20ANUAL%20ano%20base%202023%20,pdf | T53: 228237130 | U53: 110210112 | V53: =IF(AND(VALUE(N53)=0,VALUE(U53)>0),"VERIFICAR","OK") -> OK | W53: 221229629 | X53: 13273633 | Y53: SIM | Z53: 561341.06 | AA53: 33292.64 | AB53: 0 | AC53: 14241975 | AD53: =IF(AND(Y53="SIM",VALUE(AC53)<0),"VERIFICAR","OK") -> OK | AE53: 275152984 | AF53: 275152984 | AG53: 1201000 | AH53: 0 | AI53: 0 | AJ53: =IF(AND(M53="NÃO DEPENDENTE",VALUE(AI53)>0),"INDÍCIO DE DEPENDÊNCIA POR SUBVENÇÃO","OK") -> OK | AK53: 0 | AL53: 0 | AM53: 3350355 | AN53: 5701731 | AO53: 161410751 | AP53: 161410758 | AQ53: =AP53-AO53 -> 7 | AR53: 152912091 | AS53: 158613822 | AT53: 8498667 | AU53: 2796936 | AV53: =(AS53-AR53)+(AU53) -> 8498667 | AW53: =IF(OR(VALUE(AQ53)>0,VALUE(AV53)>0),"SIM","NÃO") -> SIM | AX53: =IF(AND(M53="NÃO DEPENDENTE",VALUE(AN53)>0),"VER CAPITAL","OK") -> VER CAPITAL | AY53: =IF(AND(AX53="VER CAPITAL",AW53="NÃO"),"INDÍCIO DE DEPENDÊNCIA POR CAPITAL","OK") -> OK | AZ53: =AC53*100/AE53 -> 5.1760206
B54: CE | C54: Companhia de Habitação do Ceará | D54: COHAB | E54: 07.121.536/0001-04 | F54: EM LIQUIDAÇÃO | G54: HABITAÇÃO E URBANIZAÇÃO | H54: SOCIEDADE DE ECONOMIA MISTA | I54: S.A. | J54: FECHADO | K54: NÃO | L54: NÃO | M54: DEPENDENTE | N54: 45 | O54: =IF(AND(F54="ATIVA",VALUE(N54)=0),"VERIFICAR","OK") -> OK | P54: NÃO | Q54: SIM | R54: NÃO | T54: 889561.62 | U54: 2958289.8 | V54: =IF(AND(VALUE(N54)=0,VALUE(U54)>0),"VERIFICAR","OK") -> OK | W54: 14936810 | X54: 66780 | Y54: NÃO | Z54: 121610.4 | AA54: 0 | AB54: 0 | AC54: -10281440 | AD54: =IF(AND(Y54="SIM",VALUE(AC54)<0),"VERIFICAR","OK") -> OK | AE54: -3.1555923e+08 | AG54: 0 | AH54: 9400117.8 | AI54: 3685417.1 | AJ54: =IF(AND(M54="NÃO DEPENDENTE",VALUE(AI54)>0),"INDÍCIO DE DEPENDÊNCIA POR SUBVENÇÃO","OK") -> OK | AK54: 7.2494858e+08 | AL54: 7.3182139e+08 | AM54: 0 | AN54: 0 | AO54: 29404405 | AP54: 29404405 | AQ54: =AP54-AO54 -> 0 | AR54: 29404405 | AS54: 29404405 | AT54: 0 | AU54: 0 | AV54: =(AS54-AR54)+(AU54) -> 0 | AW54: =IF(OR(VALUE(AQ54)>0,VALUE(AV54)>0),"SIM","NÃO") -> NÃO | AX54: =IF(AND(M54="NÃO DEPENDENTE",VALUE(AN54)>0),"VER CAPITAL","OK") -> OK | AY54: =IF(AND(AX54="VER CAPITAL",AW54="NÃO"),"INDÍCIO DE DEPENDÊNCIA POR CAPITAL","OK") -> OK | AZ54: =AC54*100/AE54 -> 3.2581649
B55: CE | C55: Empresa de Assistência Técnica e Extensão Rural do Ceará | D55: EMATERCE | E55: 05.371.711/0001-96 | F55: ATIVA | G55: PESQUISA E ASSISTÊNCIA TÉCNICA AGROPECUÁRIA | H55: EMPRESA PÚBLICA | I55: OUTRAS | J55: FECHADO | K55: NÃO | L55: NÃO | M55: DEPENDENTE | N55: 743 | O55: =IF(AND(F55="ATIVA",VALUE(N55)=0),"VERIFICAR","OK") -> OK | P55: SIM | Q55: SIM | R55: NÃO | T55: 1.3563043e+08 | U55: 1.2130789e+08 | V55: =IF(AND(VALUE(N55)=0,VALUE(U55)>0),"VERIFICAR","OK") -> OK | W55: 1.3608158e+08 | X55: 0 | Y55: NÃO | Z55: 503399.06 | AA55: 0 | AB55: 0 | AC55: -476324.62 | AD55: =IF(AND(Y55="SIM",VALUE(AC55)<0),"VERIFICAR","OK") -> OK | AE55: -93996136 | AG55: 0 | AH55: 1.2584748e+08 | AI55: 1.3569886e+08 | AJ55: =IF(AND(M55="NÃO DEPENDENTE",VALUE(AI55)>0),"INDÍCIO DE DEPENDÊNCIA POR SUBVENÇÃO","OK") -> OK | AK55: 0 | AL55: 0 | AM55: 0 | AN55: 0 | AO55: 0 | AP55: 0 | AQ55: =AP55-AO55 -> 0 | AR55: 2511583.8 | AS55: 2511583.8 | AT55: 0 | AU55: 0 | AV55: =(AS55-AR55)+(AU55) -> 0 | AW55: =IF(OR(VALUE(AQ55)>0,VALUE(AV55)>0),"SIM","NÃO") -> NÃO | AX55: =IF(AND(M55="NÃO DEPENDENTE",VALUE(AN55)>0),"VER CAPITAL","OK") -> OK | AY55: =IF(AND(AX55="VER CAPITAL",AW55="NÃO"),"INDÍCIO DE DEPENDÊNCIA POR CAPITAL","OK") -> OK | AZ55: =AC55*100/AE55 -> 0.50674915
B56: CE | C56: Empresa de Tecnologia da Informação do Ceará | D56: ETICE | E56: 03.773.788/0001-67 | F56: ATIVA | G56: INFORMÁTICA E TECNOLOGIA DA INFORMAÇÃO | H56: EMPRESA PÚBLICA | I56: S.A. | J56: FECHADO | K56: NÃO | L56: NÃO | M56: DEPENDENTE | N56: 193 | O56: =IF(AND(F56="ATIVA",VALUE(N56)=0),"VERIFICAR","OK") -> OK | P56: SIM | Q56: SIM | R56: NÃO | S56: https://www,etice,ce,gov,br/cartas-anuais-de-politicas-publicas-e-governanca-corporativa/ | T56: 336115591 | U56: 58947805 | V56: =IF(AND(VALUE(N56)=0,VALUE(U56)>0),"VERIFICAR","OK") -> OK | W56: 315592968 | X56: 141910 | Y56: NÃO | Z56: 534130 | AA56: 0 | AB56: 0 | AC56: 23493609 | AD56: =IF(AND(Y56="SIM",VALUE(AC56)<0),"VERIFICAR","OK") -> OK | AE56: 40007116 | AG56: 0 | AH56: 50337610 | AI56: 52846766 | AJ56: =IF(AND(M56="NÃO DEPENDENTE",VALUE(AI56)>0),"INDÍCIO DE DEPENDÊNCIA POR SUBVENÇÃO","OK") -> OK | AK56: 0 | AL56: 0 | AM56: 0 | AN56: 0 | AO56: 100 | AP56: 100 | AQ56: =AP56-AO56 -> 0 | AR56: 50000 | AS56: 13748706 | AT56: 0 | AU56: 0 | AV56: =(AS56-AR56)+(AU56) -> 13698706 | AW56: =IF(OR(VALUE(AQ56)>0,VALUE(AV56)>0),"SIM","NÃO") -> SIM | AX56: =IF(AND(M56="NÃO DEPENDENTE",VALUE(AN56)>0),"VER CAPITAL","OK") -> OK | AY56: =IF(AND(AX56="VER CAPITAL",AW56="NÃO"),"INDÍCIO DE DEPENDÊNCIA POR CAPITAL","OK") -> OK | AZ56: =AC56*100/AE56 -> 58.723576
B57: CE | C57: Companhia Cearense de Transportes Metropolitanos | D57: METROFOR | E57: 02.003.575/0001-93 | F57: ATIVA | G57: TRANSPORTE | H57: SOCIEDADE DE ECONOMIA MISTA | I57: S.A. | J57: FECHADO | K57: NÃO | L57: NÃO | M57: NÃO DEPENDENTE | N57: 1114 | O57: =IF(AND(F57="ATIVA",VALUE(N57)=0),"VERIFICAR","OK") -> OK | P57: SIM | Q57: SIM | R57: SIM | S57: https://www,metrofor,ce,gov,br/wp-content/uploads/sites/32/2022/03/Carta_Poli%CC%81ticas_Pu%CC%81blicasGovernanc%CC%A7a-2021,pdf | T57: 2.4410182e+08 | U57: 1.3275466e+08 | V57: =IF(AND(VALUE(N57)=0,VALUE(U57)>0),"VERIFICAR","OK") -> OK | W57: 3.6916145e+08 | X57: 8617638.5 | Y57: NÃO | Z57: 326294.08 | AA57: 0 | AB57: 0 | AC57: -67338883 | AD57: =IF(AND(Y57="SIM",VALUE(AC57)<0),"VERIFICAR","OK") -> OK | AE57: 9.1595358e+08 | AG57: 0 | AH57: 1.9400167e+08 | AI57: 2.1501189e+08 | AJ57: =IF(AND(M57="NÃO DEPENDENTE",VALUE(AI57)>0),"INDÍCIO DE DEPENDÊNCIA POR SUBVENÇÃO","OK") -> INDÍCIO DE DEPENDÊNCIA POR SUBVENÇÃO | AK57: 0 | AL57: 0 | AM57: 4400000 | AN57: 4000000 | AO57: 2995022400 | AP57: 3000302400 | AQ57: =AP57-AO57 -> 5280000 | AR57: 2495852000 | AS57: 2500252000 | AT57: 0 | AU57: 0 | AV57: =(AS57-AR57)+(AU57) -> 4400000 | AW57: =IF(OR(VALUE(AQ57)>0,VALUE(AV57)>0),"SIM","NÃO") -> SIM | AX57: =IF(AND(M57="NÃO DEPENDENTE",VALUE(AN57)>0),"VER CAPITAL","OK") -> VER CAPITAL | AY57: =IF(AND(AX57="VER CAPITAL",AW57="NÃO"),"INDÍCIO DE DEPENDÊNCIA POR CAPITAL","OK") -> OK | AZ57: =AC57*100/AE57 -> -7.351779
B58: CE | C58: ZPE Ceará | D58: ZPE | E58: 13.006.170/0001-25 | F58: ATIVA | G58: DESENVOLVIMENTO REGIONAL | H58: SOCIEDADE DE ECONOMIA MISTA | I58: S.A. | J58: FECHADO | K58: NÃO | L58: SIM | M58: NÃO DEPENDENTE | N58: 152 | O58: =IF(AND(F58="ATIVA",VALUE(N58)=0),"VERIFICAR","OK") -> OK | P58: SIM | Q58: SIM | R58: NÃO | S58: https://zpeceara,com,br/wp-content/uploads/2024/05/Carta-Anual-2023_ZPE,pdf | T58: 44297903 | U58: 17924084 | V58: =IF(AND(VALUE(N58)=0,VALUE(U58)>0),"VERIFICAR","OK") -> OK | W58: 29998260 | X58: 3495688.5 | Y58: SIM | Z58: 287117.16 | AA58: 147625.3 | AB58: 0 | AC58: 13568036 | AD58: =IF(AND(Y58="SIM",VALUE(AC58)<0),"VERIFICAR","OK") -> OK | AE58: 35820464 | AG58: 0 | AH58: 0 | AI58: 0 | AJ58: =IF(AND(M58="NÃO DEPENDENTE",VALUE(AI58)>0),"INDÍCIO DE DEPENDÊNCIA POR SUBVENÇÃO","OK") -> OK | AK58: 0 | AL58: 0 | AM58: 0 | AN58: 0 | AO58: 0 | AP58: 0 | AQ58: =AP58-AO58 -> 0 | AR58: 0 | AS58: 0 | AT58: 0 | AU58: 0 | AV58: =(AS58-AR58)+(AU58) -> 0 | AW58: =IF(OR(VALUE(AQ58)>0,VALUE(AV58)>0),"SIM","NÃO") -> NÃO | AX58: =IF(AND(M58="NÃO DEPENDENTE",VALUE(AN58)>0),"VER CAPITAL","OK") -> OK | AY58: =IF(AND(AX58="VER CAPITAL",AW58="NÃO"),"INDÍCIO DE DEPENDÊNCIA POR CAPITAL","OK") -> OK | AZ58: =AC58*100/AE58 -> 37.87789
B59: DF | C59: BIOTIC S.A. | D59: BIOTIC | E59: 29.580.134/0001-00 | F59: ATIVA | G59: DESENVOLVIMENTO REGIONAL | H59: EMPRESA PÚBLICA | I59: S.A. | J59: FECHADO | K59: NÃO | L59: SIM | M59: NÃO DEPENDENTE | N59: 69 | O59: =IF(AND(F59="ATIVA",VALUE(N59)=0),"VERIFICAR","OK") -> OK | P59: SIM | Q59: SIM | R59: NÃO | S59: https://www,bioticsa,com,br/pdf/Carta_governanca_Bioti | T59: 0 | U59: 10021616 | V59: =IF(AND(VALUE(N59)=0,VALUE(U59)>0),"VERIFICAR","OK") -> OK | W59: 18009638 | X59: 1515396.6 | Y59: NÃO | Z59: 532630.43 | AA59: 0 | AB59: 0 | AC59: 28800626 | AD59: =IF(AND(Y59="SIM",VALUE(AC59)<0),"VERIFICAR","OK") -> OK | AE59: 1052610978 | AG59: 0 | AH59: 0 | AI59: 0 | AJ59: =IF(AND(M59="NÃO DEPENDENTE",VALUE(AI59)>0),"INDÍCIO DE DEPENDÊNCIA POR SUBVENÇÃO","OK") -> OK | AK59: 0 | AL59: 0 | AM59: 0 | AN59: 0 | AO59: 9958047 | AP59: 9958047 | AQ59: =AP59-AO59 -> 0 | AR59: 995804700 | AS59: 995804700 | AT59: -5794655 | AU59: -5794655 | AV59: =(AS59-AR59)+(AU59) -> -5794655 | AW59: =IF(OR(VALUE(AQ59)>0,VALUE(AV59)>0),"SIM","NÃO") -> NÃO | AX59: =IF(AND(M59="NÃO DEPENDENTE",VALUE(AN59)>0),"VER CAPITAL","OK") -> OK | AY59: =IF(AND(AX59="VER CAPITAL",AW59="NÃO"),"INDÍCIO DE DEPENDÊNCIA POR CAPITAL","OK") -> OK | AZ59: =AC59*100/AE59 -> 2.736113
B60: DF | C60: Banco Regional de Brasília | D60: BRB | E60: 00.000.208/0001-00 | F60: ATIVA | G60: FINANCEIRO | H60: SOCIEDADE DE ECONOMIA MISTA | I60: S.A. | J60: ABERTO | K60: SIM | L60: NÃO | M60: NÃO DEPENDENTE | N60: 3359 | O60: =IF(AND(F60="ATIVA",VALUE(N60)=0),"VERIFICAR","OK") -> OK | P60: SIM | Q60: SIM | R60: SIM | S60: https://ri,brb,com,br/pt/carta-anual-de-politicas-publicas-e-governanca-corporativa | T60: 2.2933871e+08 | U60: 1.2153397e+09 | V60: =IF(AND(VALUE(N60)=0,VALUE(U60)>0),"VERIFICAR","OK") -> OK | W60: 8.1566339e+09 | X60: 2.0608693e+08 | Y60: SIM | Z60: 837726.37 | AA60: 324385.26 | AB60: 0 | AC60: 1.9571683e+08 | AD60: =IF(AND(Y60="SIM",VALUE(AC60)<0),"VERIFICAR","OK") -> OK | AE60: 3.6873314e+09 | AF60: 3.190606e+09 | AG60: 1206204.5 | AH60: 0 | AI60: 0 | AJ60: =IF(AND(M60="NÃO DEPENDENTE",VALUE(AI60)>0),"INDÍCIO DE DEPENDÊNCIA POR SUBVENÇÃO","OK") -> OK | AK60: 0 | AL60: 0 | AM60: 0 | AN60: 0 | AO60: 71.92 | AP60: 65.63 | AQ60: =AP60-AO60 -> -6.29 | AR60: 0 | AS60: 0 | AT60: 0 | AU60: 0 | AV60: =(AS60-AR60)+(AU60) -> 0 | AW60: =IF(OR(VALUE(AQ60)>0,VALUE(AV60)>0),"SIM","NÃO") -> NÃO | AX60: =IF(AND(M60="NÃO DEPENDENTE",VALUE(AN60)>0),"VER CAPITAL","OK") -> OK | AY60: =IF(AND(AX60="VER CAPITAL",AW60="NÃO"),"INDÍCIO DE DEPENDÊNCIA POR CAPITAL","OK") -> OK | AZ60: =AC60*100/AE60 -> 5.3078176
B61: DF | C61: BRB - Administradora e Corretora de Seguros S/A | D61: BRB Administradora | E61: 42.597.575/0001-83 | F61: ATIVA | G61: FINANCEIRO | H61: SOCIEDADE DE ECONOMIA MISTA | I61: S.A. | J61: FECHADO | K61: NÃO | L61: SIM | M61: NÃO DEPENDENTE | N61: 0 | O61: =IF(AND(F61="ATIVA",VALUE(N61)=0),"VERIFICAR","OK") -> VERIFICAR | P61: NÃO | Q61: SIM | R61: NÃO | T61: 301617.51 | U61: 1490863.6 | V61: =IF(AND(VALUE(N61)=0,VALUE(U61)>0),"VERIFICAR","OK") -> VERIFICAR | W61: 2979003.3 | X61: 0 | Y61: NÃO | Z61: 0 | AA61: 0 | AB61: 0 | AC61: 80614672 | AD61: =IF(AND(Y61="SIM",VALUE(AC61)<0),"VERIFICAR","OK") -> OK | AE61: 4.9954158e+08 | AG61: 0 | AH61: 0 | AI61: 0 | AJ61: =IF(AND(M61="NÃO DEPENDENTE",VALUE(AI61)>0),"INDÍCIO DE DEPENDÊNCIA POR SUBVENÇÃO","OK") -> OK | AK61: 0 | AL61: 0 | AM61: 0 | AN61: 0 | AO61: 0 | AP61: 0 | AQ61: =AP61-AO61 -> 0 | AR61: 0 | AS61: 0 | AT61: 0 | AU61: 0 | AV61: =(AS61-AR61)+(AU61) -> 0 | AW61: =IF(OR(VALUE(AQ61)>0,VALUE(AV61)>0),"SIM","NÃO") -> NÃO | AX61: =IF(AND(M61="NÃO DEPENDENTE",VALUE(AN61)>0),"VER CAPITAL","OK") -> OK | AY61: =IF(AND(AX61="VER CAPITAL",AW61="NÃO"),"INDÍCIO DE DEPENDÊNCIA POR CAPITAL","OK") -> OK | AZ61: =AC61*100/AE61 -> 16.13773
B62: DF | C62: BRB Distribuidora de Títulos e Valores Mobiliários | D62: BRB DVTM | E62: 33.850.686/0001-69 | F62: ATIVA | G62: FINANCEIRO | H62: SOCIEDADE DE ECONOMIA MISTA | I62: S.A. | J62: FECHADO | K62: NÃO | L62: SIM | M62: NÃO DEPENDENTE | N62: 38 | O62: =IF(AND(F62="ATIVA",VALUE(N62)=0),"VERIFICAR","OK") -> OK | P62: SIM | Q62: SIM | R62: SIM | T62: 11143665 | U62: 3082019.4 | V62: =IF(AND(VALUE(N62)=0,VALUE(U62)>0),"VERIFICAR","OK") -> OK | W62: 26478526 | X62: 0 | Y62: SIM | Z62: 697595.69 | AA62: 74146.85 | AB62: 0 | AC62: 5674698.7 | AD62: =IF(AND(Y62="SIM",VALUE(AC62)<0),"VERIFICAR","OK") -> OK | AE62: 62259026 | AG62: 0 | AH62: 0 | AI62: 0 | AJ62: =IF(AND(M62="NÃO DEPENDENTE",VALUE(AI62)>0),"INDÍCIO DE DEPENDÊNCIA POR SUBVENÇÃO","OK") -> OK | AK62: 0 | AL62: 0 | AM62: 0 | AN62: 0 | AO62: 0 | AP62: 0 | AQ62: =AP62-AO62 -> 0 | AR62: 40000000 | AS62: 40000000 | AT62: 0 | AU62: 0 | AV62: =(AS62-AR62)+(AU62) -> 0 | AW62: =IF(OR(VALUE(AQ62)>0,VALUE(AV62)>0),"SIM","NÃO") -> NÃO | AX62: =IF(AND(M62="NÃO DEPENDENTE",VALUE(AN62)>0),"VER CAPITAL","OK") -> OK | AY62: =IF(AND(AX62="VER CAPITAL",AW62="NÃO"),"INDÍCIO DE DEPENDÊNCIA POR CAPITAL","OK") -> OK | AZ62: =AC62*100/AE62 -> 9.1146603
B63: DF | C63: BRB Crédito, Financiamento e Investimento | D63: BRB Investimento | E63: 33.136.888/0001-43 | F63: ATIVA | G63: FINANCEIRO | H63: SOCIEDADE DE ECONOMIA MISTA | I63: S.A. | J63: FECHADO | K63: NÃO | L63: SIM | M63: NÃO DEPENDENTE | N63: 0 | O63: =IF(AND(F63="ATIVA",VALUE(N63)=0),"VERIFICAR","OK") -> VERIFICAR | P63: NÃO | Q63: SIM | R63: NÃO | T63: 2.3411907e+08 | U63: 567953.8 | V63: =IF(AND(VALUE(N63)=0,VALUE(U63)>0),"VERIFICAR","OK") -> VERIFICAR | W63: 9.7787041e+08 | X63: 0 | Y63: SIM | Z63: 614208.7 | AA63: 20796.97 | AB63: 0 | AC63: 1.4105431e+08 | AD63: =IF(AND(Y63="SIM",VALUE(AC63)<0),"VERIFICAR","OK") -> OK | AE63: 4.3372701e+08 | AG63: 0 | AH63: 0 | AI63: 0 | AJ63: =IF(AND(M63="NÃO DEPENDENTE",VALUE(AI63)>0),"INDÍCIO DE DEPENDÊNCIA POR SUBVENÇÃO","OK") -> OK | AK63: 0 | AL63: 0 | AM63: 0 | AN63: 0 | AO63: 420 | AP63: 420 | AQ63: =AP63-AO63 -> 0 | AR63: 150000000 | AS63: 150000000 | AT63: 0 | AU63: 0 | AV63: =(AS63-AR63)+(AU63) -> 0 | AW63: =IF(OR(VALUE(AQ63)>0,VALUE(AV63)>0),"SIM","NÃO") -> NÃO | AX63: =IF(AND(M63="NÃO DEPENDENTE",VALUE(AN63)>0),"VER CAPITAL","OK") -> OK | AY63: =IF(AND(AX63="VER CAPITAL",AW63="NÃO"),"INDÍCIO DE DEPENDÊNCIA POR CAPITAL","OK") -> OK | AZ63: =AC63*100/AE63 -> 32.52145
B64: DF | C64: BRB Participacoes | D64: BRB PAR | E64: 13.431.899/0001-49 | F64: ATIVA | G64: FINANCEIRO | H64: EMPRESA PÚBLICA | I64: S.A. | J64: FECHADO | K64: NÃO | L64: SIM | M64: NÃO DEPENDENTE | N64: 0 | O64: =IF(AND(F64="ATIVA",VALUE(N64)=0),"VERIFICAR","OK") -> VERIFICAR | P64: SIM | Q64: NÃO | R64: NÃO | T64: 0 | U64: 0 | V64: =IF(AND(VALUE(N64)=0,VALUE(U64)>0),"VERIFICAR","OK") -> OK | W64: 1032.94 | X64: 0 | Y64: NÃO | Z64: 0 | AA64: 0 | AB64: 0 | AC64: 0 | AD64: =IF(AND(Y64="SIM",VALUE(AC64)<0),"VERIFICAR","OK") -> OK | AE64: 0 | AG64: 0 | AH64: 0 | AI64: 0 | AJ64: =IF(AND(M64="NÃO DEPENDENTE",VALUE(AI64)>0),"INDÍCIO DE DEPENDÊNCIA POR SUBVENÇÃO","OK") -> OK | AK64: 0 | AL64: 0 | AM64: 0 | AN64: 0 | AO64: 0 | AP64: 0 | AQ64: =AP64-AO64 -> 0 | AR64: 0 | AS64: 0 | AT64: 0 | AU64: 0 | AV64: =(AS64-AR64)+(AU64) -> 0 | AW64: =IF(OR(VALUE(AQ64)>0,VALUE(AV64)>0),"SIM","NÃO") -> NÃO | AX64: =IF(AND(M64="NÃO DEPENDENTE",VALUE(AN64)>0),"VER CAPITAL","OK") -> OK | AY64: =IF(AND(AX64="VER CAPITAL",AW64="NÃO"),"INDÍCIO DE DEPENDÊNCIA POR CAPITAL","OK") -> OK | AZ64: =AC64*100/AE64 -> #DIV/0!
B65: DF | C65: BRB Serviços | D65: BRB Serviços | E65: 12.875.569/0001-80 | F65: ATIVA | G65: FINANCEIRO | H65: SOCIEDADE DE ECONOMIA MISTA | I65: S.A. | J65: FECHADO | K65: NÃO | L65: SIM | M65: NÃO DEPENDENTE | N65: 1166 | O65: =IF(AND(F65="ATIVA",VALUE(N65)=0),"VERIFICAR","OK") -> OK | P65: SIM | Q65: SIM | R65: NÃO | T65: 100549726 | U65: 72223772 | V65: =IF(AND(VALUE(N65)=0,VALUE(U65)>0),"VERIFICAR","OK") -> OK | W65: 1.0319979e+08 | X65: 0 | Y65: SIM | Z65: 673442.27 | AA65: 66872.98 | AB65: 0 | AC65: -26500068 | AD65: =IF(AND(Y65="SIM",VALUE(AC65)<0),"VERIFICAR","OK") -> VERIFICAR | AE65: 28906244 | AG65: 0 | AH65: 0 | AI65: 0 | AJ65: =IF(AND(M65="NÃO DEPENDENTE",VALUE(AI65)>0),"INDÍCIO DE DEPENDÊNCIA POR SUBVENÇÃO","OK") -> OK | AK65: 0 | AL65: 0 | AM65: 0 | AN65: 0 | AO65: 248000 | AP65: 248000 | AQ65: =AP65-AO65 -> 0 | AR65: 29744203 | AS65: 30000000 | AT65: 255797 | AU65: 0 | AV65: =(AS65-AR65)+(AU65) -> 255797 | AW65: =IF(OR(VALUE(AQ65)>0,VALUE(AV65)>0),"SIM","NÃO") -> SIM | AX65: =IF(AND(M65="NÃO DEPENDENTE",VALUE(AN65)>0),"VER CAPITAL","OK") -> OK | AY65: =IF(AND(AX65="VER CAPITAL",AW65="NÃO"),"INDÍCIO DE DEPENDÊNCIA POR CAPITAL","OK") -> OK | AZ65: =AC65*100/AE65 -> -91.67593
B66: DF | C66: Cartão BRB | D66: BRBCARD | E66: 01.984.199/0001-00 | F66: ATIVA | G66: FINANCEIRO | H66: SOCIEDADE DE ECONOMIA MISTA | I66: S.A. | J66: FECHADO | K66: NÃO | L66: SIM | M66: NÃO DEPENDENTE | N66: 263 | O66: =IF(AND(F66="ATIVA",VALUE(N66)=0),"VERIFICAR","OK") -> OK | P66: SIM | Q66: SIM | R66: NÃO | S66: https://www,brbcard,com,br/wp-content/uploads/2024/09/Carta-Anual-Poli4cas-Publicas-Gov-Corpora4va-2023-vf,pdf | T66: 2.9950892e+08 | U66: 55122089 | V66: =IF(AND(VALUE(N66)=0,VALUE(U66)>0),"VERIFICAR","OK") -> OK | W66: 6.8753458e+08 | X66: 1.2404669e+08 | Y66: SIM | Z66: 428014.97 | AA66: 209404.05 | AB66: 311854.32 | AC66: 36771133 | AD66: =IF(AND(Y66="SIM",VALUE(AC66)<0),"VERIFICAR","OK") -> OK | AE66: 5.8667227e+08 | AG66: 0 | AH66: 0 | AI66: 0 | AJ66: =IF(AND(M66="NÃO DEPENDENTE",VALUE(AI66)>0),"INDÍCIO DE DEPENDÊNCIA POR SUBVENÇÃO","OK") -> OK | AK66: 0 | AL66: 0 | AM66: 0 | AN66: 0 | AO66: 3941551 | AP66: 3941551 | AQ66: =AP66-AO66 -> 0 | AR66: 5.7479121e+08 | AS66: 5.2203472e+08 | AT66: 0 | AU66: 0 | AV66: =(AS66-AR66)+(AU66) -> -52756494 | AW66: =IF(OR(VALUE(AQ66)>0,VALUE(AV66)>0),"SIM","NÃO") -> NÃO | AX66: =IF(AND(M66="NÃO DEPENDENTE",VALUE(AN66)>0),"VER CAPITAL","OK") -> OK | AY66: =IF(AND(AX66="VER CAPITAL",AW66="NÃO"),"INDÍCIO DE DEPENDÊNCIA POR CAPITAL","OK") -> OK | AZ66: =AC66*100/AE66 -> 6.2677469
B67: DF | C67: Companhia de Saneamento Ambiental do Distrito Federal | D67: CAESB | E67: 00.082.024/0001-37 | F67: ATIVA | G67: SANEAMENTO | H67: SOCIEDADE DE ECONOMIA MISTA | I67: S.A. | J67: FECHADO | K67: NÃO | L67: NÃO | M67: NÃO DEPENDENTE | N67: 1997 | O67: =IF(AND(F67="ATIVA",VALUE(N67)=0),"VERIFICAR","OK") -> OK | P67: SIM | Q67: SIM | R67: SIM | S67: https://www,caesb,df,gov,br/empresa/governanca-corporativa/carta-anual,html | T67: 2.2927561e+09 | U67: 9.7515031e+08 | V67: =IF(AND(VALUE(N67)=0,VALUE(U67)>0),"VERIFICAR","OK") -> OK | W67: 2.5299069e+09 | X67: 3.7253331e+08 | Y67: SIM | Z67: 896119.71 | AA67: 24792.52 | AB67: 25755.86 | AC67: 90460720 | AD67: =IF(AND(Y67="SIM",VALUE(AC67)<0),"VERIFICAR","OK") -> OK | AE67: 2248240620 | AG67: 0 | AH67: 0 | AI67: 0 | AJ67: =IF(AND(M67="NÃO DEPENDENTE",VALUE(AI67)>0),"INDÍCIO DE DEPENDÊNCIA POR SUBVENÇÃO","OK") -> OK | AK67: 64529800 | AL67: 43607600 | AM67: 0 | AN67: 0 | AO67: 929456430 | AP67: 929456430 | AQ67: =AP67-AO67 -> 0 | AR67: 2074068686 | AS67: 2074068686 | AT67: 0 | AU67: 0 | AV67: =(AS67-AR67)+(AU67) -> 0 | AW67: =IF(OR(VALUE(AQ67)>0,VALUE(AV67)>0),"SIM","NÃO") -> NÃO | AX67: =IF(AND(M67="NÃO DEPENDENTE",VALUE(AN67)>0),"VER CAPITAL","OK") -> OK | AY67: =IF(AND(AX67="VER CAPITAL",AW67="NÃO"),"INDÍCIO DE DEPENDÊNCIA POR CAPITAL","OK") -> OK | AZ67: =AC67*100/AE67 -> 4.0236227
B68: DF | C68: Centrais de Abastecimento do Distrito Federal | D68: CEASA DF | E68: 00.314.310/0001-80 | F68: ATIVA | G68: ABASTECIMENTO DE ALIMENTOS E OUTROS INSUMOS | H68: SOCIEDADE DE ECONOMIA MISTA | I68: S.A. | J68: FECHADO | K68: NÃO | L68: NÃO | M68: NÃO DEPENDENTE | N68: 60 | O68: =IF(AND(F68="ATIVA",VALUE(N68)=0),"VERIFICAR","OK") -> OK | P68: SIM | Q68: SIM | R68: NÃO | T68: 15958077 | U68: 15729760 | V68: =IF(AND(VALUE(N68)=0,VALUE(U68)>0),"VERIFICAR","OK") -> OK | W68: 20282200 | X68: 0 | Y68: NÃO | Z68: 327915.97 | AA68: 0 | AB68: 0 | AC68: 1866174 | AD68: =IF(AND(Y68="SIM",VALUE(AC68)<0),"VERIFICAR","OK") -> OK | AE68: 60377797 | AG68: 0 | AH68: 0 | AI68: 0 | AJ68: =IF(AND(M68="NÃO DEPENDENTE",VALUE(AI68)>0),"INDÍCIO DE DEPENDÊNCIA POR SUBVENÇÃO","OK") -> OK | AK68: 0 | AL68: 0 | AM68: 0 | AN68: 18000000 | AO68: 32197937 | AP68: 32197937 | AQ68: =AP68-AO68 -> 0 | AR68: 32197937 | AS68: 32197937 | AT68: 0 | AU68: 0 | AV68: =(AS68-AR68)+(AU68) -> 0 | AW68: =IF(OR(VALUE(AQ68)>0,VALUE(AV68)>0),"SIM","NÃO") -> NÃO | AX68: =IF(AND(M68="NÃO DEPENDENTE",VALUE(AN68)>0),"VER CAPITAL","OK") -> VER CAPITAL | AY68: =IF(AND(AX68="VER CAPITAL",AW68="NÃO"),"INDÍCIO DE DEPENDÊNCIA POR CAPITAL","OK") -> INDÍCIO DE DEPENDÊNCIA POR CAPITAL | AZ68: =AC68*100/AE68 -> 3.0908282
B69: DF | C69: Companhia Energética de Brasília | D69: CEB | E69: 00.070.698/0001-11 | F69: ATIVA | G69: ENERGIA | H69: SOCIEDADE DE ECONOMIA MISTA | I69: S.A. | J69: ABERTO | K69: SIM | L69: NÃO | M69: NÃO DEPENDENTE | N69: 120 | O69: =IF(AND(F69="ATIVA",VALUE(N69)=0),"VERIFICAR","OK") -> OK | P69: SIM | Q69: SIM | R69: SIM | S69: https://www,ceb,com,br/Download,aspx?Arquivo=8AtZ9IcMZPUukeHBXSgE3w==&IdCanal=D0mlLqYnKldOCQKkP4Skqg== | T69: 31181843 | U69: 35837829 | V69: =IF(AND(VALUE(N69)=0,VALUE(U69)>0),"VERIFICAR","OK") -> OK | W69: 64043261 | X69: 0 | Y69: SIM | Z69: 716384.41 | AA69: 104728.96 | AB69: 21395.24 | AC69: 1.7422804e+08 | AD69: =IF(AND(Y69="SIM",VALUE(AC69)<0),"VERIFICAR","OK") -> OK | AE69: 1.065393e+09 | AG69: 94835083 | AH69: 0 | AI69: 0 | AJ69: =IF(AND(M69="NÃO DEPENDENTE",VALUE(AI69)>0),"INDÍCIO DE DEPENDÊNCIA POR SUBVENÇÃO","OK") -> OK | AK69: 0 | AL69: 0 | AM69: 0 | AN69: 0 | AO69: 57773215 | AP69: 57773215 | AQ69: =AP69-AO69 -> 0 | AR69: 5.6602536e+08 | AS69: 5.6602536e+08 | AT69: 0 | AU69: 0 | AV69: =(AS69-AR69)+(AU69) -> 0 | AW69: =IF(OR(VALUE(AQ69)>0,VALUE(AV69)>0),"SIM","NÃO") -> NÃO | AX69: =IF(AND(M69="NÃO DEPENDENTE",VALUE(AN69)>0),"VER CAPITAL","OK") -> OK | AY69: =IF(AND(AX69="VER CAPITAL",AW69="NÃO"),"INDÍCIO DE DEPENDÊNCIA POR CAPITAL","OK") -> OK | AZ69: =AC69*100/AE69 -> 16.353406
B70: DF | C70: CEB Iluminação Pública e Serviços | D70: CEB IPES | E70: 39.683.726/0001-01 | F70: ATIVA | G70: ENERGIA | H70: SOCIEDADE DE ECONOMIA MISTA | I70: S.A. | J70: FECHADO | K70: NÃO | L70: SIM | M70: NÃO DEPENDENTE | N70: 77 | O70: =IF(AND(F70="ATIVA",VALUE(N70)=0),"VERIFICAR","OK") -> OK | P70: NÃO | Q70: SIM | R70: NÃO | T70: 51831969 | U70: 19629027 | V70: =IF(AND(VALUE(N70)=0,VALUE(U70)>0),"VERIFICAR","OK") -> OK | W70: 60332472 | X70: 327950 | Y70: SIM | Z70: 591686.76 | AA70: 75404.84 | AB70: 21395.23 | AC70: 14013462 | AD70: =IF(AND(Y70="SIM",VALUE(AC70)<0),"VERIFICAR","OK") -> OK | AE70: 1.975087e+08 | AG70: 5170071 | AH70: 0 | AI70: 0 | AJ70: =IF(AND(M70="NÃO DEPENDENTE",VALUE(AI70)>0),"INDÍCIO DE DEPENDÊNCIA POR SUBVENÇÃO","OK") -> OK | AK70: 0 | AL70: 0 | AM70: 0 | AN70: 0 | AO70: 1.7408058e+08 | AP70: 1.7408058e+08 | AQ70: =AP70-AO70 -> 0 | AR70: 1.7408058e+08 | AS70: 1.7408058e+08 | AT70: 0 | AU70: 0 | AV70: =(AS70-AR70)+(AU70) -> 0 | AW70: =IF(OR(VALUE(AQ70)>0,VALUE(AV70)>0),"SIM","NÃO") -> NÃO | AX70: =IF(AND(M70="NÃO DEPENDENTE",VALUE(AN70)>0),"VER CAPITAL","OK") -> OK | AY70: =IF(AND(AX70="VER CAPITAL",AW70="NÃO"),"INDÍCIO DE DEPENDÊNCIA POR CAPITAL","OK") -> OK | AZ70: =AC70*100/AE70 -> 7.0951112
B71: DF | C71: CEB Lajeado | D71: CEB L | E71: 03.677.638/0001-50 | F71: ATIVA | G71: ENERGIA | H71: SOCIEDADE DE ECONOMIA MISTA | I71: S.A. | J71: FECHADO | K71: NÃO | L71: SIM | M71: NÃO DEPENDENTE | N71: 16 | O71: =IF(AND(F71="ATIVA",VALUE(N71)=0),"VERIFICAR","OK") -> OK | P71: SIM | Q71: SIM | R71: SIM | T71: 2.3436596e+08 | U71: 6859542.1 | V71: =IF(AND(VALUE(N71)=0,VALUE(U71)>0),"VERIFICAR","OK") -> OK | W71: 1.0902097e+08 | X71: 0 | Y71: SIM | Z71: 715997.49 | AA71: 0 | AB71: 13777.72 | AC71: 1.0498987e+08 | AD71: =IF(AND(Y71="SIM",VALUE(AC71)<0),"VERIFICAR","OK") -> OK | AE71: 3.875624e+08 | AG71: 0 | AH71: 0 | AI71: 0 | AJ71: =IF(AND(M71="NÃO DEPENDENTE",VALUE(AI71)>0),"INDÍCIO DE DEPENDÊNCIA POR SUBVENÇÃO","OK") -> OK | AK71: 0 | AL71: 0 | AM71: 0 | AN71: 0 | AO71: 136850013 | AP71: 136850013 | AQ71: =AP71-AO71 -> 0 | AR71: 1.12284e+08 | AS71: 1.12284e+08 | AT71: 0 | AU71: 0 | AV71: =(AS71-AR71)+(AU71) -> 0 | AW71: =IF(OR(VALUE(AQ71)>0,VALUE(AV71)>0),"SIM","NÃO") -> NÃO | AX71: =IF(AND(M71="NÃO DEPENDENTE",VALUE(AN71)>0),"VER CAPITAL","OK") -> OK | AY71: =IF(AND(AX71="VER CAPITAL",AW71="NÃO"),"INDÍCIO DE DEPENDÊNCIA POR CAPITAL","OK") -> OK | AZ71: =AC71*100/AE71 -> 27.089798
B72: DF | C72: CEB Geração | D72: CEBG | E72: 04.232.314/0001-70 | F72: ATIVA | G72: ENERGIA | H72: SOCIEDADE DE ECONOMIA MISTA | I72: S.A. | J72: FECHADO | K72: NÃO | L72: SIM | M72: NÃO DEPENDENTE | N72: 17 | O72: =IF(AND(F72="ATIVA",VALUE(N72)=0),"VERIFICAR","OK") -> OK | P72: NÃO | Q72: SIM | R72: SIM | S72: https://www,ceb,com,br/Documentos,aspx?IdCanal=hD8pqKNE+C5Xrd39y4J+Tg== | T72: 10065219 | U72: 5831363.8 | V72: =IF(AND(VALUE(N72)=0,VALUE(U72)>0),"VERIFICAR","OK") -> OK | W72: 14208086 | X72: 768850.49 | Y72: SIM | Z72: 624558.16 | AA72: 79594 | AB72: 21329.22 | AC72: -629528.41 | AD72: =IF(AND(Y72="SIM",VALUE(AC72)<0),"VERIFICAR","OK") -> VERIFICAR | AE72: 14520897 | AG72: 0 | AH72: 0 | AI72: 0 | AJ72: =IF(AND(M72="NÃO DEPENDENTE",VALUE(AI72)>0),"INDÍCIO DE DEPENDÊNCIA POR SUBVENÇÃO","OK") -> OK | AK72: 0 | AL72: 0 | AM72: 0 | AN72: 0 | AO72: 7575212 | AP72: 7575212 | AQ72: =AP72-AO72 -> 0 | AR72: 7575212.6 | AS72: 7575212.6 | AT72: 0 | AU72: 0 | AV72: =(AS72-AR72)+(AU72) -> 0 | AW72: =IF(OR(VALUE(AQ72)>0,VALUE(AV72)>0),"SIM","NÃO") -> NÃO | AX72: =IF(AND(M72="NÃO DEPENDENTE",VALUE(AN72)>0),"VER CAPITAL","OK") -> OK | AY72: =IF(AND(AX72="VER CAPITAL",AW72="NÃO"),"INDÍCIO DE DEPENDÊNCIA POR CAPITAL","OK") -> OK | AZ72: =AC72*100/AE72 -> -4.3353273
B73: DF | C73: Companhia Brasiliense de Gás | D73: CEBGAS | E73: 04.363.670/0001-23 | F73: ATIVA | G73: GÁS E DERIVADOS | H73: SOCIEDADE DE ECONOMIA MISTA | I73: S.A. | J73: FECHADO | K73: NÃO | L73: NÃO | M73: NÃO DEPENDENTE | N73: 1 | O73: =IF(AND(F73="ATIVA",VALUE(N73)=0),"VERIFICAR","OK") -> OK | P73: SIM | Q73: SIM | R73: NÃO | T73: 386191.02 | U73: 378614.51 | V73: =IF(AND(VALUE(N73)=0,VALUE(U73)>0),"VERIFICAR","OK") -> OK | W73: 1290646.2 | X73: 0 | Y73: NÃO | Z73: 199511.49 | AA73: 0 | AB73: 0 | AC73: -1029544.4 | AD73: =IF(AND(Y73="SIM",VALUE(AC73)<0),"VERIFICAR","OK") -> OK | AE73: -1493762.4 | AG73: 0 | AH73: 0 | AI73: 0 | AJ73: =IF(AND(M73="NÃO DEPENDENTE",VALUE(AI73)>0),"INDÍCIO DE DEPENDÊNCIA POR SUBVENÇÃO","OK") -> OK | AK73: 0 | AL73: 0 | AM73: 318750 | AN73: 162500 | AO73: 1930250 | AP73: 1930250 | AQ73: =AP73-AO73 -> 0 | AR73: 1930250 | AS73: 1930250 | AT73: 0 | AU73: 0 | AV73: =(AS73-AR73)+(AU73) -> 0 | AW73: =IF(OR(VALUE(AQ73)>0,VALUE(AV73)>0),"SIM","NÃO") -> NÃO | AX73: =IF(AND(M73="NÃO DEPENDENTE",VALUE(AN73)>0),"VER CAPITAL","OK") -> VER CAPITAL | AY73: =IF(AND(AX73="VER CAPITAL",AW73="NÃO"),"INDÍCIO DE DEPENDÊNCIA POR CAPITAL","OK") -> INDÍCIO DE DEPENDÊNCIA POR CAPITAL | AZ73: =AC73*100/AE73 -> 68.922902
B74: DF | C74: CEB Participações | D74: CEBPAR | E74: 03.682.014/0001-20 | F74: ATIVA | G74: ENERGIA | H74: SOCIEDADE DE ECONOMIA MISTA | I74: S.A. | J74: FECHADO | K74: NÃO | L74: SIM | M74: NÃO DEPENDENTE | N74: 18 | O74: =IF(AND(F74="ATIVA",VALUE(N74)=0),"VERIFICAR","OK") -> OK | P74: NÃO | Q74: SIM | R74: NÃO | T74: 24475006 | U74: 3619219.3 | V74: =IF(AND(VALUE(N74)=0,VALUE(U74)>0),"VERIFICAR","OK") -> OK | W74: 13752869 | X74: 1821286.3 | Y74: SIM | Z74: 610803.22 | AA74: 0 | AB74: 0 | AC74: 17304562 | AD74: =IF(AND(Y74="SIM",VALUE(AC74)<0),"VERIFICAR","OK") -> OK | AE74: 42329035 | AG74: 0 | AH74: 0 | AI74: 0 | AJ74: =IF(AND(M74="NÃO DEPENDENTE",VALUE(AI74)>0),"INDÍCIO DE DEPENDÊNCIA POR SUBVENÇÃO","OK") -> OK | AK74: 0 | AL74: 0 | AM74: 0 | AN74: 0 | AO74: 21270415 | AP74: 21270415 | AQ74: =AP74-AO74 -> 0 | AR74: 21270415 | AS74: 21270415 | AT74: 0 | AU74: 0 | AV74: =(AS74-AR74)+(AU74) -> 0 | AW74: =IF(OR(VALUE(AQ74)>0,VALUE(AV74)>0),"SIM","NÃO") -> NÃO | AX74: =IF(AND(M74="NÃO DEPENDENTE",VALUE(AN74)>0),"VER CAPITAL","OK") -> OK | AY74: =IF(AND(AX74="VER CAPITAL",AW74="NÃO"),"INDÍCIO DE DEPENDÊNCIA POR CAPITAL","OK") -> OK | AZ74: =AC74*100/AE74 -> 40.881068
B75: DF | C75: Companhia de Planejamento do Distrito Federal | D75: CODEPLAN | E75: 00.046.060/0001-45 | F75: ATIVA | G75: GESTÃO DE ATIVOS | H75: EMPRESA PÚBLICA | I75: S.A. | J75: FECHADO | K75: NÃO | L75: SIM | M75: DEPENDENTE | N75: 5 | O75: =IF(AND(F75="ATIVA",VALUE(N75)=0),"VERIFICAR","OK") -> OK | P75: SIM | Q75: SIM | R75: NÃO | T75: 0 | U75: 1328051 | V75: =IF(AND(VALUE(N75)=0,VALUE(U75)>0),"VERIFICAR","OK") -> OK | W75: 1363008.8 | X75: 0 | Y75: NÃO | Z75: 128223.55 | AA75: 0 | AB75: 0 | AC75: -96518.78 | AD75: =IF(AND(Y75="SIM",VALUE(AC75)<0),"VERIFICAR","OK") -> OK | AE75: -355358.16 | AG75: 0 | AH75: 1480509.3 | AI75: 1363008.8 | AJ75: =IF(AND(M75="NÃO DEPENDENTE",VALUE(AI75)>0),"INDÍCIO DE DEPENDÊNCIA POR SUBVENÇÃO","OK") -> OK | AK75: 69761.27 | AL75: 95150.19 | AM75: 0 | AN75: 0 | AO75: 1226666971 | AP75: 1226666971 | AQ75: =AP75-AO75 -> 0 | AR75: 1226666971 | AS75: 1226666971 | AT75: 0 | AU75: 0 | AV75: =(AS75-AR75)+(AU75) -> 0 | AW75: =IF(OR(VALUE(AQ75)>0,VALUE(AV75)>0),"SIM","NÃO") -> NÃO | AX75: =IF(AND(M75="NÃO DEPENDENTE",VALUE(AN75)>0),"VER CAPITAL","OK") -> OK | AY75: =IF(AND(AX75="VER CAPITAL",AW75="NÃO"),"INDÍCIO DE DEPENDÊNCIA POR CAPITAL","OK") -> OK | AZ75: =AC75*100/AE75 -> 27.160986
B76: DF | C76: Companhia de Desenvolvimento Habitacional do Distrito Federal | D76: CODHAB/DF | E76: 09.335.575/0001-30 | F76: ATIVA | G76: HABITAÇÃO E URBANIZAÇÃO | H76: EMPRESA PÚBLICA | I76: OUTRAS | J76: FECHADO | K76: NÃO | L76: NÃO | M76: DEPENDENTE | N76: 457 | O76: =IF(AND(F76="ATIVA",VALUE(N76)=0),"VERIFICAR","OK") -> OK | P76: SIM | Q76: SIM | R76: SIM | T76: 12622752 | U76: 42072587 | V76: =IF(AND(VALUE(N76)=0,VALUE(U76)>0),"VERIFICAR","OK") -> OK | W76: 69122330 | X76: 0 | Y76: NÃO | Z76: 242075.5 | AA76: 0 | AB76: 0 | AC76: -56499579 | AD76: =IF(AND(Y76="SIM",VALUE(AC76)<0),"VERIFICAR","OK") -> OK | AE76: 2.3377602e+08 | AG76: 0 | AH76: 85133718 | AI76: 1.0078641e+08 | AJ76: =IF(AND(M76="NÃO DEPENDENTE",VALUE(AI76)>0),"INDÍCIO DE DEPENDÊNCIA POR SUBVENÇÃO","OK") -> OK | AK76: 0 | AL76: 0 | AM76: 0 | AN76: 0 | AO76: 0 | AP76: 0 | AQ76: =AP76-AO76 -> 0 | AR76: 37029932 | AS76: 37029932 | AT76: 37029932 | AU76: 37029932 | AV76: =(AS76-AR76)+(AU76) -> 37029932 | AW76: =IF(OR(VALUE(AQ76)>0,VALUE(AV76)>0),"SIM","NÃO") -> SIM | AX76: =IF(AND(M76="NÃO DEPENDENTE",VALUE(AN76)>0),"VER CAPITAL","OK") -> OK | AY76: =IF(AND(AX76="VER CAPITAL",AW76="NÃO"),"INDÍCIO DE DEPENDÊNCIA POR CAPITAL","OK") -> OK | AZ76: =AC76*100/AE76 -> -24.168252
B77: DF | C77: Empresa de Assistência Técnica e Extensão Rural do Distrito Federal | D77: EMATER-DF | E77: 00.509.612/0001-04 | F77: ATIVA | G77: PESQUISA E ASSISTÊNCIA TÉCNICA AGROPECUÁRIA | H77: EMPRESA PÚBLICA | I77: OUTRAS | J77: FECHADO | K77: NÃO | L77: NÃO | M77: DEPENDENTE | N77: 309 | O77: =IF(AND(F77="ATIVA",VALUE(N77)=0),"VERIFICAR","OK") -> OK | P77: SIM | Q77: SIM | R77: SIM | S77: https://emater,df,gov,br/category/carta-de-servicos/ | T77: 55522.87 | U77: 1.3937372e+08 | V77: =IF(AND(VALUE(N77)=0,VALUE(U77)>0),"VERIFICAR","OK") -> OK | W77: 1.6118769e+08 | X77: 0 | Y77: NÃO | Z77: 712722.87 | AA77: 0 | AB77: 0 | AC77: 19285188 | AD77: =IF(AND(Y77="SIM",VALUE(AC77)<0),"VERIFICAR","OK") -> OK | AE77: 677760.52 | AG77: 0 | AH77: 1.3379615e+08 | AI77: 1.4765586e+08 | AJ77: =IF(AND(M77="NÃO DEPENDENTE",VALUE(AI77)>0),"INDÍCIO DE DEPENDÊNCIA POR SUBVENÇÃO","OK") -> OK | AK77: 0 | AL77: 0 | AM77: 0 | AN77: 0 | AO77: 0 | AP77: 0 | AQ77: =AP77-AO77 -> 0 | AR77: 677760.52 | AS77: 677760.52 | AT77: 10350559 | AU77: 10350559 | AV77: =(AS77-AR77)+(AU77) -> 10350559 | AW77: =IF(OR(VALUE(AQ77)>0,VALUE(AV77)>0),"SIM","NÃO") -> SIM | AX77: =IF(AND(M77="NÃO DEPENDENTE",VALUE(AN77)>0),"VER CAPITAL","OK") -> OK | AY77: =IF(AND(AX77="VER CAPITAL",AW77="NÃO"),"INDÍCIO DE DEPENDÊNCIA POR CAPITAL","OK") -> OK | AZ77: =AC77*100/AE77 -> 2845.4281
B78: DF | C78: Empresa de Regularização de Terras Rurais | D78: ETR S.A. | E78: 50.698.494/0001-06 | F78: ATIVA | G78: DESENVOLVIMENTO REGIONAL | H78: SOCIEDADE DE ECONOMIA MISTA | I78: S.A. | J78: FECHADO | K78: NÃO | L78: SIM | M78: DEPENDENTE | N78: 44 | O78: =IF(AND(F78="ATIVA",VALUE(N78)=0),"VERIFICAR","OK") -> OK | P78: SIM | Q78: SIM | R78: SIM | T78: 0 | U78: 7222325.6 | V78: =IF(AND(VALUE(N78)=0,VALUE(U78)>0),"VERIFICAR","OK") -> OK | W78: 10203666 | X78: 859790 | Y78: SIM | Z78: 561405.34 | AA78: 15889.45 | AB78: 33884.16 | AC78: -9380301 | AD78: =IF(AND(Y78="SIM",VALUE(AC78)<0),"VERIFICAR","OK") -> VERIFICAR | AE78: 880741 | AG78: 0 | AH78: 0 | AI78: 0 | AJ78: =IF(AND(M78="NÃO DEPENDENTE",VALUE(AI78)>0),"INDÍCIO DE DEPENDÊNCIA POR SUBVENÇÃO","OK") -> OK | AK78: 0 | AL78: 0 | AM78: 5840466.3 | AN78: 10203666 | AO78: 10 | AP78: 100 | AQ78: =AP78-AO78 -> 90 | AR78: 50000 | AS78: 50000 | AT78: 45000 | AU78: 0 | AV78: =(AS78-AR78)+(AU78) -> 0 | AW78: =IF(OR(VALUE(AQ78)>0,VALUE(AV78)>0),"SIM","NÃO") -> SIM | AX78: =IF(AND(M78="NÃO DEPENDENTE",VALUE(AN78)>0),"VER CAPITAL","OK") -> OK | AY78: =IF(AND(AX78="VER CAPITAL",AW78="NÃO"),"INDÍCIO DE DEPENDÊNCIA POR CAPITAL","OK") -> OK | AZ78: =AC78*100/AE78 -> -1065.0465
B79: DF | C79: Companhia do Metropolitano do Distrito Federal | D79: METRÔ-DF | E79: 38.070.074/0001-77 | F79: ATIVA | G79: TRANSPORTE | H79: EMPRESA PÚBLICA | I79: OUTRAS | J79: FECHADO | K79: NÃO | L79: NÃO | M79: DEPENDENTE | N79: 1201 | O79: =IF(AND(F79="ATIVA",VALUE(N79)=0),"VERIFICAR","OK") -> OK | P79: SIM | Q79: SIM | R79: NÃO | S79: https://metro,df,gov,br/?page_id=37077 | T79: 1.9251064e+08 | U79: 3.1029168e+08 | V79: =IF(AND(VALUE(N79)=0,VALUE(U79)>0),"VERIFICAR","OK") -> OK | W79: 1.1168942e+09 | X79: 51402372 | Y79: NÃO | Z79: 812490.74 | AA79: 0 | AB79: 23512.62 | AC79: -5.4040019e+08 | AD79: =IF(AND(Y79="SIM",VALUE(AC79)<0),"VERIFICAR","OK") -> OK | AE79: 1.3684753e+09 | AG79: 0 | AH79: 3.6961595e+08 | AI79: 4.686674e+08 | AJ79: =IF(AND(M79="NÃO DEPENDENTE",VALUE(AI79)>0),"INDÍCIO DE DEPENDÊNCIA POR SUBVENÇÃO","OK") -> OK | AK79: 0 | AL79: 0 | AM79: 2233538.6 | AN79: 44635187 | AO79: 30689692 | AP79: 30713387 | AQ79: =AP79-AO79 -> 23695 | AR79: 2.8934242e+09 | AS79: 2.8956581e+09 | AT79: 2233538.6 | AU79: 44635187 | AV79: =(AS79-AR79)+(AU79) -> 46869151 | AW79: =IF(OR(VALUE(AQ79)>0,VALUE(AV79)>0),"SIM","NÃO") -> SIM | AX79: =IF(AND(M79="NÃO DEPENDENTE",VALUE(AN79)>0),"VER CAPITAL","OK") -> OK | AY79: =IF(AND(AX79="VER CAPITAL",AW79="NÃO"),"INDÍCIO DE DEPENDÊNCIA POR CAPITAL","OK") -> OK | AZ79: =AC79*100/AE79 -> -39.489219
B80: DF | C80: Companhia Urbanizadora da Nova Capital do Brasil | D80: NOVACAP | E80: 00.037.457/0001-70 | F80: ATIVA | G80: HABITAÇÃO E URBANIZAÇÃO | H80: EMPRESA PÚBLICA | I80: S.A. | J80: FECHADO | K80: NÃO | L80: NÃO | M80: DEPENDENTE | N80: 992 | O80: =IF(AND(F80="ATIVA",VALUE(N80)=0),"VERIFICAR","OK") -> OK | P80: SIM | Q80: SIM | R80: NÃO | T80: 0 | U80: 0 | V80: =IF(AND(VALUE(N80)=0,VALUE(U80)>0),"VERIFICAR","OK") -> OK | W80: 536246883 | X80: 2827683.6 | Y80: NÃO | Z80: 539262.2 | AA80: 0 | AB80: 0 | AC80: -35717756 | AD80: =IF(AND(Y80="SIM",VALUE(AC80)<0),"VERIFICAR","OK") -> OK | AE80: 8.2204447e+08 | AG80: 0 | AH80: 1.3940762e+09 | AI80: 2.0574368e+09 | AJ80: =IF(AND(M80="NÃO DEPENDENTE",VALUE(AI80)>0),"INDÍCIO DE DEPENDÊNCIA POR SUBVENÇÃO","OK") -> OK | AK80: 0 | AL80: 0 | AM80: 7272937 | AN80: 7272937 | AO80: 280600 | AP80: 280600 | AQ80: =AP80-AO80 -> 0 | AR80: 26713076 | AS80: 26716076 | AT80: 0 | AU80: 0 | AV80: =(AS80-AR80)+(AU80) -> 3000 | AW80: =IF(OR(VALUE(AQ80)>0,VALUE(AV80)>0),"SIM","NÃO") -> SIM | AX80: =IF(AND(M80="NÃO DEPENDENTE",VALUE(AN80)>0),"VER CAPITAL","OK") -> OK | AY80: =IF(AND(AX80="VER CAPITAL",AW80="NÃO"),"INDÍCIO DE DEPENDÊNCIA POR CAPITAL","OK") -> OK | AZ80: =AC80*100/AE80 -> -4.3449907
B81: DF | C81: PROFLORA | D81: PROFLORA | E81: 00.338.079/0001-65 | F81: EM LIQUIDAÇÃO | G81: DESENVOLVIMENTO REGIONAL | H81: SOCIEDADE DE ECONOMIA MISTA | I81: S.A. | J81: FECHADO | K81: NÃO | L81: NÃO | M81: NÃO DEPENDENTE | N81: 7 | O81: =IF(AND(F81="ATIVA",VALUE(N81)=0),"VERIFICAR","OK") -> OK | P81: SIM | Q81: SIM | R81: NÃO | T81: 1385020.3 | U81: 1209779.5 | V81: =IF(AND(VALUE(N81)=0,VALUE(U81)>0),"VERIFICAR","OK") -> OK | W81: 1479461.8 | X81: 0 | Y81: NÃO | Z81: 187442.3 | AA81: 0 | AB81: 0 | AC81: -7200331.1 | AD81: =IF(AND(Y81="SIM",VALUE(AC81)<0),"VERIFICAR","OK") -> OK | AE81: 8244998.9 | AG81: 0 | AH81: 0 | AI81: 0 | AJ81: =IF(AND(M81="NÃO DEPENDENTE",VALUE(AI81)>0),"INDÍCIO DE DEPENDÊNCIA POR SUBVENÇÃO","OK") -> OK | AK81: 0 | AL81: 0 | AM81: 0 | AN81: 0 | AO81: 4024.42 | AP81: 4024.42 | AQ81: =AP81-AO81 -> 0 | AR81: 4024.42 | AS81: 4024.42 | AT81: 0 | AU81: 0 | AV81: =(AS81-AR81)+(AU81) -> 0 | AW81: =IF(OR(VALUE(AQ81)>0,VALUE(AV81)>0),"SIM","NÃO") -> NÃO | AX81: =IF(AND(M81="NÃO DEPENDENTE",VALUE(AN81)>0),"VER CAPITAL","OK") -> OK | AY81: =IF(AND(AX81="VER CAPITAL",AW81="NÃO"),"INDÍCIO DE DEPENDÊNCIA POR CAPITAL","OK") -> OK | AZ81: =AC81*100/AE81 -> -87.32968
B82: DF | C82: Sociedade de Abastecimento de Brasília | D82: SAB | E82: 00.037.226/0001-67 | F82: EM LIQUIDAÇÃO | G82: SANEAMENTO | H82: EMPRESA PÚBLICA | I82: S.A. | J82: FECHADO | K82: NÃO | L82: NÃO | M82: DEPENDENTE | N82: 113 | O82: =IF(AND(F82="ATIVA",VALUE(N82)=0),"VERIFICAR","OK") -> OK | P82: SIM | Q82: SIM | R82: NÃO | T82: 21550612 | U82: 21157094 | V82: =IF(AND(VALUE(N82)=0,VALUE(U82)>0),"VERIFICAR","OK") -> OK | W82: 21297960 | X82: 0 | Y82: NÃO | Z82: 287369.68 | AA82: 0 | AB82: 0 | AC82: 252652.15 | AD82: =IF(AND(Y82="SIM",VALUE(AC82)<0),"VERIFICAR","OK") -> OK | AE82: -1727395.8 | AG82: 0 | AH82: 20598560 | AI82: 21416537 | AJ82: =IF(AND(M82="NÃO DEPENDENTE",VALUE(AI82)>0),"INDÍCIO DE DEPENDÊNCIA POR SUBVENÇÃO","OK") -> OK | AK82: 0 | AL82: 0 | AM82: 22.3 | AN82: 0 | AO82: 1636885749 | AP82: 1636885749 | AQ82: =AP82-AO82 -> 0 | AR82: 16368857 | AS82: 16368857 | AT82: 0 | AU82: 0 | AV82: =(AS82-AR82)+(AU82) -> 0 | AW82: =IF(OR(VALUE(AQ82)>0,VALUE(AV82)>0),"SIM","NÃO") -> NÃO | AX82: =IF(AND(M82="NÃO DEPENDENTE",VALUE(AN82)>0),"VER CAPITAL","OK") -> OK | AY82: =IF(AND(AX82="VER CAPITAL",AW82="NÃO"),"INDÍCIO DE DEPENDÊNCIA POR CAPITAL","OK") -> OK | AZ82: =AC82*100/AE82 -> -14.626188
B83: DF | C83: Sociedade de Transportes Coletivos de Brasília | D83: TCB | E83: 00.037.127/0001-85 | F83: ATIVA | G83: TRANSPORTE | H83: EMPRESA PÚBLICA | I83: LTDA | J83: FECHADO | K83: NÃO | L83: NÃO | M83: DEPENDENTE | N83: 552 | O83: =IF(AND(F83="ATIVA",VALUE(N83)=0),"VERIFICAR","OK") -> OK | P83: SIM | Q83: SIM | R83: NÃO | T83: 5775667.1 | U83: 10168034 | V83: =IF(AND(VALUE(N83)=0,VALUE(U83)>0),"VERIFICAR","OK") -> OK | W83: 28236642 | X83: 0 | Y83: NÃO | Z83: 331624.15 | AA83: 0 | AB83: 0 | AC83: -36494716 | AD83: =IF(AND(Y83="SIM",VALUE(AC83)<0),"VERIFICAR","OK") -> OK | AE83: 60677501 | AG83: 0 | AH83: 2.1512391e+08 | AI83: 2.669227e+08 | AJ83: =IF(AND(M83="NÃO DEPENDENTE",VALUE(AI83)>0),"INDÍCIO DE DEPENDÊNCIA POR SUBVENÇÃO","OK") -> OK | AK83: 75022399 | AL83: 1.3619987e+08 | AM83: 0 | AN83: 0 | AO83: 37722.75 | AP83: 37722.75 | AQ83: =AP83-AO83 -> 0 | AR83: 43886200 | AS83: 43886200 | AT83: 0 | AU83: 0 | AV83: =(AS83-AR83)+(AU83) -> 0 | AW83: =IF(OR(VALUE(AQ83)>0,VALUE(AV83)>0),"SIM","NÃO") -> NÃO | AX83: =IF(AND(M83="NÃO DEPENDENTE",VALUE(AN83)>0),"VER CAPITAL","OK") -> OK | AY83: =IF(AND(AX83="VER CAPITAL",AW83="NÃO"),"INDÍCIO DE DEPENDÊNCIA POR CAPITAL","OK") -> OK | AZ83: =AC83*100/AE83 -> -60.145383
B84: DF | C84: Companhia Imobiliária de Brasília | D84: Terracap | E84: 00.359.877/0001-73 | F84: ATIVA | G84: HABITAÇÃO E URBANIZAÇÃO | H84: EMPRESA PÚBLICA | I84: S.A. | J84: FECHADO | K84: NÃO | L84: NÃO | M84: NÃO DEPENDENTE | N84: 1100 | O84: =IF(AND(F84="ATIVA",VALUE(N84)=0),"VERIFICAR","OK") -> OK | P84: SIM | Q84: SIM | R84: SIM | S84: https://www,terracap,df,gov,br/index,php/carta-deservico/imprimaaqui-a-carta-deservico | T84: 6.5311442e+08 | U84: 3.3131808e+08 | V84: =IF(AND(VALUE(N84)=0,VALUE(U84)>0),"VERIFICAR","OK") -> OK | W84: 8.1831793e+08 | X84: 241820000 | Y84: SIM | Z84: 928239.58 | AA84: 32984.3 | AB84: 77201.9 | AC84: -1.6520351e+08 | AD84: =IF(AND(Y84="SIM",VALUE(AC84)<0),"VERIFICAR","OK") -> VERIFICAR | AE84: 5.2870569e+09 | AG84: 0 | AH84: 0 | AI84: 0 | AJ84: =IF(AND(M84="NÃO DEPENDENTE",VALUE(AI84)>0),"INDÍCIO DE DEPENDÊNCIA POR SUBVENÇÃO","OK") -> OK | AK84: 0 | AL84: 0 | AM84: 0 | AN84: 0 | AO84: 255000 | AP84: 255000 | AQ84: =AP84-AO84 -> 0 | AR84: 1.8510785e+09 | AS84: 1.8510785e+09 | AT84: 0 | AU84: 0 | AV84: =(AS84-AR84)+(AU84) -> 0 | AW84: =IF(OR(VALUE(AQ84)>0,VALUE(AV84)>0),"SIM","NÃO") -> NÃO | AX84: =IF(AND(M84="NÃO DEPENDENTE",VALUE(AN84)>0),"VER CAPITAL","OK") -> OK | AY84: =IF(AND(AX84="VER CAPITAL",AW84="NÃO"),"INDÍCIO DE DEPENDÊNCIA POR CAPITAL","OK") -> OK | AZ84: =AC84*100/AE84 -> -3.1246781
B85: ES | C85: Bandes - Banco de Desenvolvimento do Espírito Santo S/A | D85: BANDES | E85: 28.145.829/0001-00 | F85: ATIVA | G85: FINANCEIRO | H85: SOCIEDADE DE ECONOMIA MISTA | I85: S.A. | J85: FECHADO | K85: NÃO | L85: NÃO | M85: NÃO DEPENDENTE | N85: 190 | O85: =IF(AND(F85="ATIVA",VALUE(N85)=0),"VERIFICAR","OK") -> OK | P85: SIM | Q85: SIM | R85: SIM | S85: https://www,bandes,com,br/Site/Dinamico/Show/933/Governanca-Corporativa# | T85: 2.2843852e+08 | U85: 54800725 | V85: =IF(AND(VALUE(N85)=0,VALUE(U85)>0),"VERIFICAR","OK") -> OK | W85: 1.8855088e+08 | X85: 4083775 | Y85: SIM | Z85: 35566517 | AA85: 4879123 | AB85: 9110878.4 | AC85: 99380416 | AD85: =IF(AND(Y85="SIM",VALUE(AC85)<0),"VERIFICAR","OK") -> OK | AE85: 5.2040998e+08 | AF85: 5.2040998e+08 | AG85: 0 | AH85: 0 | AI85: 0 | AJ85: =IF(AND(M85="NÃO DEPENDENTE",VALUE(AI85)>0),"INDÍCIO DE DEPENDÊNCIA POR SUBVENÇÃO","OK") -> OK | AK85: 0 | AL85: 0 | AM85: 0 | AN85: 0 | AO85: 25246979553 | AP85: 26742192753 | AQ85: =AP85-AO85 -> 1495213200 | AR85: 439371000 | AS85: 4.6338e+08 | AT85: 0 | AU85: 0 | AV85: =(AS85-AR85)+(AU85) -> 24008996 | AW85: =IF(OR(VALUE(AQ85)>0,VALUE(AV85)>0),"SIM","NÃO") -> SIM | AX85: =IF(AND(M85="NÃO DEPENDENTE",VALUE(AN85)>0),"VER CAPITAL","OK") -> OK | AY85: =IF(AND(AX85="VER CAPITAL",AW85="NÃO"),"INDÍCIO DE DEPENDÊNCIA POR CAPITAL","OK") -> OK | AZ85: =AC85*100/AE85 -> 19.096562
B86: ES | C86: Banestes - Banco do Estado do Espirito Santo | D86: BANESTES | E86: 28.127.603/0001-78 | F86: ATIVA | G86: FINANCEIRO | H86: SOCIEDADE DE ECONOMIA MISTA | I86: S.A. | J86: ABERTO | K86: SIM | L86: NÃO | M86: NÃO DEPENDENTE | N86: 2164 | O86: =IF(AND(F86="ATIVA",VALUE(N86)=0),"VERIFICAR","OK") -> OK | P86: SIM | Q86: SIM | R86: SIM | S86: https://ri,banestes,com,br | T86: 1.1853401e+09 | U86: 4.9193627e+08 | V86: =IF(AND(VALUE(N86)=0,VALUE(U86)>0),"VERIFICAR","OK") -> OK | W86: 5.0652512e+09 | X86: 2.4996539e+08 | Y86: SIM | Z86: 763612.13 | AA86: 158498.22 | AB86: 0 | AC86: 3.9248711e+08 | AD86: =IF(AND(Y86="SIM",VALUE(AC86)<0),"VERIFICAR","OK") -> OK | AE86: 2.3572137e+09 | AF86: 2706860802 | AG86: 1.9996934e+08 | AH86: 0 | AI86: 0 | AJ86: =IF(AND(M86="NÃO DEPENDENTE",VALUE(AI86)>0),"INDÍCIO DE DEPENDÊNCIA POR SUBVENÇÃO","OK") -> OK | AK86: 0 | AL86: 0 | AM86: 0 | AN86: 0 | AO86: 291793529 | AP86: 291793529 | AQ86: =AP86-AO86 -> 0 | AR86: 1477920000 | AS86: 1600000000 | AT86: 0 | AU86: 0 | AV86: =(AS86-AR86)+(AU86) -> 122080000 | AW86: =IF(OR(VALUE(AQ86)>0,VALUE(AV86)>0),"SIM","NÃO") -> SIM | AX86: =IF(AND(M86="NÃO DEPENDENTE",VALUE(AN86)>0),"VER CAPITAL","OK") -> OK | AY86: =IF(AND(AX86="VER CAPITAL",AW86="NÃO"),"INDÍCIO DE DEPENDÊNCIA POR CAPITAL","OK") -> OK | AZ86: =AC86*100/AE86 -> 16.650468
B87: ES | C87: Ceasa - Centrais de Abastecimento do Espirito Santo S/A | D87: CEASA | E87: 27.064.062/0001-13 | F87: ATIVA | G87: ABASTECIMENTO DE ALIMENTOS E OUTROS INSUMOS | H87: SOCIEDADE DE ECONOMIA MISTA | I87: S.A. | J87: FECHADO | K87: NÃO | L87: NÃO | M87: DEPENDENTE | N87: 158 | O87: =IF(AND(F87="ATIVA",VALUE(N87)=0),"VERIFICAR","OK") -> OK | P87: SIM | Q87: SIM | R87: NÃO | S87: https://ioes,dio,es,gov,br/portal/visualizacoes/pdf/10176#/p:47/e:10176?find=ceasa | T87: 19359297 | U87: 14516509 | V87: =IF(AND(VALUE(N87)=0,VALUE(U87)>0),"VERIFICAR","OK") -> OK | W87: 23723451 | X87: 0 | Y87: NÃO | Z87: 4737029.6 | AA87: 0 | AB87: 0 | AC87: 794552.61 | AD87: =IF(AND(Y87="SIM",VALUE(AC87)<0),"VERIFICAR","OK") -> OK | AE87: 10901902 | AF87: 0 | AG87: 0 | AH87: 0 | AI87: 0 | AJ87: =IF(AND(M87="NÃO DEPENDENTE",VALUE(AI87)>0),"INDÍCIO DE DEPENDÊNCIA POR SUBVENÇÃO","OK") -> OK | AK87: 0 | AL87: 0 | AM87: 0 | AN87: 0 | AO87: 3159556 | AP87: 3159556 | AQ87: =AP87-AO87 -> 0 | AR87: 3159556.7 | AS87: 3159556.7 | AT87: 0 | AU87: 0 | AV87: =(AS87-AR87)+(AU87) -> 0 | AW87: =IF(OR(VALUE(AQ87)>0,VALUE(AV87)>0),"SIM","NÃO") -> NÃO | AX87: =IF(AND(M87="NÃO DEPENDENTE",VALUE(AN87)>0),"VER CAPITAL","OK") -> OK | AY87: =IF(AND(AX87="VER CAPITAL",AW87="NÃO"),"INDÍCIO DE DEPENDÊNCIA POR CAPITAL","OK") -> OK | AZ87: =AC87*100/AE87 -> 7.2882017
B88: ES | C88: Cesan - Companhia Espirito Santense de Saneamento | D88: CESAN | E88: 28.151.363/0001-47 | F88: ATIVA | G88: SANEAMENTO | H88: SOCIEDADE DE ECONOMIA MISTA | I88: S.A. | J88: FECHADO | K88: NÃO | L88: NÃO | M88: NÃO DEPENDENTE | N88: 1274 | O88: =IF(AND(F88="ATIVA",VALUE(N88)=0),"VERIFICAR","OK") -> OK | P88: SIM | Q88: SIM | R88: SIM | S88: https://www,cesan,com,br/wp-content/uploads/2024/07/Carta-Anual-de-Politicas-Publicas-3,pdf | T88: 1.2759444e+09 | U88: 3.1513607e+08 | V88: =IF(AND(VALUE(N88)=0,VALUE(U88)>0),"VERIFICAR","OK") -> OK | W88: 1.2006939e+09 | X88: 0 | Y88: SIM | Z88: 722809.61 | AA88: 54781.47 | AB88: 91704.99 | AC88: 2.0243866e+08 | AD88: =IF(AND(Y88="SIM",VALUE(AC88)<0),"VERIFICAR","OK") -> OK | AE88: 4218159000 | AF88: 0 | AG88: 0 | AH88: 0 | AI88: 0 | AJ88: =IF(AND(M88="NÃO DEPENDENTE",VALUE(AI88)>0),"INDÍCIO DE DEPENDÊNCIA POR SUBVENÇÃO","OK") -> OK | AK88: 0 | AL88: 0 | AM88: 249280703 | AN88: 1.7928997e+08 | AO88: 3015250810 | AP88: 3413141853 | AQ88: =AP88-AO88 -> 397891043 | AR88: 390685165 | AS88: 397891043 | AT88: 0 | AU88: 0 | AV88: =(AS88-AR88)+(AU88) -> 7205878 | AW88: =IF(OR(VALUE(AQ88)>0,VALUE(AV88)>0),"SIM","NÃO") -> SIM | AX88: =IF(AND(M88="NÃO DEPENDENTE",VALUE(AN88)>0),"VER CAPITAL","OK") -> VER CAPITAL | AY88: =IF(AND(AX88="VER CAPITAL",AW88="NÃO"),"INDÍCIO DE DEPENDÊNCIA POR CAPITAL","OK") -> OK | AZ88: =AC88*100/AE88 -> 4.7992184
B89: ES | C89: Ceturb - Companhia Estadual de Transportes Coletivos de Passageiros do Espirito Santo | D89: CETURB | E89: 28.503.894/0001-51 | F89: ATIVA | G89: TRANSPORTE | H89: EMPRESA PÚBLICA | I89: S.A. | J89: FECHADO | K89: NÃO | L89: NÃO | M89: NÃO DEPENDENTE | N89: 244 | O89: =IF(AND(F89="ATIVA",VALUE(N89)=0),"VERIFICAR","OK") -> OK | P89: SIM | Q89: SIM | R89: NÃO | S89: https://centraldebalancos,estaleiro,serpro,gov,br/centraldebalancos/#/ver-demonstracao/212163 | T89: 85695694 | U89: 36943692 | V89: =IF(AND(VALUE(N89)=0,VALUE(U89)>0),"VERIFICAR","OK") -> OK | W89: 87620575 | X89: 799246.52 | Y89: NÃO | Z89: 453088.04 | AA89: 0 | AB89: 0 | AC89: 2119642.4 | AD89: =IF(AND(Y89="SIM",VALUE(AC89)<0),"VERIFICAR","OK") -> OK | AE89: 21912715 | AF89: 0 | AG89: 0 | AH89: 0 | AI89: 0 | AJ89: =IF(AND(M89="NÃO DEPENDENTE",VALUE(AI89)>0),"INDÍCIO DE DEPENDÊNCIA POR SUBVENÇÃO","OK") -> OK | AK89: 0 | AL89: 0 | AM89: 0 | AN89: 1500000 | AO89: 93473015 | AP89: 120370891 | AQ89: =AP89-AO89 -> 26897876 | AR89: 93473015 | AS89: 1.2037089e+08 | AT89: 1.0652698e+08 | AU89: 79629108 | AV89: =(AS89-AR89)+(AU89) -> 1.0652698e+08 | AW89: =IF(OR(VALUE(AQ89)>0,VALUE(AV89)>0),"SIM","NÃO") -> SIM | AX89: =IF(AND(M89="NÃO DEPENDENTE",VALUE(AN89)>0),"VER CAPITAL","OK") -> VER CAPITAL | AY89: =IF(AND(AX89="VER CAPITAL",AW89="NÃO"),"INDÍCIO DE DEPENDÊNCIA POR CAPITAL","OK") -> OK | AZ89: =AC89*100/AE89 -> 9.6731163
B90: ES | C90: COHAB - Companhia de Habitação e Urbanização do Estado do Espirito Santo - Em Liquidação | D90: COHAB | E90: 28.139.012/0001-10 | F90: EM LIQUIDAÇÃO | G90: HABITAÇÃO E URBANIZAÇÃO | H90: SOCIEDADE DE ECONOMIA MISTA | I90: S.A. | J90: FECHADO | K90: NÃO | L90: NÃO | M90: NÃO DEPENDENTE | N90: 20 | O90: =IF(AND(F90="ATIVA",VALUE(N90)=0),"VERIFICAR","OK") -> OK | P90: SIM | Q90: SIM | R90: SIM | S90: https://seger,es,gov,br/autarquias | T90: 3827365.2 | U90: 1430113.2 | V90: =IF(AND(VALUE(N90)=0,VALUE(U90)>0),"VERIFICAR","OK") -> OK | W90: 3974715.2 | X90: 0 | Y90: NÃO | Z90: 95433.59 | AA90: 0 | AB90: 632934.79 | AC90: -147350.05 | AD90: =IF(AND(Y90="SIM",VALUE(AC90)<0),"VERIFICAR","OK") -> OK | AE90: 14717292 | AF90: 14717292 | AG90: 0 | AH90: 0 | AI90: 0 | AJ90: =IF(AND(M90="NÃO DEPENDENTE",VALUE(AI90)>0),"INDÍCIO DE DEPENDÊNCIA POR SUBVENÇÃO","OK") -> OK | AK90: 0 | AL90: 0 | AM90: 0 | AN90: 0 | AO90: 68602271495 | AP90: 68602271495 | AQ90: =AP90-AO90 -> 0 | AR90: 4525000 | AS90: 4525000 | AT90: 0 | AU90: 0 | AV90: =(AS90-AR90)+(AU90) -> 0 | AW90: =IF(OR(VALUE(AQ90)>0,VALUE(AV90)>0),"SIM","NÃO") -> NÃO | AX90: =IF(AND(M90="NÃO DEPENDENTE",VALUE(AN90)>0),"VER CAPITAL","OK") -> OK | AY90: =IF(AND(AX90="VER CAPITAL",AW90="NÃO"),"INDÍCIO DE DEPENDÊNCIA POR CAPITAL","OK") -> OK | AZ90: =AC90*100/AE90 -> -1.0012036
B91: ES | C91: Fundação Carmelia Maria de Souza Cultura e Comunicação Pública | D91: FUNDAÇÃO CARMELIA | E91: 54.715.094/0001-04 | F91: ATIVA | G91: COMUNICAÇÃO | H91: EMPRESA PÚBLICA | I91: LTDA | J91: FECHADO | K91: NÃO | L91: NÃO | M91: NÃO DEPENDENTE | N91: 30 | O91: =IF(AND(F91="ATIVA",VALUE(N91)=0),"VERIFICAR","OK") -> OK | P91: SIM | Q91: SIM | R91: NÃO | S91: não se aplica | T91: 240576 | U91: 2240252.6 | V91: =IF(AND(VALUE(N91)=0,VALUE(U91)>0),"VERIFICAR","OK") -> OK | W91: 2343475.6 | X91: 0 | Y91: NÃO | Z91: 1787799.9 | AA91: 0 | AB91: 0 | AC91: 1815812.4 | AD91: =IF(AND(Y91="SIM",VALUE(AC91)<0),"VERIFICAR","OK") -> OK | AE91: 8445906.6 | AF91: 0 | AG91: 0 | AH91: 0 | AI91: 0 | AJ91: =IF(AND(M91="NÃO DEPENDENTE",VALUE(AI91)>0),"INDÍCIO DE DEPENDÊNCIA POR SUBVENÇÃO","OK") -> OK | AK91: 0 | AL91: 0 | AM91: 0 | AN91: 0 | AO91: 0 | AP91: 0 | AQ91: =AP91-AO91 -> 0 | AR91: 0 | AS91: 10261719 | AT91: 0 | AU91: 42000000 | AV91: =(AS91-AR91)+(AU91) -> 52261719 | AW91: =IF(OR(VALUE(AQ91)>0,VALUE(AV91)>0),"SIM","NÃO") -> SIM | AX91: =IF(AND(M91="NÃO DEPENDENTE",VALUE(AN91)>0),"VER CAPITAL","OK") -> OK | AY91: =IF(AND(AX91="VER CAPITAL",AW91="NÃO"),"INDÍCIO DE DEPENDÊNCIA POR CAPITAL","OK") -> OK | AZ91: =AC91*100/AE91 -> 21.499319
B92: GO | C92: Agência Goiana de Habitação S/A | D92: AGEHAB | E92: 01.274.240/0001-47 | F92: ATIVA | G92: HABITAÇÃO E URBANIZAÇÃO | H92: SOCIEDADE DE ECONOMIA MISTA | I92: S.A. | J92: FECHADO | K92: NÃO | L92: NÃO | M92: DEPENDENTE | N92: 400 | O92: =IF(AND(F92="ATIVA",VALUE(N92)=0),"VERIFICAR","OK") -> OK | P92: SIM | Q92: SIM | R92: SIM | S92: https://goias,gov,br/agehab/carta-anual-de-governanca-corporativa/ | T92: 3768285.3 | U92: 67137142 | V92: =IF(AND(VALUE(N92)=0,VALUE(U92)>0),"VERIFICAR","OK") -> OK | W92: 6.0134887e+08 | X92: 2.9177899e+08 | Y92: NÃO | Z92: 1108154.3 | AA92: 0 | AB92: 0 | AC92: 1.4695064e+08 | AD92: =IF(AND(Y92="SIM",VALUE(AC92)<0),"VERIFICAR","OK") -> OK | AE92: 5.2220426e+08 | AF92: 0 | AG92: 0 | AH92: 3.5185835e+08 | AI92: 3.128984e+08 | AJ92: =IF(AND(M92="NÃO DEPENDENTE",VALUE(AI92)>0),"INDÍCIO DE DEPENDÊNCIA POR SUBVENÇÃO","OK") -> OK | AK92: 0 | AL92: 0 | AM92: 0 | AN92: 0 | AO92: 1.9604092e+08 | AP92: 1.9604092e+08 | AQ92: =AP92-AO92 -> 0 | AR92: 1.8716377e+08 | AS92: 1.8716377e+08 | AT92: 8877149.1 | AU92: 8877149.1 | AV92: =(AS92-AR92)+(AU92) -> 8877149.1 | AW92: =IF(OR(VALUE(AQ92)>0,VALUE(AV92)>0),"SIM","NÃO") -> SIM | AX92: =IF(AND(M92="NÃO DEPENDENTE",VALUE(AN92)>0),"VER CAPITAL","OK") -> OK | AY92: =IF(AND(AX92="VER CAPITAL",AW92="NÃO"),"INDÍCIO DE DEPENDÊNCIA POR CAPITAL","OK") -> OK | AZ92: =AC92*100/AE92 -> 28.140451
B93: GO | C93: Caixa Econômica do Estado de Goiás | D93: CAIXEGO | E93: 01.600.204/0001-26 | F93: EM LIQUIDAÇÃO | G93: FINANCEIRO | H93: EMPRESA PÚBLICA | I93: OUTRAS | J93: FECHADO | K93: NÃO | L93: NÃO | M93: NÃO DEPENDENTE | N93: 0 | O93: =IF(AND(F93="ATIVA",VALUE(N93)=0),"VERIFICAR","OK") -> OK | P93: NÃO | Q93: NÃO | R93: NÃO | T93: 0 | U93: 0 | V93: =IF(AND(VALUE(N93)=0,VALUE(U93)>0),"VERIFICAR","OK") -> OK | W93: 0 | X93: 0 | Y93: NÃO | Z93: 0 | AA93: 0 | AB93: 0 | AC93: 0 | AD93: =IF(AND(Y93="SIM",VALUE(AC93)<0),"VERIFICAR","OK") -> OK | AE93: -4.2519722e+08 | AF93: 0 | AG93: 0 | AH93: 0 | AI93: 0 | AJ93: =IF(AND(M93="NÃO DEPENDENTE",VALUE(AI93)>0),"INDÍCIO DE DEPENDÊNCIA POR SUBVENÇÃO","OK") -> OK | AK93: 0 | AL93: 0 | AM93: 0 | AN93: 0 | AO93: 1 | AP93: 1 | AQ93: =AP93-AO93 -> 0 | AR93: 1.24 | AS93: 1.24 | AT93: 0 | AU93: 0 | AV93: =(AS93-AR93)+(AU93) -> 0 | AW93: =IF(OR(VALUE(AQ93)>0,VALUE(AV93)>0),"SIM","NÃO") -> NÃO | AX93: =IF(AND(M93="NÃO DEPENDENTE",VALUE(AN93)>0),"VER CAPITAL","OK") -> OK | AY93: =IF(AND(AX93="VER CAPITAL",AW93="NÃO"),"INDÍCIO DE DEPENDÊNCIA POR CAPITAL","OK") -> OK | AZ93: =AC93*100/AE93 -> 0
B94: GO | C94: Centrais de Abastecimento de Goiás S/A | D94: CEASA-GO | E94: 01.098.797/0001-74 | F94: ATIVA | G94: ABASTECIMENTO DE ALIMENTOS E OUTROS INSUMOS | H94: SOCIEDADE DE ECONOMIA MISTA | I94: S.A. | J94: FECHADO | K94: NÃO | L94: NÃO | M94: NÃO DEPENDENTE | N94: 93 | O94: =IF(AND(F94="ATIVA",VALUE(N94)=0),"VERIFICAR","OK") -> OK | P94: SIM | Q94: SIM | R94: SIM | S94: https://goias,gov,br/ceasa/carta-anual-de-governanca-corporativa/ | T94: 36113028 | U94: 14671227 | V94: =IF(AND(VALUE(N94)=0,VALUE(U94)>0),"VERIFICAR","OK") -> OK | W94: 34890671 | X94: 1830220.8 | Y94: NÃO | Z94: 426408.06 | AA94: 0 | AB94: 168386.46 | AC94: 823698.66 | AD94: =IF(AND(Y94="SIM",VALUE(AC94)<0),"VERIFICAR","OK") -> OK | AE94: 2.5220218e+08 | AF94: 0 | AG94: 0 | AH94: 0 | AI94: 0 | AJ94: =IF(AND(M94="NÃO DEPENDENTE",VALUE(AI94)>0),"INDÍCIO DE DEPENDÊNCIA POR SUBVENÇÃO","OK") -> OK | AK94: 0 | AL94: 0 | AM94: 0 | AN94: 0 | AO94: 23435690 | AP94: 23376622 | AQ94: =AP94-AO94 -> -59068.3 | AR94: 23376622 | AS94: 23435690 | AT94: 0 | AU94: 0 | AV94: =(AS94-AR94)+(AU94) -> 59067.94 | AW94: =IF(OR(VALUE(AQ94)>0,VALUE(AV94)>0),"SIM","NÃO") -> SIM | AX94: =IF(AND(M94="NÃO DEPENDENTE",VALUE(AN94)>0),"VER CAPITAL","OK") -> OK | AY94: =IF(AND(AX94="VER CAPITAL",AW94="NÃO"),"INDÍCIO DE DEPENDÊNCIA POR CAPITAL","OK") -> OK | AZ94: =AC94*100/AE94 -> 0.32660251
B95: GO | C95: Companhia Celg de Participações | D95: CELGPAR | E95: 08.560.444/0001-93 | F95: ATIVA | G95: ENERGIA | H95: SOCIEDADE DE ECONOMIA MISTA | I95: S.A. | J95: ABERTO | K95: SIM | L95: NÃO | M95: NÃO DEPENDENTE | N95: 113 | O95: =IF(AND(F95="ATIVA",VALUE(N95)=0),"VERIFICAR","OK") -> OK | P95: SIM | Q95: SIM | R95: SIM | S95: https://ri,celgpar,com/BuscaPagina,aspx?ID={41799EC4-9CB4-4F81-BC75-64087B8BE678} | T95: 19287585 | U95: 25061326 | V95: =IF(AND(VALUE(N95)=0,VALUE(U95)>0),"VERIFICAR","OK") -> OK | W95: 58565486 | X95: 21027359 | Y95: NÃO | Z95: 888466.76 | AA95: 0 | AB95: 0 | AC95: 37486205 | AD95: =IF(AND(Y95="SIM",VALUE(AC95)<0),"VERIFICAR","OK") -> OK | AE95: 7.8355891e+08 | AF95: 0 | AG95: 0 | AH95: 0 | AI95: 0 | AJ95: =IF(AND(M95="NÃO DEPENDENTE",VALUE(AI95)>0),"INDÍCIO DE DEPENDÊNCIA POR SUBVENÇÃO","OK") -> OK | AK95: 0 | AL95: 0 | AM95: 0 | AN95: 0 | AO95: 79676502 | AP95: 79676502 | AQ95: =AP95-AO95 -> 0 | AR95: 6.023507e+08 | AS95: 6.023507e+08 | AT95: 0 | AU95: 0 | AV95: =(AS95-AR95)+(AU95) -> 0 | AW95: =IF(OR(VALUE(AQ95)>0,VALUE(AV95)>0),"SIM","NÃO") -> NÃO | AX95: =IF(AND(M95="NÃO DEPENDENTE",VALUE(AN95)>0),"VER CAPITAL","OK") -> OK | AY95: =IF(AND(AX95="VER CAPITAL",AW95="NÃO"),"INDÍCIO DE DEPENDÊNCIA POR CAPITAL","OK") -> OK | AZ95: =AC95*100/AE95 -> 4.7840953
B96: GO | C96: Companhia Metropolitana de Transportes Coletivos | D96: CMTC | E96: 05.787.273/0001-41 | F96: ATIVA | G96: TRANSPORTE | H96: EMPRESA PÚBLICA | I96: OUTRAS | J96: FECHADO | K96: NÃO | L96: NÃO | M96: NÃO DEPENDENTE | N96: 94 | O96: =IF(AND(F96="ATIVA",VALUE(N96)=0),"VERIFICAR","OK") -> OK | P96: SIM | Q96: SIM | R96: NÃO | S96: https://cmtcrmg,com,br/pasta/prestacao-de-contas/ | T96: 10685127 | U96: 10859558 | V96: =IF(AND(VALUE(N96)=0,VALUE(U96)>0),"VERIFICAR","OK") -> OK | W96: 17278101 | X96: 0 | Y96: NÃO | Z96: 267005.07 | AA96: 0 | AB96: 14836.94 | AC96: -6592973.2 | AD96: =IF(AND(Y96="SIM",VALUE(AC96)<0),"VERIFICAR","OK") -> OK | AE96: 1465632.2 | AF96: 0 | AG96: 0 | AH96: 0 | AI96: 0 | AJ96: =IF(AND(M96="NÃO DEPENDENTE",VALUE(AI96)>0),"INDÍCIO DE DEPENDÊNCIA POR SUBVENÇÃO","OK") -> OK | AK96: 0 | AL96: 0 | AM96: 0 | AN96: 3380000 | AO96: 0 | AP96: 10000000 | AQ96: =AP96-AO96 -> 10000000 | AR96: 0 | AS96: 4130000 | AT96: 0 | AU96: 5870000 | AV96: =(AS96-AR96)+(AU96) -> 10000000 | AW96: =IF(OR(VALUE(AQ96)>0,VALUE(AV96)>0),"SIM","NÃO") -> SIM | AX96: =IF(AND(M96="NÃO DEPENDENTE",VALUE(AN96)>0),"VER CAPITAL","OK") -> VER CAPITAL | AY96: =IF(AND(AX96="VER CAPITAL",AW96="NÃO"),"INDÍCIO DE DEPENDÊNCIA POR CAPITAL","OK") -> OK | AZ96: =AC96*100/AE96 -> -449.83816
B97: GO | C97: Companhia de Desenvolvimento Econômico de Goiás | D97: CODEGO | E97: 01.285.170/0001-22 | F97: ATIVA | G97: DESENVOLVIMENTO REGIONAL | H97: SOCIEDADE DE ECONOMIA MISTA | I97: S.A. | J97: FECHADO | K97: NÃO | L97: NÃO | M97: NÃO DEPENDENTE | N97: 414 | O97: =IF(AND(F97="ATIVA",VALUE(N97)=0),"VERIFICAR","OK") -> OK | P97: SIM | Q97: SIM | R97: SIM | S97: https://www,codego,com,br/acesso-a-informacao/carta-anual-de-politicas-publicas-e-governanca-corporativa/ | T97: 68588577 | U97: 58285765 | V97: =IF(AND(VALUE(N97)=0,VALUE(U97)>0),"VERIFICAR","OK") -> OK | W97: 62508621 | X97: 0 | Y97: NÃO | Z97: 420000 | AA97: 0 | AB97: 132000 | AC97: -52937445 | AD97: =IF(AND(Y97="SIM",VALUE(AC97)<0),"VERIFICAR","OK") -> OK | AE97: 220753873 | AF97: 0 | AG97: 0 | AH97: 0 | AI97: 0 | AJ97: =IF(AND(M97="NÃO DEPENDENTE",VALUE(AI97)>0),"INDÍCIO DE DEPENDÊNCIA POR SUBVENÇÃO","OK") -> OK | AK97: 0 | AL97: 0 | AM97: 0 | AN97: 0 | AO97: 285854692 | AP97: 328022634 | AQ97: =AP97-AO97 -> 42167942 | AR97: 4.2044704e+08 | AS97: 481302976 | AT97: 0 | AU97: 0 | AV97: =(AS97-AR97)+(AU97) -> 60855938 | AW97: =IF(OR(VALUE(AQ97)>0,VALUE(AV97)>0),"SIM","NÃO") -> SIM | AX97: =IF(AND(M97="NÃO DEPENDENTE",VALUE(AN97)>0),"VER CAPITAL","OK") -> OK | AY97: =IF(AND(AX97="VER CAPITAL",AW97="NÃO"),"INDÍCIO DE DEPENDÊNCIA POR CAPITAL","OK") -> OK | AZ97: =AC97*100/AE97 -> -23.980302
B98: GO | C98: Firminópolis Transmissão S.A. | D98: FTSA | E98: 24.253.735/0001-95 | F98: ATIVA | G98: ENERGIA | H98: SOCIEDADE DE ECONOMIA MISTA | I98: S.A. | J98: FECHADO | K98: NÃO | L98: SIM | M98: NÃO DEPENDENTE | N98: 10 | O98: =IF(AND(F98="ATIVA",VALUE(N98)=0),"VERIFICAR","OK") -> OK | P98: NÃO | Q98: SIM | R98: NÃO | S98: https://ri,celgpar,com/BuscaPagina,aspx?ID={41799EC4-9CB4-4F81-BC75-64087B8BE678} | T98: 12136391 | U98: 1186958.8 | V98: =IF(AND(VALUE(N98)=0,VALUE(U98)>0),"VERIFICAR","OK") -> OK | W98: 5755733.5 | X98: 0 | Y98: NÃO | Z98: 156757.48 | AA98: 0 | AB98: 0 | AC98: 4756432.6 | AD98: =IF(AND(Y98="SIM",VALUE(AC98)<0),"VERIFICAR","OK") -> OK | AE98: 76628910 | AF98: 0 | AG98: 0 | AH98: 0 | AI98: 0 | AJ98: =IF(AND(M98="NÃO DEPENDENTE",VALUE(AI98)>0),"INDÍCIO DE DEPENDÊNCIA POR SUBVENÇÃO","OK") -> OK | AK98: 0 | AL98: 0 | AM98: 0 | AN98: 0 | AO98: 34696000 | AP98: 34696000 | AQ98: =AP98-AO98 -> 0 | AR98: 34696000 | AS98: 34696000 | AT98: 0 | AU98: 0 | AV98: =(AS98-AR98)+(AU98) -> 0 | AW98: =IF(OR(VALUE(AQ98)>0,VALUE(AV98)>0),"SIM","NÃO") -> NÃO | AX98: =IF(AND(M98="NÃO DEPENDENTE",VALUE(AN98)>0),"VER CAPITAL","OK") -> OK | AY98: =IF(AND(AX98="VER CAPITAL",AW98="NÃO"),"INDÍCIO DE DEPENDÊNCIA POR CAPITAL","OK") -> OK | AZ98: =AC98*100/AE98 -> 6.2070994
B99: GO | C99: Goiás Telecomunicções S/A | D99: GOIAS TELECOM | E99: 10.268.439/0001-53 | F99: ATIVA | G99: COMUNICAÇÃO | H99: SOCIEDADE DE ECONOMIA MISTA | I99: S.A. | J99: FECHADO | K99: NÃO | L99: NÃO | M99: DEPENDENTE | N99: 43 | O99: =IF(AND(F99="ATIVA",VALUE(N99)=0),"VERIFICAR","OK") -> OK | P99: SIM | Q99: SIM | R99: SIM | S99: https://goiastelecom,go,gov,br | T99: -112059.96 | U99: 5762687.9 | V99: =IF(AND(VALUE(N99)=0,VALUE(U99)>0),"VERIFICAR","OK") -> OK | W99: 6600428.4 | X99: 0 | Y99: NÃO | Z99: 509842.36 | AA99: 0 | AB99: 0 | AC99: 1310016 | AD99: =IF(AND(Y99="SIM",VALUE(AC99)<0),"VERIFICAR","OK") -> OK | AE99: 1972373.9 | AF99: 0 | AG99: 0 | AH99: 4558969.2 | AI99: 8094138.9 | AJ99: =IF(AND(M99="NÃO DEPENDENTE",VALUE(AI99)>0),"INDÍCIO DE DEPENDÊNCIA POR SUBVENÇÃO","OK") -> OK | AK99: 0 | AL99: 0 | AM99: 0 | AN99: 0 | AO99: 9000000 | AP99: 9000000 | AQ99: =AP99-AO99 -> 0 | AR99: 9000000 | AS99: 9000000 | AT99: 0 | AU99: 0 | AV99: =(AS99-AR99)+(AU99) -> 0 | AW99: =IF(OR(VALUE(AQ99)>0,VALUE(AV99)>0),"SIM","NÃO") -> NÃO | AX99: =IF(AND(M99="NÃO DEPENDENTE",VALUE(AN99)>0),"VER CAPITAL","OK") -> OK | AY99: =IF(AND(AX99="VER CAPITAL",AW99="NÃO"),"INDÍCIO DE DEPENDÊNCIA POR CAPITAL","OK") -> OK | AZ99: =AC99*100/AE99 -> 66.41824
B100: GO | C100: Agência de Fomento de Goiás S/A | D100: GOIASFOMENTO | E100: 03.918.382/0001-25 | F100: ATIVA | G100: FINANCEIRO | H100: SOCIEDADE DE ECONOMIA MISTA | I100: S.A. | J100: FECHADO | K100: NÃO | L100: NÃO | M100: NÃO DEPENDENTE | N100: 138 | O100: =IF(AND(F100="ATIVA",VALUE(N100)=0),"VERIFICAR","OK") -> OK | P100: SIM | Q100: SIM | R100: NÃO | S100: https://www,goiasfomento,com/wp-content/uploads/2024/06/Carta-Anual-de-Politicas-Publicas-e-Governanca-Corporativa-2024-Ano-Base-2023-Final,pdf | T100: 67149142 | U100: 34912881 | V100: =IF(AND(VALUE(N100)=0,VALUE(U100)>0),"VERIFICAR","OK") -> OK | W100: 63689614 | X100: 0 | Y100: SIM | Z100: 448712.5 | AA100: 6090.93 | AB100: 0 | AC100: 3573169.6 | AD100: =IF(AND(Y100="SIM",VALUE(AC100)<0),"VERIFICAR","OK") -> OK | AE100: 2.0275307e+08 | AF100: 0 | AG100: 0 | AH100: 0 | AI100: 0 | AJ100: =IF(AND(M100="NÃO DEPENDENTE",VALUE(AI100)>0),"INDÍCIO DE DEPENDÊNCIA POR SUBVENÇÃO","OK") -> OK | AK100: 0 | AL100: 0 | AM100: 0 | AN100: 0 | AO100: 186394380 | AP100: 193195396 | AQ100: =AP100-AO100 -> 6801016 | AR100: 1.8639438e+08 | AS100: 1.931954e+08 | AT100: 3199176.4 | AU100: 0 | AV100: =(AS100-AR100)+(AU100) -> 6801016.5 | AW100: =IF(OR(VALUE(AQ100)>0,VALUE(AV100)>0),"SIM","NÃO") -> SIM | AX100: =IF(AND(M100="NÃO DEPENDENTE",VALUE(AN100)>0),"VER CAPITAL","OK") -> OK | AY100: =IF(AND(AX100="VER CAPITAL",AW100="NÃO"),"INDÍCIO DE DEPENDÊNCIA POR CAPITAL","OK") -> OK | AZ100: =AC100*100/AE100 -> 1.7623257
...

Sheet ex2023
